Workbook

Sheet Tópicos
A1: Tópicos do curso — numeração baseada nas listas
A3: Código | B3: Tópico | C3: Categoria | E3: Rótulo completo
A4: 01 | B4: Contas Nacionais | C4: Lista | E4: 01 — Contas Nacionais
A5: 02 | B5: Balanço de Pagamentos | C5: Lista | E5: 02 — Balanço de Pagamentos
A6: 03 | B6: Sistema Monetário | C6: Lista | E6: 03 — Sistema Monetário
A7: 04 | B7: Demanda por Moeda | C7: Lista | E7: 04 — Demanda por Moeda
A8: 05 | B8: IS-LM | C8: Lista | E8: 05 — IS-LM
A9: 06 | B9: IS-LM-BP | C9: Lista | E9: 06 — IS-LM-BP
A10: 07a | B10: Paridades | C10: Lista | E10: 07a — Paridades
A11: 07b | B11: OA-DA | C11: Lista | E11: 07b — OA-DA
A12: 08 | B12: Curva de Phillips | C12: Lista | E12: 08 — Curva de Phillips
A13: 09 | B13: Expectativas, Novos Clássicos e Novos Keynesianos | C13: Lista | E13: 09 — Expectativas, Novos Clássicos e Novos Keynesianos
A14: 10 | B14: Ciclos Reais de Negócios (RBC) | C14: Lista | E14: 10 — Ciclos Reais de Negócios (RBC)
... A20: E2 | B20: Demanda de Bens e Complementaridade | C20: Extra | E20: E2 — Demanda de Bens e Complementaridade
A25: Taxonomia atualizada: 07a separa Paridades; 07b separa OA-DA. E1, E2, E3 e E5 foram incorporados conforme a metodologia.

Sheet Matriz
A1: Quantidade de itens equivalentes por tópico e prova — ANPEC Macro 2010–2026
A2: Levantamento item a item concluído: 17 provas, 2010–2026. Valores em itens equivalentes; confira a aba Validação.
A3: Tópico | B3: 2010 | C3: 2011 | D3: 2012 | E3: 2013 | F3: 2014 | G3: 2015 | H3: 2016 | I3: 2017 | J3: 2018 | K3: 2019 | L3: 2020 | M3: 2021 | N3: 2022 | O3: 2023 | P3: 2024 | Q3: 2025 | R3: 2026 | S3: Total
A4: 01 — Contas Nacionais | B4: =SUMIFS(Base_Itens!$I$5:$I$1504,Base_Itens!$A$5:$A$1504,B$3,Base_Itens!$G$5:$G$1504,$A4) -> 10 | C4: =SUMIFS(Base_Itens!$I$5:$I$1504,Base_Itens!$A$5:$A$1504,C$3,Base_Itens!$G$5:$G$1504,$A4) -> 5 | D4: =SUMIFS(Base_Itens!$I$5:$I$1504,Base_Itens!$A$5:$A$1504,D$3,Base_Itens!$G$5:$G$1504,$A4) -> 1 | E4: =SUMIFS(Base_Itens!$I$5:$I$1504,Base_Itens!$A$5:$A$1504,E$3,Base_Itens!$G$5:$G$1504,$A4) -> 7.5 | F4: =SUMIFS(Base_Itens!$I$5:$I$1504,Base_Itens!$A$5:$A$1504,F$3,Base_Itens!$G$5:$G$1504,$A4) -> 4 | G4: =SUMIFS(Base_Itens!$I$5:$I$1504,Base_Itens!$A$5:$A$1504,G$3,Base_Itens!$G$5:$G$1504,$A4) -> 5 | H4: =SUMIFS(Base_Itens!$I$5:$I$1504,Base_Itens!$A$5:$A$1504,H$3,Base_Itens!$G$5:$G$1504,$A4) -> 4 | I4: =SUMIFS(Base_Itens!$I$5:$I$1504,Base_Itens!$A$5:$A$1504,I$3,Base_Itens!$G$5:$G$1504,$A4) -> 8 | ... R4: =SUMIFS(Base_Itens!$I$5:$I$1504,Base_Itens!$A$5:$A$1504,R$3,Base_Itens!$G$5:$G$1504,$A4) -> 4 | S4: =SUM(B4:R4) -> 87.5
A5: 02 — Balanço de Pagamentos | B5: =SUMIFS(Base_Itens!$I$5:$I$1504,Base_Itens!$A$5:$A$1504,B$3,Base_Itens!$G$5:$G$1504,$A5) -> 0 | C5: =SUMIFS(Base_Itens!$I$5:$I$1504,Base_Itens!$A$5:$A$1504,C$3,Base_Itens!$G$5:$G$1504,$A5) -> 5 | D5: =SUMIFS(Base_Itens!$I$5:$I$1504,Base_Itens!$A$5:$A$1504,D$3,Base_Itens!$G$5:$G$1504,$A5) -> 4 | E5: =SUMIFS(Base_Itens!$I$5:$I$1504,Base_Itens!$A$5:$A$1504,E$3,Base_Itens!$G$5:$G$1504,$A5) -> 4.5 | F5: =SUMIFS(Base_Itens!$I$5:$I$1504,Base_Itens!$A$5:$A$1504,F$3,Base_Itens!$G$5:$G$1504,$A5) -> 1 | G5: =SUMIFS(Base_Itens!$I$5:$I$1504,Base_Itens!$A$5:$A$1504,G$3,Base_Itens!$G$5:$G$1504,$A5) -> 6 | H5: =SUMIFS(Base_Itens!$I$5:$I$1504,Base_Itens!$A$5:$A$1504,H$3,Base_Itens!$G$5:$G$1504,$A5) -> 5 | I5: =SUMIFS(Base_Itens!$I$5:$I$1504,Base_Itens!$A$5:$A$1504,I$3,Base_Itens!$G$5:$G$1504,$A5) -> 2 | ... R5: =SUMIFS(Base_Itens!$I$5:$I$1504,Base_Itens!$A$5:$A$1504,R$3,Base_Itens!$G$5:$G$1504,$A5) -> 5 | S5: =SUM(B5:R5) -> 61.5
A6: 03 — Sistema Monetário | B6: =SUMIFS(Base_Itens!$I$5:$I$1504,Base_Itens!$A$5:$A$1504,B$3,Base_Itens!$G$5:$G$1504,$A6) -> 7.6666667 | C6: =SUMIFS(Base_Itens!$I$5:$I$1504,Base_Itens!$A$5:$A$1504,C$3,Base_Itens!$G$5:$G$1504,$A6) -> 5 | D6: =SUMIFS(Base_Itens!$I$5:$I$1504,Base_Itens!$A$5:$A$1504,D$3,Base_Itens!$G$5:$G$1504,$A6) -> 8 | E6: =SUMIFS(Base_Itens!$I$5:$I$1504,Base_Itens!$A$5:$A$1504,E$3,Base_Itens!$G$5:$G$1504,$A6) -> 4 | F6: =SUMIFS(Base_Itens!$I$5:$I$1504,Base_Itens!$A$5:$A$1504,F$3,Base_Itens!$G$5:$G$1504,$A6) -> 4 | G6: =SUMIFS(Base_Itens!$I$5:$I$1504,Base_Itens!$A$5:$A$1504,G$3,Base_Itens!$G$5:$G$1504,$A6) -> 2 | H6: =SUMIFS(Base_Itens!$I$5:$I$1504,Base_Itens!$A$5:$A$1504,H$3,Base_Itens!$G$5:$G$1504,$A6) -> 5 | I6: =SUMIFS(Base_Itens!$I$5:$I$1504,Base_Itens!$A$5:$A$1504,I$3,Base_Itens!$G$5:$G$1504,$A6) -> 6 | ... R6: =SUMIFS(Base_Itens!$I$5:$I$1504,Base_Itens!$A$5:$A$1504,R$3,Base_Itens!$G$5:$G$1504,$A6) -> 2.5 | S6: =SUM(B6:R6) -> 69.666667
A7: 04 — Demanda por Moeda | B7: =SUMIFS(Base_Itens!$I$5:$I$1504,Base_Itens!$A$5:$A$1504,B$3,Base_Itens!$G$5:$G$1504,$A7) -> 2.1666667 | C7: =SUMIFS(Base_Itens!$I$5:$I$1504,Base_Itens!$A$5:$A$1504,C$3,Base_Itens!$G$5:$G$1504,$A7) -> 3 | D7: =SUMIFS(Base_Itens!$I$5:$I$1504,Base_Itens!$A$5:$A$1504,D$3,Base_Itens!$G$5:$G$1504,$A7) -> 5 | E7: =SUMIFS(Base_Itens!$I$5:$I$1504,Base_Itens!$A$5:$A$1504,E$3,Base_Itens!$G$5:$G$1504,$A7) -> 4 | F7: =SUMIFS(Base_Itens!$I$5:$I$1504,Base_Itens!$A$5:$A$1504,F$3,Base_Itens!$G$5:$G$1504,$A7) -> 2 | G7: =SUMIFS(Base_Itens!$I$5:$I$1504,Base_Itens!$A$5:$A$1504,G$3,Base_Itens!$G$5:$G$1504,$A7) -> 3 | H7: =SUMIFS(Base_Itens!$I$5:$I$1504,Base_Itens!$A$5:$A$1504,H$3,Base_Itens!$G$5:$G$1504,$A7) -> 1 | I7: =SUMIFS(Base_Itens!$I$5:$I$1504,Base_Itens!$A$5:$A$1504,I$3,Base_Itens!$G$5:$G$1504,$A7) -> 0 | ... R7: =SUMIFS(Base_Itens!$I$5:$I$1504,Base_Itens!$A$5:$A$1504,R$3,Base_Itens!$G$5:$G$1504,$A7) -> 2.5 | S7: =SUM(B7:R7) -> 40.666667
A8: 05 — IS-LM | B8: =SUMIFS(Base_Itens!$I$5:$I$1504,Base_Itens!$A$5:$A$1504,B$3,Base_Itens!$G$5:$G$1504,$A8) -> 9 | C8: =SUMIFS(Base_Itens!$I$5:$I$1504,Base_Itens!$A$5:$A$1504,C$3,Base_Itens!$G$5:$G$1504,$A8) -> 10 | D8: =SUMIFS(Base_Itens!$I$5:$I$1504,Base_Itens!$A$5:$A$1504,D$3,Base_Itens!$G$5:$G$1504,$A8) -> 5 | E8: =SUMIFS(Base_Itens!$I$5:$I$1504,Base_Itens!$A$5:$A$1504,E$3,Base_Itens!$G$5:$G$1504,$A8) -> 5 | F8: =SUMIFS(Base_Itens!$I$5:$I$1504,Base_Itens!$A$5:$A$1504,F$3,Base_Itens!$G$5:$G$1504,$A8) -> 4 | G8: =SUMIFS(Base_Itens!$I$5:$I$1504,Base_Itens!$A$5:$A$1504,G$3,Base_Itens!$G$5:$G$1504,$A8) -> 6.5 | H8: =SUMIFS(Base_Itens!$I$5:$I$1504,Base_Itens!$A$5:$A$1504,H$3,Base_Itens!$G$5:$G$1504,$A8) -> 8 | I8: =SUMIFS(Base_Itens!$I$5:$I$1504,Base_Itens!$A$5:$A$1504,I$3,Base_Itens!$G$5:$G$1504,$A8) -> 5 | ... R8: =SUMIFS(Base_Itens!$I$5:$I$1504,Base_Itens!$A$5:$A$1504,R$3,Base_Itens!$G$5:$G$1504,$A8) -> 2.5 | S8: =SUM(B8:R8) -> 74.5
A9: 06 — IS-LM-BP | B9: =SUMIFS(Base_Itens!$I$5:$I$1504,Base_Itens!$A$5:$A$1504,B$3,Base_Itens!$G$5:$G$1504,$A9) -> 7 | C9: =SUMIFS(Base_Itens!$I$5:$I$1504,Base_Itens!$A$5:$A$1504,C$3,Base_Itens!$G$5:$G$1504,$A9) -> 5 | D9: =SUMIFS(Base_Itens!$I$5:$I$1504,Base_Itens!$A$5:$A$1504,D$3,Base_Itens!$G$5:$G$1504,$A9) -> 15 | E9: =SUMIFS(Base_Itens!$I$5:$I$1504,Base_Itens!$A$5:$A$1504,E$3,Base_Itens!$G$5:$G$1504,$A9) -> 5 | F9: =SUMIFS(Base_Itens!$I$5:$I$1504,Base_Itens!$A$5:$A$1504,F$3,Base_Itens!$G$5:$G$1504,$A9) -> 6 | G9: =SUMIFS(Base_Itens!$I$5:$I$1504,Base_Itens!$A$5:$A$1504,G$3,Base_Itens!$G$5:$G$1504,$A9) -> 5 | H9: =SUMIFS(Base_Itens!$I$5:$I$1504,Base_Itens!$A$5:$A$1504,H$3,Base_Itens!$G$5:$G$1504,$A9) -> 4.5 | I9: =SUMIFS(Base_Itens!$I$5:$I$1504,Base_Itens!$A$5:$A$1504,I$3,Base_Itens!$G$5:$G$1504,$A9) -> 10 | ... R9: =SUMIFS(Base_Itens!$I$5:$I$1504,Base_Itens!$A$5:$A$1504,R$3,Base_Itens!$G$5:$G$1504,$A9) -> 0 | S9: =SUM(B9:R9) -> 119.5
A10: 07a — Paridades | B10: =SUMIFS(Base_Itens!$I$5:$I$1504,Base_Itens!$A$5:$A$1504,B$3,Base_Itens!$G$5:$G$1504,$A10) -> 7.5 | C10: =SUMIFS(Base_Itens!$I$5:$I$1504,Base_Itens!$A$5:$A$1504,C$3,Base_Itens!$G$5:$G$1504,$A10) -> 5 | D10: =SUMIFS(Base_Itens!$I$5:$I$1504,Base_Itens!$A$5:$A$1504,D$3,Base_Itens!$G$5:$G$1504,$A10) -> 4 | E10: =SUMIFS(Base_Itens!$I$5:$I$1504,Base_Itens!$A$5:$A$1504,E$3,Base_Itens!$G$5:$G$1504,$A10) -> 11 | F10: =SUMIFS(Base_Itens!$I$5:$I$1504,Base_Itens!$A$5:$A$1504,F$3,Base_Itens!$G$5:$G$1504,$A10) -> 7 | G10: =SUMIFS(Base_Itens!$I$5:$I$1504,Base_Itens!$A$5:$A$1504,G$3,Base_Itens!$G$5:$G$1504,$A10) -> 6 | H10: =SUMIFS(Base_Itens!$I$5:$I$1504,Base_Itens!$A$5:$A$1504,H$3,Base_Itens!$G$5:$G$1504,$A10) -> 5.5 | I10: =SUMIFS(Base_Itens!$I$5:$I$1504,Base_Itens!$A$5:$A$1504,I$3,Base_Itens!$G$5:$G$1504,$A10) -> 0 | ... R10: =SUMIFS(Base_Itens!$I$5:$I$1504,Base_Itens!$A$5:$A$1504,R$3,Base_Itens!$G$5:$G$1504,$A10) -> 5 | S10: =SUM(B10:R10) -> 127
A11: 07b — OA-DA | B11: =SUMIFS(Base_Itens!$I$5:$I$1504,Base_Itens!$A$5:$A$1504,B$3,Base_Itens!$G$5:$G$1504,$A11) -> 2.5 | C11: =SUMIFS(Base_Itens!$I$5:$I$1504,Base_Itens!$A$5:$A$1504,C$3,Base_Itens!$G$5:$G$1504,$A11) -> 1 | D11: =SUMIFS(Base_Itens!$I$5:$I$1504,Base_Itens!$A$5:$A$1504,D$3,Base_Itens!$G$5:$G$1504,$A11) -> 1 | E11: =SUMIFS(Base_Itens!$I$5:$I$1504,Base_Itens!$A$5:$A$1504,E$3,Base_Itens!$G$5:$G$1504,$A11) -> 1 | F11: =SUMIFS(Base_Itens!$I$5:$I$1504,Base_Itens!$A$5:$A$1504,F$3,Base_Itens!$G$5:$G$1504,$A11) -> 1 | G11: =SUMIFS(Base_Itens!$I$5:$I$1504,Base_Itens!$A$5:$A$1504,G$3,Base_Itens!$G$5:$G$1504,$A11) -> 0 | H11: =SUMIFS(Base_Itens!$I$5:$I$1504,Base_Itens!$A$5:$A$1504,H$3,Base_Itens!$G$5:$G$1504,$A11) -> 4.5 | I11: =SUMIFS(Base_Itens!$I$5:$I$1504,Base_Itens!$A$5:$A$1504,I$3,Base_Itens!$G$5:$G$1504,$A11) -> 0.5 | ... R11: =SUMIFS(Base_Itens!$I$5:$I$1504,Base_Itens!$A$5:$A$1504,R$3,Base_Itens!$G$5:$G$1504,$A11) -> 2 | S11: =SUM(B11:R11) -> 35
A12: 08 — Curva de Phillips | B12: =SUMIFS(Base_Itens!$I$5:$I$1504,Base_Itens!$A$5:$A$1504,B$3,Base_Itens!$G$5:$G$1504,$A12) -> 7.5 | C12: =SUMIFS(Base_Itens!$I$5:$I$1504,Base_Itens!$A$5:$A$1504,C$3,Base_Itens!$G$5:$G$1504,$A12) -> 4 | D12: =SUMIFS(Base_Itens!$I$5:$I$1504,Base_Itens!$A$5:$A$1504,D$3,Base_Itens!$G$5:$G$1504,$A12) -> 5.5 | E12: =SUMIFS(Base_Itens!$I$5:$I$1504,Base_Itens!$A$5:$A$1504,E$3,Base_Itens!$G$5:$G$1504,$A12) -> 1 | F12: =SUMIFS(Base_Itens!$I$5:$I$1504,Base_Itens!$A$5:$A$1504,F$3,Base_Itens!$G$5:$G$1504,$A12) -> 7 | G12: =SUMIFS(Base_Itens!$I$5:$I$1504,Base_Itens!$A$5:$A$1504,G$3,Base_Itens!$G$5:$G$1504,$A12) -> 5 | H12: =SUMIFS(Base_Itens!$I$5:$I$1504,Base_Itens!$A$5:$A$1504,H$3,Base_Itens!$G$5:$G$1504,$A12) -> 3.5 | I12: =SUMIFS(Base_Itens!$I$5:$I$1504,Base_Itens!$A$5:$A$1504,I$3,Base_Itens!$G$5:$G$1504,$A12) -> 6.5 | ... R12: =SUMIFS(Base_Itens!$I$5:$I$1504,Base_Itens!$A$5:$A$1504,R$3,Base_Itens!$G$5:$G$1504,$A12) -> 1.5 | S12: =SUM(B12:R12) -> 81.5
A13: 09 — Expectativas, Novos Clássicos e Novos Keynesianos | B13: =SUMIFS(Base_Itens!$I$5:$I$1504,Base_Itens!$A$5:$A$1504,B$3,Base_Itens!$G$5:$G$1504,$A13) -> 6 | C13: =SUMIFS(Base_Itens!$I$5:$I$1504,Base_Itens!$A$5:$A$1504,C$3,Base_Itens!$G$5:$G$1504,$A13) -> 2 | D13: =SUMIFS(Base_Itens!$I$5:$I$1504,Base_Itens!$A$5:$A$1504,D$3,Base_Itens!$G$5:$G$1504,$A13) -> 9.5 | E13: =SUMIFS(Base_Itens!$I$5:$I$1504,Base_Itens!$A$5:$A$1504,E$3,Base_Itens!$G$5:$G$1504,$A13) -> 6 | F13: =SUMIFS(Base_Itens!$I$5:$I$1504,Base_Itens!$A$5:$A$1504,F$3,Base_Itens!$G$5:$G$1504,$A13) -> 14.5 | G13: =SUMIFS(Base_Itens!$I$5:$I$1504,Base_Itens!$A$5:$A$1504,G$3,Base_Itens!$G$5:$G$1504,$A13) -> 13.5 | H13: =SUMIFS(Base_Itens!$I$5:$I$1504,Base_Itens!$A$5:$A$1504,H$3,Base_Itens!$G$5:$G$1504,$A13) -> 5 | I13: =SUMIFS(Base_Itens!$I$5:$I$1504,Base_Itens!$A$5:$A$1504,I$3,Base_Itens!$G$5:$G$1504,$A13) -> 7 | ... R13: =SUMIFS(Base_Itens!$I$5:$I$1504,Base_Itens!$A$5:$A$1504,R$3,Base_Itens!$G$5:$G$1504,$A13) -> 12 | S13: =SUM(B13:R13) -> 144
A14: 10 — Ciclos Reais de Negócios (RBC) | B14: =SUMIFS(Base_Itens!$I$5:$I$1504,Base_Itens!$A$5:$A$1504,B$3,Base_Itens!$G$5:$G$1504,$A14) -> 1 | C14: =SUMIFS(Base_Itens!$I$5:$I$1504,Base_Itens!$A$5:$A$1504,C$3,Base_Itens!$G$5:$G$1504,$A14) -> 5 | D14: =SUMIFS(Base_Itens!$I$5:$I$1504,Base_Itens!$A$5:$A$1504,D$3,Base_Itens!$G$5:$G$1504,$A14) -> 0 | E14: =SUMIFS(Base_Itens!$I$5:$I$1504,Base_Itens!$A$5:$A$1504,E$3,Base_Itens!$G$5:$G$1504,$A14) -> 3 | F14: =SUMIFS(Base_Itens!$I$5:$I$1504,Base_Itens!$A$5:$A$1504,F$3,Base_Itens!$G$5:$G$1504,$A14) -> 0.5 | G14: =SUMIFS(Base_Itens!$I$5:$I$1504,Base_Itens!$A$5:$A$1504,G$3,Base_Itens!$G$5:$G$1504,$A14) -> 2 | H14: =SUMIFS(Base_Itens!$I$5:$I$1504,Base_Itens!$A$5:$A$1504,H$3,Base_Itens!$G$5:$G$1504,$A14) -> 2 | I14: =SUMIFS(Base_Itens!$I$5:$I$1504,Base_Itens!$A$5:$A$1504,I$3,Base_Itens!$G$5:$G$1504,$A14) -> 3 | ... R14: =SUMIFS(Base_Itens!$I$5:$I$1504,Base_Itens!$A$5:$A$1504,R$3,Base_Itens!$G$5:$G$1504,$A14) -> 1 | S14: =SUM(B14:R14) -> 22.5
A15: 11 — Crescimento Econômico | B15: =SUMIFS(Base_Itens!$I$5:$I$1504,Base_Itens!$A$5:$A$1504,B$3,Base_Itens!$G$5:$G$1504,$A15) -> 10 | C15: =SUMIFS(Base_Itens!$I$5:$I$1504,Base_Itens!$A$5:$A$1504,C$3,Base_Itens!$G$5:$G$1504,$A15) -> 10 | D15: =SUMIFS(Base_Itens!$I$5:$I$1504,Base_Itens!$A$5:$A$1504,D$3,Base_Itens!$G$5:$G$1504,$A15) -> 10 | E15: =SUMIFS(Base_Itens!$I$5:$I$1504,Base_Itens!$A$5:$A$1504,E$3,Base_Itens!$G$5:$G$1504,$A15) -> 10 | F15: =SUMIFS(Base_Itens!$I$5:$I$1504,Base_Itens!$A$5:$A$1504,F$3,Base_Itens!$G$5:$G$1504,$A15) -> 10 | G15: =SUMIFS(Base_Itens!$I$5:$I$1504,Base_Itens!$A$5:$A$1504,G$3,Base_Itens!$G$5:$G$1504,$A15) -> 10 | H15: =SUMIFS(Base_Itens!$I$5:$I$1504,Base_Itens!$A$5:$A$1504,H$3,Base_Itens!$G$5:$G$1504,$A15) -> 15 | I15: =SUMIFS(Base_Itens!$I$5:$I$1504,Base_Itens!$A$5:$A$1504,I$3,Base_Itens!$G$5:$G$1504,$A15) -> 10 | ... R15: =SUMIFS(Base_Itens!$I$5:$I$1504,Base_Itens!$A$5:$A$1504,R$3,Base_Itens!$G$5:$G$1504,$A15) -> 5 | S15: =SUM(B15:R15) -> 155
... A20: E2 — Demanda de Bens e Complementaridade | B20: =SUMIFS(Base_Itens!$I$5:$I$1504,Base_Itens!$A$5:$A$1504,B$3,Base_Itens!$G$5:$G$1504,$A20) -> 0 | C20: =SUMIFS(Base_Itens!$I$5:$I$1504,Base_Itens!$A$5:$A$1504,C$3,Base_Itens!$G$5:$G$1504,$A20) -> 0 | D20: =SUMIFS(Base_Itens!$I$5:$I$1504,Base_Itens!$A$5:$A$1504,D$3,Base_Itens!$G$5:$G$1504,$A20) -> 0 | E20: =SUMIFS(Base_Itens!$I$5:$I$1504,Base_Itens!$A$5:$A$1504,E$3,Base_Itens!$G$5:$G$1504,$A20) -> 0 | F20: =SUMIFS(Base_Itens!$I$5:$I$1504,Base_Itens!$A$5:$A$1504,F$3,Base_Itens!$G$5:$G$1504,$A20) -> 0 | G20: =SUMIFS(Base_Itens!$I$5:$I$1504,Base_Itens!$A$5:$A$1504,G$3,Base_Itens!$G$5:$G$1504,$A20) -> 0 | H20: =SUMIFS(Base_Itens!$I$5:$I$1504,Base_Itens!$A$5:$A$1504,H$3,Base_Itens!$G$5:$G$1504,$A20) -> 0 | I20: =SUMIFS(Base_Itens!$I$5:$I$1504,Base_Itens!$A$5:$A$1504,I$3,Base_Itens!$G$5:$G$1504,$A20) -> 0 | ... R20: =SUMIFS(Base_Itens!$I$5:$I$1504,Base_Itens!$A$5:$A$1504,R$3,Base_Itens!$G$5:$G$1504,$A20) -> 0 | S20: =SUM(B20:R20) -> 1
A25: TOTAL POR PROVA | B25: =SUM(B4:B20) -> 75 | C25: =SUM(C4:C20) -> 75 | D25: =SUM(D4:D20) -> 75 | E25: =SUM(E4:E20) -> 75 | F25: =SUM(F4:F20) -> 75 | G25: =SUM(G4:G20) -> 75 | H25: =SUM(H4:H20) -> 75 | I25: =SUM(I4:I20) -> 75 | ... S25: =SUM(S4:S20) -> 1200

Sheet Dashboard
A1: Dashboard — incidência de tópicos nas provas de Macroeconomia da ANPEC
A3: Ano selecionado | B3: 2026 | E3: Altere B3 para filtrar o gráfico de barras por ano. A Base_Itens alimenta automaticamente a matriz e os dois gráficos.
U5: Ano | V5: 01 — Contas Nacionais | W5: 02 — Balanço de Pagamentos | X5: 03 — Sistema Monetário | Y5: 04 — Demanda por Moeda | Z5: 05 — IS-LM | AA5: 06 — IS-LM-BP | AB5: 07a — Paridades | AC5: 07b — OA-DA | AD5: 08 — Curva de Phillips | AE5: 09 — Expectativas, Novos Clássicos e Novos Keynesianos | AF5: 10 — Ciclos Reais de Negócios (RBC) | AG5: 11 — Crescimento Econômico | AH5: 12 — Consumo | AI5: 13 — Investimento | AJ5: 14 — Dívida Pública e Senhoriagem | AK5: E1 — Mercados Financeiros | AL5: E2 — Demanda de Bens e Complementaridade | AM5: =Tópicos!E21 -> 0 | AN5: =Tópicos!E22 -> 0 | AO5: =Tópicos!E23 -> 0
A6: Tópico | B6: Quantidade | C6: (%) | U6: 2010 | V6: =IF($B$32="Sim",INDEX(Matriz!$B$4:$R$4,1,MATCH($U6,Matriz!$B$3:$R$3,0)),NA()) -> #N/A | W6: =IF($B$33="Sim",INDEX(Matriz!$B$5:$R$5,1,MATCH($U6,Matriz!$B$3:$R$3,0)),NA()) -> #N/A | X6: =IF($B$34="Sim",INDEX(Matriz!$B$6:$R$6,1,MATCH($U6,Matriz!$B$3:$R$3,0)),NA()) -> #N/A | Y6: =IF($B$35="Sim",INDEX(Matriz!$B$7:$R$7,1,MATCH($U6,Matriz!$B$3:$R$3,0)),NA()) -> #N/A | Z6: =IF($B$36="Sim",INDEX(Matriz!$B$8:$R$8,1,MATCH($U6,Matriz!$B$3:$R$3,0)),NA()) -> #N/A | AA6: =IF($B$37="Sim",INDEX(Matriz!$B$9:$R$9,1,MATCH($U6,Matriz!$B$3:$R$3,0)),NA()) -> 7 | AB6: =IF($B$38="Sim",INDEX(Matriz!$B$10:$R$10,1,MATCH($U6,Matriz!$B$3:$R$3,0)),NA()) -> #N/A | AC6: =IF($B$39="Sim",INDEX(Matriz!$B$11:$R$11,1,MATCH($U6,Matriz!$B$3:$R$3,0)),NA()) -> #N/A | AD6: =IF($B$40="Sim",INDEX(Matriz!$B$12:$R$12,1,MATCH($U6,Matriz!$B$3:$R$3,0)),NA()) -> #N/A | AE6: =IF($B$41="Sim",INDEX(Matriz!$B$13:$R$13,1,MATCH($U6,Matriz!$B$3:$R$3,0)),NA()) -> #N/A | AF6: =IF($B$42="Sim",INDEX(Matriz!$B$14:$R$14,1,MATCH($U6,Matriz!$B$3:$R$3,0)),NA()) -> #N/A | AG6: =IF($B$43="Sim",INDEX(Matriz!$B$15:$R$15,1,MATCH($U6,Matriz!$B$3:$R$3,0)),NA()) -> #N/A | AH6: =IF($B$44="Sim",INDEX(Matriz!$B$16:$R$16,1,MATCH($U6,Matriz!$B$3:$R$3,0)),NA()) -> #N/A | AI6: =IF($B$45="Sim",INDEX(Matriz!$B$17:$R$17,1,MATCH($U6,Matriz!$B$3:$R$3,0)),NA()) -> #N/A | AJ6: =IF($B$46="Sim",INDEX(Matriz!$B$18:$R$18,1,MATCH($U6,Matriz!$B$3:$R$3,0)),NA()) -> #N/A | AK6: =IF($B$47="Sim",INDEX(Matriz!$B$19:$R$19,1,MATCH($U6,Matriz!$B$3:$R$3,0)),NA()) -> #N/A | AL6: =IF($B$48="Sim",INDEX(Matriz!$B$20:$R$20,1,MATCH($U6,Matriz!$B$3:$R$3,0)),NA()) -> #N/A | AM6: =INDEX(Matriz!$B$21:$R$21,1,MATCH($U6,Matriz!$B$3:$R$3,0)) -> 0 | AN6: =INDEX(Matriz!$B$22:$R$22,1,MATCH($U6,Matriz!$B$3:$R$3,0)) -> 0 | AO6: =INDEX(Matriz!$B$23:$R$23,1,MATCH($U6,Matriz!$B$3:$R$3,0)) -> 0
A7: 01 — Contas Nacionais | B7: =INDEX(Matriz!$B$4:$R$4,1,MATCH(VALUE($B$3),Matriz!$B$3:$R$3,0)) -> 4 | C7: =B7/SUM($B$7:$B$23) -> 0.08 | U7: 2011 | V7: =IF($B$32="Sim",INDEX(Matriz!$B$4:$R$4,1,MATCH($U7,Matriz!$B$3:$R$3,0)),NA()) -> #N/A | W7: =IF($B$33="Sim",INDEX(Matriz!$B$5:$R$5,1,MATCH($U7,Matriz!$B$3:$R$3,0)),NA()) -> #N/A | X7: =IF($B$34="Sim",INDEX(Matriz!$B$6:$R$6,1,MATCH($U7,Matriz!$B$3:$R$3,0)),NA()) -> #N/A | Y7: =IF($B$35="Sim",INDEX(Matriz!$B$7:$R$7,1,MATCH($U7,Matriz!$B$3:$R$3,0)),NA()) -> #N/A | Z7: =IF($B$36="Sim",INDEX(Matriz!$B$8:$R$8,1,MATCH($U7,Matriz!$B$3:$R$3,0)),NA()) -> #N/A | AA7: =IF($B$37="Sim",INDEX(Matriz!$B$9:$R$9,1,MATCH($U7,Matriz!$B$3:$R$3,0)),NA()) -> 5 | AB7: =IF($B$38="Sim",INDEX(Matriz!$B$10:$R$10,1,MATCH($U7,Matriz!$B$3:$R$3,0)),NA()) -> #N/A | AC7: =IF($B$39="Sim",INDEX(Matriz!$B$11:$R$11,1,MATCH($U7,Matriz!$B$3:$R$3,0)),NA()) -> #N/A | AD7: =IF($B$40="Sim",INDEX(Matriz!$B$12:$R$12,1,MATCH($U7,Matriz!$B$3:$R$3,0)),NA()) -> #N/A | AE7: =IF($B$41="Sim",INDEX(Matriz!$B$13:$R$13,1,MATCH($U7,Matriz!$B$3:$R$3,0)),NA()) -> #N/A | AF7: =IF($B$42="Sim",INDEX(Matriz!$B$14:$R$14,1,MATCH($U7,Matriz!$B$3:$R$3,0)),NA()) -> #N/A | AG7: =IF($B$43="Sim",INDEX(Matriz!$B$15:$R$15,1,MATCH($U7,Matriz!$B$3:$R$3,0)),NA()) -> #N/A | AH7: =IF($B$44="Sim",INDEX(Matriz!$B$16:$R$16,1,MATCH($U7,Matriz!$B$3:$R$3,0)),NA()) -> #N/A | AI7: =IF($B$45="Sim",INDEX(Matriz!$B$17:$R$17,1,MATCH($U7,Matriz!$B$3:$R$3,0)),NA()) -> #N/A | AJ7: =IF($B$46="Sim",INDEX(Matriz!$B$18:$R$18,1,MATCH($U7,Matriz!$B$3:$R$3,0)),NA()) -> #N/A | AK7: =IF($B$47="Sim",INDEX(Matriz!$B$19:$R$19,1,MATCH($U7,Matriz!$B$3:$R$3,0)),NA()) -> #N/A | AL7: =IF($B$48="Sim",INDEX(Matriz!$B$20:$R$20,1,MATCH($U7,Matriz!$B$3:$R$3,0)),NA()) -> #N/A | AM7: =INDEX(Matriz!$B$21:$R$21,1,MATCH($U7,Matriz!$B$3:$R$3,0)) -> 0 | AN7: =INDEX(Matriz!$B$22:$R$22,1,MATCH($U7,Matriz!$B$3:$R$3,0)) -> 0 | AO7: =INDEX(Matriz!$B$23:$R$23,1,MATCH($U7,Matriz!$B$3:$R$3,0)) -> 0
A8: 02 — Balanço de Pagamentos | B8: =INDEX(Matriz!$B$5:$R$5,1,MATCH(VALUE($B$3),Matriz!$B$3:$R$3,0)) -> 5 | C8: =B8/SUM($B$7:$B$23) -> 0.1 | U8: 2012 | V8: =IF($B$32="Sim",INDEX(Matriz!$B$4:$R$4,1,MATCH($U8,Matriz!$B$3:$R$3,0)),NA()) -> #N/A | W8: =IF($B$33="Sim",INDEX(Matriz!$B$5:$R$5,1,MATCH($U8,Matriz!$B$3:$R$3,0)),NA()) -> #N/A | X8: =IF($B$34="Sim",INDEX(Matriz!$B$6:$R$6,1,MATCH($U8,Matriz!$B$3:$R$3,0)),NA()) -> #N/A | Y8: =IF($B$35="Sim",INDEX(Matriz!$B$7:$R$7,1,MATCH($U8,Matriz!$B$3:$R$3,0)),NA()) -> #N/A | Z8: =IF($B$36="Sim",INDEX(Matriz!$B$8:$R$8,1,MATCH($U8,Matriz!$B$3:$R$3,0)),NA()) -> #N/A | AA8: =IF($B$37="Sim",INDEX(Matriz!$B$9:$R$9,1,MATCH($U8,Matriz!$B$3:$R$3,0)),NA()) -> 15 | AB8: =IF($B$38="Sim",INDEX(Matriz!$B$10:$R$10,1,MATCH($U8,Matriz!$B$3:$R$3,0)),NA()) -> #N/A | AC8: =IF($B$39="Sim",INDEX(Matriz!$B$11:$R$11,1,MATCH($U8,Matriz!$B$3:$R$3,0)),NA()) -> #N/A | AD8: =IF($B$40="Sim",INDEX(Matriz!$B$12:$R$12,1,MATCH($U8,Matriz!$B$3:$R$3,0)),NA()) -> #N/A | AE8: =IF($B$41="Sim",INDEX(Matriz!$B$13:$R$13,1,MATCH($U8,Matriz!$B$3:$R$3,0)),NA()) -> #N/A | AF8: =IF($B$42="Sim",INDEX(Matriz!$B$14:$R$14,1,MATCH($U8,Matriz!$B$3:$R$3,0)),NA()) -> #N/A | AG8: =IF($B$43="Sim",INDEX(Matriz!$B$15:$R$15,1,MATCH($U8,Matriz!$B$3:$R$3,0)),NA()) -> #N/A | AH8: =IF($B$44="Sim",INDEX(Matriz!$B$16:$R$16,1,MATCH($U8,Matriz!$B$3:$R$3,0)),NA()) -> #N/A | AI8: =IF($B$45="Sim",INDEX(Matriz!$B$17:$R$17,1,MATCH($U8,Matriz!$B$3:$R$3,0)),NA()) -> #N/A | AJ8: =IF($B$46="Sim",INDEX(Matriz!$B$18:$R$18,1,MATCH($U8,Matriz!$B$3:$R$3,0)),NA()) -> #N/A | AK8: =IF($B$47="Sim",INDEX(Matriz!$B$19:$R$19,1,MATCH($U8,Matriz!$B$3:$R$3,0)),NA()) -> #N/A | AL8: =IF($B$48="Sim",INDEX(Matriz!$B$20:$R$20,1,MATCH($U8,Matriz!$B$3:$R$3,0)),NA()) -> #N/A | AM8: =INDEX(Matriz!$B$21:$R$21,1,MATCH($U8,Matriz!$B$3:$R$3,0)) -> 0 | AN8: =INDEX(Matriz!$B$22:$R$22,1,MATCH($U8,Matriz!$B$3:$R$3,0)) -> 0 | AO8: =INDEX(Matriz!$B$23:$R$23,1,MATCH($U8,Matriz!$B$3:$R$3,0)) -> 0
A9: 03 — Sistema Monetário | B9: =INDEX(Matriz!$B$6:$R$6,1,MATCH(VALUE($B$3),Matriz!$B$3:$R$3,0)) -> 2.5 | C9: =B9/SUM($B$7:$B$23) -> 0.05 | U9: 2013 | V9: =IF($B$32="Sim",INDEX(Matriz!$B$4:$R$4,1,MATCH($U9,Matriz!$B$3:$R$3,0)),NA()) -> #N/A | W9: =IF($B$33="Sim",INDEX(Matriz!$B$5:$R$5,1,MATCH($U9,Matriz!$B$3:$R$3,0)),NA()) -> #N/A | X9: =IF($B$34="Sim",INDEX(Matriz!$B$6:$R$6,1,MATCH($U9,Matriz!$B$3:$R$3,0)),NA()) -> #N/A | Y9: =IF($B$35="Sim",INDEX(Matriz!$B$7:$R$7,1,MATCH($U9,Matriz!$B$3:$R$3,0)),NA()) -> #N/A | Z9: =IF($B$36="Sim",INDEX(Matriz!$B$8:$R$8,1,MATCH($U9,Matriz!$B$3:$R$3,0)),NA()) -> #N/A | AA9: =IF($B$37="Sim",INDEX(Matriz!$B$9:$R$9,1,MATCH($U9,Matriz!$B$3:$R$3,0)),NA()) -> 5 | AB9: =IF($B$38="Sim",INDEX(Matriz!$B$10:$R$10,1,MATCH($U9,Matriz!$B$3:$R$3,0)),NA()) -> #N/A | AC9: =IF($B$39="Sim",INDEX(Matriz!$B$11:$R$11,1,MATCH($U9,Matriz!$B$3:$R$3,0)),NA()) -> #N/A | AD9: =IF($B$40="Sim",INDEX(Matriz!$B$12:$R$12,1,MATCH($U9,Matriz!$B$3:$R$3,0)),NA()) -> #N/A | AE9: =IF($B$41="Sim",INDEX(Matriz!$B$13:$R$13,1,MATCH($U9,Matriz!$B$3:$R$3,0)),NA()) -> #N/A | AF9: =IF($B$42="Sim",INDEX(Matriz!$B$14:$R$14,1,MATCH($U9,Matriz!$B$3:$R$3,0)),NA()) -> #N/A | AG9: =IF($B$43="Sim",INDEX(Matriz!$B$15:$R$15,1,MATCH($U9,Matriz!$B$3:$R$3,0)),NA()) -> #N/A | AH9: =IF($B$44="Sim",INDEX(Matriz!$B$16:$R$16,1,MATCH($U9,Matriz!$B$3:$R$3,0)),NA()) -> #N/A | AI9: =IF($B$45="Sim",INDEX(Matriz!$B$17:$R$17,1,MATCH($U9,Matriz!$B$3:$R$3,0)),NA()) -> #N/A | AJ9: =IF($B$46="Sim",INDEX(Matriz!$B$18:$R$18,1,MATCH($U9,Matriz!$B$3:$R$3,0)),NA()) -> #N/A | AK9: =IF($B$47="Sim",INDEX(Matriz!$B$19:$R$19,1,MATCH($U9,Matriz!$B$3:$R$3,0)),NA()) -> #N/A | AL9: =IF($B$48="Sim",INDEX(Matriz!$B$20:$R$20,1,MATCH($U9,Matriz!$B$3:$R$3,0)),NA()) -> #N/A | AM9: =INDEX(Matriz!$B$21:$R$21,1,MATCH($U9,Matriz!$B$3:$R$3,0)) -> 0 | AN9: =INDEX(Matriz!$B$22:$R$22,1,MATCH($U9,Matriz!$B$3:$R$3,0)) -> 0 | AO9: =INDEX(Matriz!$B$23:$R$23,1,MATCH($U9,Matriz!$B$3:$R$3,0)) -> 0
A10: 04 — Demanda por Moeda | B10: =INDEX(Matriz!$B$7:$R$7,1,MATCH(VALUE($B$3),Matriz!$B$3:$R$3,0)) -> 2.5 | C10: =B10/SUM($B$7:$B$23) -> 0.05 | U10: 2014 | V10: =IF($B$32="Sim",INDEX(Matriz!$B$4:$R$4,1,MATCH($U10,Matriz!$B$3:$R$3,0)),NA()) -> #N/A | W10: =IF($B$33="Sim",INDEX(Matriz!$B$5:$R$5,1,MATCH($U10,Matriz!$B$3:$R$3,0)),NA()) -> #N/A | X10: =IF($B$34="Sim",INDEX(Matriz!$B$6:$R$6,1,MATCH($U10,Matriz!$B$3:$R$3,0)),NA()) -> #N/A | Y10: =IF($B$35="Sim",INDEX(Matriz!$B$7:$R$7,1,MATCH($U10,Matriz!$B$3:$R$3,0)),NA()) -> #N/A | Z10: =IF($B$36="Sim",INDEX(Matriz!$B$8:$R$8,1,MATCH($U10,Matriz!$B$3:$R$3,0)),NA()) -> #N/A | AA10: =IF($B$37="Sim",INDEX(Matriz!$B$9:$R$9,1,MATCH($U10,Matriz!$B$3:$R$3,0)),NA()) -> 6 | AB10: =IF($B$38="Sim",INDEX(Matriz!$B$10:$R$10,1,MATCH($U10,Matriz!$B$3:$R$3,0)),NA()) -> #N/A | AC10: =IF($B$39="Sim",INDEX(Matriz!$B$11:$R$11,1,MATCH($U10,Matriz!$B$3:$R$3,0)),NA()) -> #N/A | AD10: =IF($B$40="Sim",INDEX(Matriz!$B$12:$R$12,1,MATCH($U10,Matriz!$B$3:$R$3,0)),NA()) -> #N/A | AE10: =IF($B$41="Sim",INDEX(Matriz!$B$13:$R$13,1,MATCH($U10,Matriz!$B$3:$R$3,0)),NA()) -> #N/A | AF10: =IF($B$42="Sim",INDEX(Matriz!$B$14:$R$14,1,MATCH($U10,Matriz!$B$3:$R$3,0)),NA()) -> #N/A | AG10: =IF($B$43="Sim",INDEX(Matriz!$B$15:$R$15,1,MATCH($U10,Matriz!$B$3:$R$3,0)),NA()) -> #N/A | AH10: =IF($B$44="Sim",INDEX(Matriz!$B$16:$R$16,1,MATCH($U10,Matriz!$B$3:$R$3,0)),NA()) -> #N/A | AI10: =IF($B$45="Sim",INDEX(Matriz!$B$17:$R$17,1,MATCH($U10,Matriz!$B$3:$R$3,0)),NA()) -> #N/A | AJ10: =IF($B$46="Sim",INDEX(Matriz!$B$18:$R$18,1,MATCH($U10,Matriz!$B$3:$R$3,0)),NA()) -> #N/A | AK10: =IF($B$47="Sim",INDEX(Matriz!$B$19:$R$19,1,MATCH($U10,Matriz!$B$3:$R$3,0)),NA()) -> #N/A | AL10: =IF($B$48="Sim",INDEX(Matriz!$B$20:$R$20,1,MATCH($U10,Matriz!$B$3:$R$3,0)),NA()) -> #N/A | AM10: =INDEX(Matriz!$B$21:$R$21,1,MATCH($U10,Matriz!$B$3:$R$3,0)) -> 0 | AN10: =INDEX(Matriz!$B$22:$R$22,1,MATCH($U10,Matriz!$B$3:$R$3,0)) -> 0 | AO10: =INDEX(Matriz!$B$23:$R$23,1,MATCH($U10,Matriz!$B$3:$R$3,0)) -> 0
A11: 05 — IS-LM | B11: =INDEX(Matriz!$B$8:$R$8,1,MATCH(VALUE($B$3),Matriz!$B$3:$R$3,0)) -> 2.5 | C11: =B11/SUM($B$7:$B$23) -> 0.05 | U11: 2015 | V11: =IF($B$32="Sim",INDEX(Matriz!$B$4:$R$4,1,MATCH($U11,Matriz!$B$3:$R$3,0)),NA()) -> #N/A | W11: =IF($B$33="Sim",INDEX(Matriz!$B$5:$R$5,1,MATCH($U11,Matriz!$B$3:$R$3,0)),NA()) -> #N/A | X11: =IF($B$34="Sim",INDEX(Matriz!$B$6:$R$6,1,MATCH($U11,Matriz!$B$3:$R$3,0)),NA()) -> #N/A | Y11: =IF($B$35="Sim",INDEX(Matriz!$B$7:$R$7,1,MATCH($U11,Matriz!$B$3:$R$3,0)),NA()) -> #N/A | Z11: =IF($B$36="Sim",INDEX(Matriz!$B$8:$R$8,1,MATCH($U11,Matriz!$B$3:$R$3,0)),NA()) -> #N/A | AA11: =IF($B$37="Sim",INDEX(Matriz!$B$9:$R$9,1,MATCH($U11,Matriz!$B$3:$R$3,0)),NA()) -> 5 | AB11: =IF($B$38="Sim",INDEX(Matriz!$B$10:$R$10,1,MATCH($U11,Matriz!$B$3:$R$3,0)),NA()) -> #N/A | AC11: =IF($B$39="Sim",INDEX(Matriz!$B$11:$R$11,1,MATCH($U11,Matriz!$B$3:$R$3,0)),NA()) -> #N/A | AD11: =IF($B$40="Sim",INDEX(Matriz!$B$12:$R$12,1,MATCH($U11,Matriz!$B$3:$R$3,0)),NA()) -> #N/A | AE11: =IF($B$41="Sim",INDEX(Matriz!$B$13:$R$13,1,MATCH($U11,Matriz!$B$3:$R$3,0)),NA()) -> #N/A | AF11: =IF($B$42="Sim",INDEX(Matriz!$B$14:$R$14,1,MATCH($U11,Matriz!$B$3:$R$3,0)),NA()) -> #N/A | AG11: =IF($B$43="Sim",INDEX(Matriz!$B$15:$R$15,1,MATCH($U11,Matriz!$B$3:$R$3,0)),NA()) -> #N/A | AH11: =IF($B$44="Sim",INDEX(Matriz!$B$16:$R$16,1,MATCH($U11,Matriz!$B$3:$R$3,0)),NA()) -> #N/A | AI11: =IF($B$45="Sim",INDEX(Matriz!$B$17:$R$17,1,MATCH($U11,Matriz!$B$3:$R$3,0)),NA()) -> #N/A | AJ11: =IF($B$46="Sim",INDEX(Matriz!$B$18:$R$18,1,MATCH($U11,Matriz!$B$3:$R$3,0)),NA()) -> #N/A | AK11: =IF($B$47="Sim",INDEX(Matriz!$B$19:$R$19,1,MATCH($U11,Matriz!$B$3:$R$3,0)),NA()) -> #N/A | AL11: =IF($B$48="Sim",INDEX(Matriz!$B$20:$R$20,1,MATCH($U11,Matriz!$B$3:$R$3,0)),NA()) -> #N/A | AM11: =INDEX(Matriz!$B$21:$R$21,1,MATCH($U11,Matriz!$B$3:$R$3,0)) -> 0 | AN11: =INDEX(Matriz!$B$22:$R$22,1,MATCH($U11,Matriz!$B$3:$R$3,0)) -> 0 | AO11: =INDEX(Matriz!$B$23:$R$23,1,MATCH($U11,Matriz!$B$3:$R$3,0)) -> 0
A12: 06 — IS-LM-BP | B12: =INDEX(Matriz!$B$9:$R$9,1,MATCH(VALUE($B$3),Matriz!$B$3:$R$3,0)) -> 0 | C12: =B12/SUM($B$7:$B$23) -> 0 | U12: 2016 | V12: =IF($B$32="Sim",INDEX(Matriz!$B$4:$R$4,1,MATCH($U12,Matriz!$B$3:$R$3,0)),NA()) -> #N/A | W12: =IF($B$33="Sim",INDEX(Matriz!$B$5:$R$5,1,MATCH($U12,Matriz!$B$3:$R$3,0)),NA()) -> #N/A | X12: =IF($B$34="Sim",INDEX(Matriz!$B$6:$R$6,1,MATCH($U12,Matriz!$B$3:$R$3,0)),NA()) -> #N/A | Y12: =IF($B$35="Sim",INDEX(Matriz!$B$7:$R$7,1,MATCH($U12,Matriz!$B$3:$R$3,0)),NA()) -> #N/A | Z12: =IF($B$36="Sim",INDEX(Matriz!$B$8:$R$8,1,MATCH($U12,Matriz!$B$3:$R$3,0)),NA()) -> #N/A | AA12: =IF($B$37="Sim",INDEX(Matriz!$B$9:$R$9,1,MATCH($U12,Matriz!$B$3:$R$3,0)),NA()) -> 4.5 | AB12: =IF($B$38="Sim",INDEX(Matriz!$B$10:$R$10,1,MATCH($U12,Matriz!$B$3:$R$3,0)),NA()) -> #N/A | AC12: =IF($B$39="Sim",INDEX(Matriz!$B$11:$R$11,1,MATCH($U12,Matriz!$B$3:$R$3,0)),NA()) -> #N/A | AD12: =IF($B$40="Sim",INDEX(Matriz!$B$12:$R$12,1,MATCH($U12,Matriz!$B$3:$R$3,0)),NA()) -> #N/A | AE12: =IF($B$41="Sim",INDEX(Matriz!$B$13:$R$13,1,MATCH($U12,Matriz!$B$3:$R$3,0)),NA()) -> #N/A | AF12: =IF($B$42="Sim",INDEX(Matriz!$B$14:$R$14,1,MATCH($U12,Matriz!$B$3:$R$3,0)),NA()) -> #N/A | AG12: =IF($B$43="Sim",INDEX(Matriz!$B$15:$R$15,1,MATCH($U12,Matriz!$B$3:$R$3,0)),NA()) -> #N/A | AH12: =IF($B$44="Sim",INDEX(Matriz!$B$16:$R$16,1,MATCH($U12,Matriz!$B$3:$R$3,0)),NA()) -> #N/A | AI12: =IF($B$45="Sim",INDEX(Matriz!$B$17:$R$17,1,MATCH($U12,Matriz!$B$3:$R$3,0)),NA()) -> #N/A | AJ12: =IF($B$46="Sim",INDEX(Matriz!$B$18:$R$18,1,MATCH($U12,Matriz!$B$3:$R$3,0)),NA()) -> #N/A | AK12: =IF($B$47="Sim",INDEX(Matriz!$B$19:$R$19,1,MATCH($U12,Matriz!$B$3:$R$3,0)),NA()) -> #N/A | AL12: =IF($B$48="Sim",INDEX(Matriz!$B$20:$R$20,1,MATCH($U12,Matriz!$B$3:$R$3,0)),NA()) -> #N/A | AM12: =INDEX(Matriz!$B$21:$R$21,1,MATCH($U12,Matriz!$B$3:$R$3,0)) -> 0 | AN12: =INDEX(Matriz!$B$22:$R$22,1,MATCH($U12,Matriz!$B$3:$R$3,0)) -> 0 | AO12: =INDEX(Matriz!$B$23:$R$23,1,MATCH($U12,Matriz!$B$3:$R$3,0)) -> 0
A13: 07a — Paridades | B13: =INDEX(Matriz!$B$10:$R$10,1,MATCH(VALUE($B$3),Matriz!$B$3:$R$3,0)) -> 5 | C13: =B13/SUM($B$7:$B$23) -> 0.1 | U13: 2017 | V13: =IF($B$32="Sim",INDEX(Matriz!$B$4:$R$4,1,MATCH($U13,Matriz!$B$3:$R$3,0)),NA()) -> #N/A | W13: =IF($B$33="Sim",INDEX(Matriz!$B$5:$R$5,1,MATCH($U13,Matriz!$B$3:$R$3,0)),NA()) -> #N/A | X13: =IF($B$34="Sim",INDEX(Matriz!$B$6:$R$6,1,MATCH($U13,Matriz!$B$3:$R$3,0)),NA()) -> #N/A | Y13: =IF($B$35="Sim",INDEX(Matriz!$B$7:$R$7,1,MATCH($U13,Matriz!$B$3:$R$3,0)),NA()) -> #N/A | Z13: =IF($B$36="Sim",INDEX(Matriz!$B$8:$R$8,1,MATCH($U13,Matriz!$B$3:$R$3,0)),NA()) -> #N/A | AA13: =IF($B$37="Sim",INDEX(Matriz!$B$9:$R$9,1,MATCH($U13,Matriz!$B$3:$R$3,0)),NA()) -> 10 | AB13: =IF($B$38="Sim",INDEX(Matriz!$B$10:$R$10,1,MATCH($U13,Matriz!$B$3:$R$3,0)),NA()) -> #N/A | AC13: =IF($B$39="Sim",INDEX(Matriz!$B$11:$R$11,1,MATCH($U13,Matriz!$B$3:$R$3,0)),NA()) -> #N/A | AD13: =IF($B$40="Sim",INDEX(Matriz!$B$12:$R$12,1,MATCH($U13,Matriz!$B$3:$R$3,0)),NA()) -> #N/A | AE13: =IF($B$41="Sim",INDEX(Matriz!$B$13:$R$13,1,MATCH($U13,Matriz!$B$3:$R$3,0)),NA()) -> #N/A | AF13: =IF($B$42="Sim",INDEX(Matriz!$B$14:$R$14,1,MATCH($U13,Matriz!$B$3:$R$3,0)),NA()) -> #N/A | AG13: =IF($B$43="Sim",INDEX(Matriz!$B$15:$R$15,1,MATCH($U13,Matriz!$B$3:$R$3,0)),NA()) -> #N/A | AH13: =IF($B$44="Sim",INDEX(Matriz!$B$16:$R$16,1,MATCH($U13,Matriz!$B$3:$R$3,0)),NA()) -> #N/A | AI13: =IF($B$45="Sim",INDEX(Matriz!$B$17:$R$17,1,MATCH($U13,Matriz!$B$3:$R$3,0)),NA()) -> #N/A | AJ13: =IF($B$46="Sim",INDEX(Matriz!$B$18:$R$18,1,MATCH($U13,Matriz!$B$3:$R$3,0)),NA()) -> #N/A | AK13: =IF($B$47="Sim",INDEX(Matriz!$B$19:$R$19,1,MATCH($U13,Matriz!$B$3:$R$3,0)),NA()) -> #N/A | AL13: =IF($B$48="Sim",INDEX(Matriz!$B$20:$R$20,1,MATCH($U13,Matriz!$B$3:$R$3,0)),NA()) -> #N/A | AM13: =INDEX(Matriz!$B$21:$R$21,1,MATCH($U13,Matriz!$B$3:$R$3,0)) -> 0 | AN13: =INDEX(Matriz!$B$22:$R$22,1,MATCH($U13,Matriz!$B$3:$R$3,0)) -> 0 | AO13: =INDEX(Matriz!$B$23:$R$23,1,MATCH($U13,Matriz!$B$3:$R$3,0)) -> 0
A14: 07b — OA-DA | B14: =INDEX(Matriz!$B$11:$R$11,1,MATCH(VALUE($B$3),Matriz!$B$3:$R$3,0)) -> 2 | C14: =B14/SUM($B$7:$B$23) -> 0.04 | U14: 2018 | V14: =IF($B$32="Sim",INDEX(Matriz!$B$4:$R$4,1,MATCH($U14,Matriz!$B$3:$R$3,0)),NA()) -> #N/A | W14: =IF($B$33="Sim",INDEX(Matriz!$B$5:$R$5,1,MATCH($U14,Matriz!$B$3:$R$3,0)),NA()) -> #N/A | X14: =IF($B$34="Sim",INDEX(Matriz!$B$6:$R$6,1,MATCH($U14,Matriz!$B$3:$R$3,0)),NA()) -> #N/A | Y14: =IF($B$35="Sim",INDEX(Matriz!$B$7:$R$7,1,MATCH($U14,Matriz!$B$3:$R$3,0)),NA()) -> #N/A | Z14: =IF($B$36="Sim",INDEX(Matriz!$B$8:$R$8,1,MATCH($U14,Matriz!$B$3:$R$3,0)),NA()) -> #N/A | AA14: =IF($B$37="Sim",INDEX(Matriz!$B$9:$R$9,1,MATCH($U14,Matriz!$B$3:$R$3,0)),NA()) -> 10 | AB14: =IF($B$38="Sim",INDEX(Matriz!$B$10:$R$10,1,MATCH($U14,Matriz!$B$3:$R$3,0)),NA()) -> #N/A | AC14: =IF($B$39="Sim",INDEX(Matriz!$B$11:$R$11,1,MATCH($U14,Matriz!$B$3:$R$3,0)),NA()) -> #N/A | AD14: =IF($B$40="Sim",INDEX(Matriz!$B$12:$R$12,1,MATCH($U14,Matriz!$B$3:$R$3,0)),NA()) -> #N/A | AE14: =IF($B$41="Sim",INDEX(Matriz!$B$13:$R$13,1,MATCH($U14,Matriz!$B$3:$R$3,0)),NA()) -> #N/A | AF14: =IF($B$42="Sim",INDEX(Matriz!$B$14:$R$14,1,MATCH($U14,Matriz!$B$3:$R$3,0)),NA()) -> #N/A | AG14: =IF($B$43="Sim",INDEX(Matriz!$B$15:$R$15,1,MATCH($U14,Matriz!$B$3:$R$3,0)),NA()) -> #N/A | AH14: =IF($B$44="Sim",INDEX(Matriz!$B$16:$R$16,1,MATCH($U14,Matriz!$B$3:$R$3,0)),NA()) -> #N/A | AI14: =IF($B$45="Sim",INDEX(Matriz!$B$17:$R$17,1,MATCH($U14,Matriz!$B$3:$R$3,0)),NA()) -> #N/A | AJ14: =IF($B$46="Sim",INDEX(Matriz!$B$18:$R$18,1,MATCH($U14,Matriz!$B$3:$R$3,0)),NA()) -> #N/A | AK14: =IF($B$47="Sim",INDEX(Matriz!$B$19:$R$19,1,MATCH($U14,Matriz!$B$3:$R$3,0)),NA()) -> #N/A | AL14: =IF($B$48="Sim",INDEX(Matriz!$B$20:$R$20,1,MATCH($U14,Matriz!$B$3:$R$3,0)),NA()) -> #N/A | AM14: =INDEX(Matriz!$B$21:$R$21,1,MATCH($U14,Matriz!$B$3:$R$3,0)) -> 0 | AN14: =INDEX(Matriz!$B$22:$R$22,1,MATCH($U14,Matriz!$B$3:$R$3,0)) -> 0 | AO14: =INDEX(Matriz!$B$23:$R$23,1,MATCH($U14,Matriz!$B$3:$R$3,0)) -> 0
A15: 08 — Curva de Phillips | B15: =INDEX(Matriz!$B$12:$R$12,1,MATCH(VALUE($B$3),Matriz!$B$3:$R$3,0)) -> 1.5 | C15: =B15/SUM($B$7:$B$23) -> 0.03 | U15: 2019 | V15: =IF($B$32="Sim",INDEX(Matriz!$B$4:$R$4,1,MATCH($U15,Matriz!$B$3:$R$3,0)),NA()) -> #N/A | W15: =IF($B$33="Sim",INDEX(Matriz!$B$5:$R$5,1,MATCH($U15,Matriz!$B$3:$R$3,0)),NA()) -> #N/A | X15: =IF($B$34="Sim",INDEX(Matriz!$B$6:$R$6,1,MATCH($U15,Matriz!$B$3:$R$3,0)),NA()) -> #N/A | Y15: =IF($B$35="Sim",INDEX(Matriz!$B$7:$R$7,1,MATCH($U15,Matriz!$B$3:$R$3,0)),NA()) -> #N/A | Z15: =IF($B$36="Sim",INDEX(Matriz!$B$8:$R$8,1,MATCH($U15,Matriz!$B$3:$R$3,0)),NA()) -> #N/A | AA15: =IF($B$37="Sim",INDEX(Matriz!$B$9:$R$9,1,MATCH($U15,Matriz!$B$3:$R$3,0)),NA()) -> 10 | AB15: =IF($B$38="Sim",INDEX(Matriz!$B$10:$R$10,1,MATCH($U15,Matriz!$B$3:$R$3,0)),NA()) -> #N/A | AC15: =IF($B$39="Sim",INDEX(Matriz!$B$11:$R$11,1,MATCH($U15,Matriz!$B$3:$R$3,0)),NA()) -> #N/A | AD15: =IF($B$40="Sim",INDEX(Matriz!$B$12:$R$12,1,MATCH($U15,Matriz!$B$3:$R$3,0)),NA()) -> #N/A | AE15: =IF($B$41="Sim",INDEX(Matriz!$B$13:$R$13,1,MATCH($U15,Matriz!$B$3:$R$3,0)),NA()) -> #N/A | AF15: =IF($B$42="Sim",INDEX(Matriz!$B$14:$R$14,1,MATCH($U15,Matriz!$B$3:$R$3,0)),NA()) -> #N/A | AG15: =IF($B$43="Sim",INDEX(Matriz!$B$15:$R$15,1,MATCH($U15,Matriz!$B$3:$R$3,0)),NA()) -> #N/A | AH15: =IF($B$44="Sim",INDEX(Matriz!$B$16:$R$16,1,MATCH($U15,Matriz!$B$3:$R$3,0)),NA()) -> #N/A | AI15: =IF($B$45="Sim",INDEX(Matriz!$B$17:$R$17,1,MATCH($U15,Matriz!$B$3:$R$3,0)),NA()) -> #N/A | AJ15: =IF($B$46="Sim",INDEX(Matriz!$B$18:$R$18,1,MATCH($U15,Matriz!$B$3:$R$3,0)),NA()) -> #N/A | AK15: =IF($B$47="Sim",INDEX(Matriz!$B$19:$R$19,1,MATCH($U15,Matriz!$B$3:$R$3,0)),NA()) -> #N/A | AL15: =IF($B$48="Sim",INDEX(Matriz!$B$20:$R$20,1,MATCH($U15,Matriz!$B$3:$R$3,0)),NA()) -> #N/A | AM15: =INDEX(Matriz!$B$21:$R$21,1,MATCH($U15,Matriz!$B$3:$R$3,0)) -> 0 | AN15: =INDEX(Matriz!$B$22:$R$22,1,MATCH($U15,Matriz!$B$3:$R$3,0)) -> 0 | AO15: =INDEX(Matriz!$B$23:$R$23,1,MATCH($U15,Matriz!$B$3:$R$3,0)) -> 0
A16: 09 — Expectativas, Novos Clássicos e Novos Keynesianos | B16: =INDEX(Matriz!$B$13:$R$13,1,MATCH(VALUE($B$3),Matriz!$B$3:$R$3,0)) -> 12 | C16: =B16/SUM($B$7:$B$23) -> 0.24 | U16: 2020 | V16: =IF($B$32="Sim",INDEX(Matriz!$B$4:$R$4,1,MATCH($U16,Matriz!$B$3:$R$3,0)),NA()) -> #N/A | W16: =IF($B$33="Sim",INDEX(Matriz!$B$5:$R$5,1,MATCH($U16,Matriz!$B$3:$R$3,0)),NA()) -> #N/A | X16: =IF($B$34="Sim",INDEX(Matriz!$B$6:$R$6,1,MATCH($U16,Matriz!$B$3:$R$3,0)),NA()) -> #N/A | Y16: =IF($B$35="Sim",INDEX(Matriz!$B$7:$R$7,1,MATCH($U16,Matriz!$B$3:$R$3,0)),NA()) -> #N/A | Z16: =IF($B$36="Sim",INDEX(Matriz!$B$8:$R$8,1,MATCH($U16,Matriz!$B$3:$R$3,0)),NA()) -> #N/A | AA16: =IF($B$37="Sim",INDEX(Matriz!$B$9:$R$9,1,MATCH($U16,Matriz!$B$3:$R$3,0)),NA()) -> 5 | AB16: =IF($B$38="Sim",INDEX(Matriz!$B$10:$R$10,1,MATCH($U16,Matriz!$B$3:$R$3,0)),NA()) -> #N/A | AC16: =IF($B$39="Sim",INDEX(Matriz!$B$11:$R$11,1,MATCH($U16,Matriz!$B$3:$R$3,0)),NA()) -> #N/A | AD16: =IF($B$40="Sim",INDEX(Matriz!$B$12:$R$12,1,MATCH($U16,Matriz!$B$3:$R$3,0)),NA()) -> #N/A | AE16: =IF($B$41="Sim",INDEX(Matriz!$B$13:$R$13,1,MATCH($U16,Matriz!$B$3:$R$3,0)),NA()) -> #N/A | AF16: =IF($B$42="Sim",INDEX(Matriz!$B$14:$R$14,1,MATCH($U16,Matriz!$B$3:$R$3,0)),NA()) -> #N/A | AG16: =IF($B$43="Sim",INDEX(Matriz!$B$15:$R$15,1,MATCH($U16,Matriz!$B$3:$R$3,0)),NA()) -> #N/A | AH16: =IF($B$44="Sim",INDEX(Matriz!$B$16:$R$16,1,MATCH($U16,Matriz!$B$3:$R$3,0)),NA()) -> #N/A | AI16: =IF($B$45="Sim",INDEX(Matriz!$B$17:$R$17,1,MATCH($U16,Matriz!$B$3:$R$3,0)),NA()) -> #N/A | AJ16: =IF($B$46="Sim",INDEX(Matriz!$B$18:$R$18,1,MATCH($U16,Matriz!$B$3:$R$3,0)),NA()) -> #N/A | AK16: =IF($B$47="Sim",INDEX(Matriz!$B$19:$R$19,1,MATCH($U16,Matriz!$B$3:$R$3,0)),NA()) -> #N/A | AL16: =IF($B$48="Sim",INDEX(Matriz!$B$20:$R$20,1,MATCH($U16,Matriz!$B$3:$R$3,0)),NA()) -> #N/A | AM16: =INDEX(Matriz!$B$21:$R$21,1,MATCH($U16,Matriz!$B$3:$R$3,0)) -> 0 | AN16: =INDEX(Matriz!$B$22:$R$22,1,MATCH($U16,Matriz!$B$3:$R$3,0)) -> 0 | AO16: =INDEX(Matriz!$B$23:$R$23,1,MATCH($U16,Matriz!$B$3:$R$3,0)) -> 0
A17: 10 — Ciclos Reais de Negócios (RBC) | B17: =INDEX(Matriz!$B$14:$R$14,1,MATCH(VALUE($B$3),Matriz!$B$3:$R$3,0)) -> 1 | C17: =B17/SUM($B$7:$B$23) -> 0.02 | U17: 2021 | V17: =IF($B$32="Sim",INDEX(Matriz!$B$4:$R$4,1,MATCH($U17,Matriz!$B$3:$R$3,0)),NA()) -> #N/A | W17: =IF($B$33="Sim",INDEX(Matriz!$B$5:$R$5,1,MATCH($U17,Matriz!$B$3:$R$3,0)),NA()) -> #N/A | X17: =IF($B$34="Sim",INDEX(Matriz!$B$6:$R$6,1,MATCH($U17,Matriz!$B$3:$R$3,0)),NA()) -> #N/A | Y17: =IF($B$35="Sim",INDEX(Matriz!$B$7:$R$7,1,MATCH($U17,Matriz!$B$3:$R$3,0)),NA()) -> #N/A | Z17: =IF($B$36="Sim",INDEX(Matriz!$B$8:$R$8,1,MATCH($U17,Matriz!$B$3:$R$3,0)),NA()) -> #N/A | AA17: =IF($B$37="Sim",INDEX(Matriz!$B$9:$R$9,1,MATCH($U17,Matriz!$B$3:$R$3,0)),NA()) -> 10 | AB17: =IF($B$38="Sim",INDEX(Matriz!$B$10:$R$10,1,MATCH($U17,Matriz!$B$3:$R$3,0)),NA()) -> #N/A | AC17: =IF($B$39="Sim",INDEX(Matriz!$B$11:$R$11,1,MATCH($U17,Matriz!$B$3:$R$3,0)),NA()) -> #N/A | AD17: =IF($B$40="Sim",INDEX(Matriz!$B$12:$R$12,1,MATCH($U17,Matriz!$B$3:$R$3,0)),NA()) -> #N/A | AE17: =IF($B$41="Sim",INDEX(Matriz!$B$13:$R$13,1,MATCH($U17,Matriz!$B$3:$R$3,0)),NA()) -> #N/A | AF17: =IF($B$42="Sim",INDEX(Matriz!$B$14:$R$14,1,MATCH($U17,Matriz!$B$3:$R$3,0)),NA()) -> #N/A | AG17: =IF($B$43="Sim",INDEX(Matriz!$B$15:$R$15,1,MATCH($U17,Matriz!$B$3:$R$3,0)),NA()) -> #N/A | AH17: =IF($B$44="Sim",INDEX(Matriz!$B$16:$R$16,1,MATCH($U17,Matriz!$B$3:$R$3,0)),NA()) -> #N/A | AI17: =IF($B$45="Sim",INDEX(Matriz!$B$17:$R$17,1,MATCH($U17,Matriz!$B$3:$R$3,0)),NA()) -> #N/A | AJ17: =IF($B$46="Sim",INDEX(Matriz!$B$18:$R$18,1,MATCH($U17,Matriz!$B$3:$R$3,0)),NA()) -> #N/A | AK17: =IF($B$47="Sim",INDEX(Matriz!$B$19:$R$19,1,MATCH($U17,Matriz!$B$3:$R$3,0)),NA()) -> #N/A | AL17: =IF($B$48="Sim",INDEX(Matriz!$B$20:$R$20,1,MATCH($U17,Matriz!$B$3:$R$3,0)),NA()) -> #N/A | AM17: =INDEX(Matriz!$B$21:$R$21,1,MATCH($U17,Matriz!$B$3:$R$3,0)) -> 0 | AN17: =INDEX(Matriz!$B$22:$R$22,1,MATCH($U17,Matriz!$B$3:$R$3,0)) -> 0 | AO17: =INDEX(Matriz!$B$23:$R$23,1,MATCH($U17,Matriz!$B$3:$R$3,0)) -> 0
A18: 11 — Crescimento Econômico | B18: =INDEX(Matriz!$B$15:$R$15,1,MATCH(VALUE($B$3),Matriz!$B$3:$R$3,0)) -> 5 | C18: =B18/SUM($B$7:$B$23) -> 0.1 | U18: 2022 | V18: =IF($B$32="Sim",INDEX(Matriz!$B$4:$R$4,1,MATCH($U18,Matriz!$B$3:$R$3,0)),NA()) -> #N/A | W18: =IF($B$33="Sim",INDEX(Matriz!$B$5:$R$5,1,MATCH($U18,Matriz!$B$3:$R$3,0)),NA()) -> #N/A | X18: =IF($B$34="Sim",INDEX(Matriz!$B$6:$R$6,1,MATCH($U18,Matriz!$B$3:$R$3,0)),NA()) -> #N/A | Y18: =IF($B$35="Sim",INDEX(Matriz!$B$7:$R$7,1,MATCH($U18,Matriz!$B$3:$R$3,0)),NA()) -> #N/A | Z18: =IF($B$36="Sim",INDEX(Matriz!$B$8:$R$8,1,MATCH($U18,Matriz!$B$3:$R$3,0)),NA()) -> #N/A | AA18: =IF($B$37="Sim",INDEX(Matriz!$B$9:$R$9,1,MATCH($U18,Matriz!$B$3:$R$3,0)),NA()) -> 8 | AB18: =IF($B$38="Sim",INDEX(Matriz!$B$10:$R$10,1,MATCH($U18,Matriz!$B$3:$R$3,0)),NA()) -> #N/A | AC18: =IF($B$39="Sim",INDEX(Matriz!$B$11:$R$11,1,MATCH($U18,Matriz!$B$3:$R$3,0)),NA()) -> #N/A | AD18: =IF($B$40="Sim",INDEX(Matriz!$B$12:$R$12,1,MATCH($U18,Matriz!$B$3:$R$3,0)),NA()) -> #N/A | AE18: =IF($B$41="Sim",INDEX(Matriz!$B$13:$R$13,1,MATCH($U18,Matriz!$B$3:$R$3,0)),NA()) -> #N/A | AF18: =IF($B$42="Sim",INDEX(Matriz!$B$14:$R$14,1,MATCH($U18,Matriz!$B$3:$R$3,0)),NA()) -> #N/A | AG18: =IF($B$43="Sim",INDEX(Matriz!$B$15:$R$15,1,MATCH($U18,Matriz!$B$3:$R$3,0)),NA()) -> #N/A | AH18: =IF($B$44="Sim",INDEX(Matriz!$B$16:$R$16,1,MATCH($U18,Matriz!$B$3:$R$3,0)),NA()) -> #N/A | AI18: =IF($B$45="Sim",INDEX(Matriz!$B$17:$R$17,1,MATCH($U18,Matriz!$B$3:$R$3,0)),NA()) -> #N/A | AJ18: =IF($B$46="Sim",INDEX(Matriz!$B$18:$R$18,1,MATCH($U18,Matriz!$B$3:$R$3,0)),NA()) -> #N/A | AK18: =IF($B$47="Sim",INDEX(Matriz!$B$19:$R$19,1,MATCH($U18,Matriz!$B$3:$R$3,0)),NA()) -> #N/A | AL18: =IF($B$48="Sim",INDEX(Matriz!$B$20:$R$20,1,MATCH($U18,Matriz!$B$3:$R$3,0)),NA()) -> #N/A | AM18: =INDEX(Matriz!$B$21:$R$21,1,MATCH($U18,Matriz!$B$3:$R$3,0)) -> 0 | AN18: =INDEX(Matriz!$B$22:$R$22,1,MATCH($U18,Matriz!$B$3:$R$3,0)) -> 0 | AO18: =INDEX(Matriz!$B$23:$R$23,1,MATCH($U18,Matriz!$B$3:$R$3,0)) -> 0
A19: 12 — Consumo | B19: =INDEX(Matriz!$B$16:$R$16,1,MATCH(VALUE($B$3),Matriz!$B$3:$R$3,0)) -> 2 | C19: =B19/SUM($B$7:$B$23) -> 0.04 | U19: 2023 | V19: =IF($B$32="Sim",INDEX(Matriz!$B$4:$R$4,1,MATCH($U19,Matriz!$B$3:$R$3,0)),NA()) -> #N/A | W19: =IF($B$33="Sim",INDEX(Matriz!$B$5:$R$5,1,MATCH($U19,Matriz!$B$3:$R$3,0)),NA()) -> #N/A | X19: =IF($B$34="Sim",INDEX(Matriz!$B$6:$R$6,1,MATCH($U19,Matriz!$B$3:$R$3,0)),NA()) -> #N/A | Y19: =IF($B$35="Sim",INDEX(Matriz!$B$7:$R$7,1,MATCH($U19,Matriz!$B$3:$R$3,0)),NA()) -> #N/A | Z19: =IF($B$36="Sim",INDEX(Matriz!$B$8:$R$8,1,MATCH($U19,Matriz!$B$3:$R$3,0)),NA()) -> #N/A | AA19: =IF($B$37="Sim",INDEX(Matriz!$B$9:$R$9,1,MATCH($U19,Matriz!$B$3:$R$3,0)),NA()) -> 11 | AB19: =IF($B$38="Sim",INDEX(Matriz!$B$10:$R$10,1,MATCH($U19,Matriz!$B$3:$R$3,0)),NA()) -> #N/A | AC19: =IF($B$39="Sim",INDEX(Matriz!$B$11:$R$11,1,MATCH($U19,Matriz!$B$3:$R$3,0)),NA()) -> #N/A | AD19: =IF($B$40="Sim",INDEX(Matriz!$B$12:$R$12,1,MATCH($U19,Matriz!$B$3:$R$3,0)),NA()) -> #N/A | AE19: =IF($B$41="Sim",INDEX(Matriz!$B$13:$R$13,1,MATCH($U19,Matriz!$B$3:$R$3,0)),NA()) -> #N/A | AF19: =IF($B$42="Sim",INDEX(Matriz!$B$14:$R$14,1,MATCH($U19,Matriz!$B$3:$R$3,0)),NA()) -> #N/A | AG19: =IF($B$43="Sim",INDEX(Matriz!$B$15:$R$15,1,MATCH($U19,Matriz!$B$3:$R$3,0)),NA()) -> #N/A | AH19: =IF($B$44="Sim",INDEX(Matriz!$B$16:$R$16,1,MATCH($U19,Matriz!$B$3:$R$3,0)),NA()) -> #N/A | AI19: =IF($B$45="Sim",INDEX(Matriz!$B$17:$R$17,1,MATCH($U19,Matriz!$B$3:$R$3,0)),NA()) -> #N/A | AJ19: =IF($B$46="Sim",INDEX(Matriz!$B$18:$R$18,1,MATCH($U19,Matriz!$B$3:$R$3,0)),NA()) -> #N/A | AK19: =IF($B$47="Sim",INDEX(Matriz!$B$19:$R$19,1,MATCH($U19,Matriz!$B$3:$R$3,0)),NA()) -> #N/A | AL19: =IF($B$48="Sim",INDEX(Matriz!$B$20:$R$20,1,MATCH($U19,Matriz!$B$3:$R$3,0)),NA()) -> #N/A | AM19: =INDEX(Matriz!$B$21:$R$21,1,MATCH($U19,Matriz!$B$3:$R$3,0)) -> 0 | AN19: =INDEX(Matriz!$B$22:$R$22,1,MATCH($U19,Matriz!$B$3:$R$3,0)) -> 0 | AO19: =INDEX(Matriz!$B$23:$R$23,1,MATCH($U19,Matriz!$B$3:$R$3,0)) -> 0
A20: 13 — Investimento | B20: =INDEX(Matriz!$B$17:$R$17,1,MATCH(VALUE($B$3),Matriz!$B$3:$R$3,0)) -> 2 | C20: =B20/SUM($B$7:$B$23) -> 0.04 | U20: 2024 | V20: =IF($B$32="Sim",INDEX(Matriz!$B$4:$R$4,1,MATCH($U20,Matriz!$B$3:$R$3,0)),NA()) -> #N/A | W20: =IF($B$33="Sim",INDEX(Matriz!$B$5:$R$5,1,MATCH($U20,Matriz!$B$3:$R$3,0)),NA()) -> #N/A | X20: =IF($B$34="Sim",INDEX(Matriz!$B$6:$R$6,1,MATCH($U20,Matriz!$B$3:$R$3,0)),NA()) -> #N/A | Y20: =IF($B$35="Sim",INDEX(Matriz!$B$7:$R$7,1,MATCH($U20,Matriz!$B$3:$R$3,0)),NA()) -> #N/A | Z20: =IF($B$36="Sim",INDEX(Matriz!$B$8:$R$8,1,MATCH($U20,Matriz!$B$3:$R$3,0)),NA()) -> #N/A | AA20: =IF($B$37="Sim",INDEX(Matriz!$B$9:$R$9,1,MATCH($U20,Matriz!$B$3:$R$3,0)),NA()) -> 8 | AB20: =IF($B$38="Sim",INDEX(Matriz!$B$10:$R$10,1,MATCH($U20,Matriz!$B$3:$R$3,0)),NA()) -> #N/A | AC20: =IF($B$39="Sim",INDEX(Matriz!$B$11:$R$11,1,MATCH($U20,Matriz!$B$3:$R$3,0)),NA()) -> #N/A | AD20: =IF($B$40="Sim",INDEX(Matriz!$B$12:$R$12,1,MATCH($U20,Matriz!$B$3:$R$3,0)),NA()) -> #N/A | AE20: =IF($B$41="Sim",INDEX(Matriz!$B$13:$R$13,1,MATCH($U20,Matriz!$B$3:$R$3,0)),NA()) -> #N/A | AF20: =IF($B$42="Sim",INDEX(Matriz!$B$14:$R$14,1,MATCH($U20,Matriz!$B$3:$R$3,0)),NA()) -> #N/A | AG20: =IF($B$43="Sim",INDEX(Matriz!$B$15:$R$15,1,MATCH($U20,Matriz!$B$3:$R$3,0)),NA()) -> #N/A | AH20: =IF($B$44="Sim",INDEX(Matriz!$B$16:$R$16,1,MATCH($U20,Matriz!$B$3:$R$3,0)),NA()) -> #N/A | AI20: =IF($B$45="Sim",INDEX(Matriz!$B$17:$R$17,1,MATCH($U20,Matriz!$B$3:$R$3,0)),NA()) -> #N/A | AJ20: =IF($B$46="Sim",INDEX(Matriz!$B$18:$R$18,1,MATCH($U20,Matriz!$B$3:$R$3,0)),NA()) -> #N/A | AK20: =IF($B$47="Sim",INDEX(Matriz!$B$19:$R$19,1,MATCH($U20,Matriz!$B$3:$R$3,0)),NA()) -> #N/A | AL20: =IF($B$48="Sim",INDEX(Matriz!$B$20:$R$20,1,MATCH($U20,Matriz!$B$3:$R$3,0)),NA()) -> #N/A | AM20: =INDEX(Matriz!$B$21:$R$21,1,MATCH($U20,Matriz!$B$3:$R$3,0)) -> 0 | AN20: =INDEX(Matriz!$B$22:$R$22,1,MATCH($U20,Matriz!$B$3:$R$3,0)) -> 0 | AO20: =INDEX(Matriz!$B$23:$R$23,1,MATCH($U20,Matriz!$B$3:$R$3,0)) -> 0
A21: 14 — Dívida Pública e Senhoriagem | B21: =INDEX(Matriz!$B$18:$R$18,1,MATCH(VALUE($B$3),Matriz!$B$3:$R$3,0)) -> 3 | C21: =B21/SUM($B$7:$B$23) -> 0.06 | U21: 2025 | V21: =IF($B$32="Sim",INDEX(Matriz!$B$4:$R$4,1,MATCH($U21,Matriz!$B$3:$R$3,0)),NA()) -> #N/A | W21: =IF($B$33="Sim",INDEX(Matriz!$B$5:$R$5,1,MATCH($U21,Matriz!$B$3:$R$3,0)),NA()) -> #N/A | X21: =IF($B$34="Sim",INDEX(Matriz!$B$6:$R$6,1,MATCH($U21,Matriz!$B$3:$R$3,0)),NA()) -> #N/A | Y21: =IF($B$35="Sim",INDEX(Matriz!$B$7:$R$7,1,MATCH($U21,Matriz!$B$3:$R$3,0)),NA()) -> #N/A | Z21: =IF($B$36="Sim",INDEX(Matriz!$B$8:$R$8,1,MATCH($U21,Matriz!$B$3:$R$3,0)),NA()) -> #N/A | AA21: =IF($B$37="Sim",INDEX(Matriz!$B$9:$R$9,1,MATCH($U21,Matriz!$B$3:$R$3,0)),NA()) -> 0 | AB21: =IF($B$38="Sim",INDEX(Matriz!$B$10:$R$10,1,MATCH($U21,Matriz!$B$3:$R$3,0)),NA()) -> #N/A | AC21: =IF($B$39="Sim",INDEX(Matriz!$B$11:$R$11,1,MATCH($U21,Matriz!$B$3:$R$3,0)),NA()) -> #N/A | AD21: =IF($B$40="Sim",INDEX(Matriz!$B$12:$R$12,1,MATCH($U21,Matriz!$B$3:$R$3,0)),NA()) -> #N/A | AE21: =IF($B$41="Sim",INDEX(Matriz!$B$13:$R$13,1,MATCH($U21,Matriz!$B$3:$R$3,0)),NA()) -> #N/A | AF21: =IF($B$42="Sim",INDEX(Matriz!$B$14:$R$14,1,MATCH($U21,Matriz!$B$3:$R$3,0)),NA()) -> #N/A | AG21: =IF($B$43="Sim",INDEX(Matriz!$B$15:$R$15,1,MATCH($U21,Matriz!$B$3:$R$3,0)),NA()) -> #N/A | AH21: =IF($B$44="Sim",INDEX(Matriz!$B$16:$R$16,1,MATCH($U21,Matriz!$B$3:$R$3,0)),NA()) -> #N/A | AI21: =IF($B$45="Sim",INDEX(Matriz!$B$17:$R$17,1,MATCH($U21,Matriz!$B$3:$R$3,0)),NA()) -> #N/A | AJ21: =IF($B$46="Sim",INDEX(Matriz!$B$18:$R$18,1,MATCH($U21,Matriz!$B$3:$R$3,0)),NA()) -> #N/A | AK21: =IF($B$47="Sim",INDEX(Matriz!$B$19:$R$19,1,MATCH($U21,Matriz!$B$3:$R$3,0)),NA()) -> #N/A | AL21: =IF($B$48="Sim",INDEX(Matriz!$B$20:$R$20,1,MATCH($U21,Matriz!$B$3:$R$3,0)),NA()) -> #N/A | AM21: =INDEX(Matriz!$B$21:$R$21,1,MATCH($U21,Matriz!$B$3:$R$3,0)) -> 0 | AN21: =INDEX(Matriz!$B$22:$R$22,1,MATCH($U21,Matriz!$B$3:$R$3,0)) -> 0 | AO21: =INDEX(Matriz!$B$23:$R$23,1,MATCH($U21,Matriz!$B$3:$R$3,0)) -> 0
A22: E1 — Mercados Financeiros | B22: =INDEX(Matriz!$B$19:$R$19,1,MATCH(VALUE($B$3),Matriz!$B$3:$R$3,0)) -> 0 | C22: =B22/SUM($B$7:$B$23) -> 0 | U22: 2026 | V22: =IF($B$32="Sim",INDEX(Matriz!$B$4:$R$4,1,MATCH($U22,Matriz!$B$3:$R$3,0)),NA()) -> #N/A | W22: =IF($B$33="Sim",INDEX(Matriz!$B$5:$R$5,1,MATCH($U22,Matriz!$B$3:$R$3,0)),NA()) -> #N/A | X22: =IF($B$34="Sim",INDEX(Matriz!$B$6:$R$6,1,MATCH($U22,Matriz!$B$3:$R$3,0)),NA()) -> #N/A | Y22: =IF($B$35="Sim",INDEX(Matriz!$B$7:$R$7,1,MATCH($U22,Matriz!$B$3:$R$3,0)),NA()) -> #N/A | Z22: =IF($B$36="Sim",INDEX(Matriz!$B$8:$R$8,1,MATCH($U22,Matriz!$B$3:$R$3,0)),NA()) -> #N/A | AA22: =IF($B$37="Sim",INDEX(Matriz!$B$9:$R$9,1,MATCH($U22,Matriz!$B$3:$R$3,0)),NA()) -> 0 | AB22: =IF($B$38="Sim",INDEX(Matriz!$B$10:$R$10,1,MATCH($U22,Matriz!$B$3:$R$3,0)),NA()) -> #N/A | AC22: =IF($B$39="Sim",INDEX(Matriz!$B$11:$R$11,1,MATCH($U22,Matriz!$B$3:$R$3,0)),NA()) -> #N/A | AD22: =IF($B$40="Sim",INDEX(Matriz!$B$12:$R$12,1,MATCH($U22,Matriz!$B$3:$R$3,0)),NA()) -> #N/A | AE22: =IF($B$41="Sim",INDEX(Matriz!$B$13:$R$13,1,MATCH($U22,Matriz!$B$3:$R$3,0)),NA()) -> #N/A | AF22: =IF($B$42="Sim",INDEX(Matriz!$B$14:$R$14,1,MATCH($U22,Matriz!$B$3:$R$3,0)),NA()) -> #N/A | AG22: =IF($B$43="Sim",INDEX(Matriz!$B$15:$R$15,1,MATCH($U22,Matriz!$B$3:$R$3,0)),NA()) -> #N/A | AH22: =IF($B$44="Sim",INDEX(Matriz!$B$16:$R$16,1,MATCH($U22,Matriz!$B$3:$R$3,0)),NA()) -> #N/A | AI22: =IF($B$45="Sim",INDEX(Matriz!$B$17:$R$17,1,MATCH($U22,Matriz!$B$3:$R$3,0)),NA()) -> #N/A | AJ22: =IF($B$46="Sim",INDEX(Matriz!$B$18:$R$18,1,MATCH($U22,Matriz!$B$3:$R$3,0)),NA()) -> #N/A | AK22: =IF($B$47="Sim",INDEX(Matriz!$B$19:$R$19,1,MATCH($U22,Matriz!$B$3:$R$3,0)),NA()) -> #N/A | AL22: =IF($B$48="Sim",INDEX(Matriz!$B$20:$R$20,1,MATCH($U22,Matriz!$B$3:$R$3,0)),NA()) -> #N/A | AM22: =INDEX(Matriz!$B$21:$R$21,1,MATCH($U22,Matriz!$B$3:$R$3,0)) -> 0 | AN22: =INDEX(Matriz!$B$22:$R$22,1,MATCH($U22,Matriz!$B$3:$R$3,0)) -> 0 | AO22: =INDEX(Matriz!$B$23:$R$23,1,MATCH($U22,Matriz!$B$3:$R$3,0)) -> 0
A23: E2 — Demanda de Bens e Complementaridade | B23: =INDEX(Matriz!$B$20:$R$20,1,MATCH(VALUE($B$3),Matriz!$B$3:$R$3,0)) -> 0 | C23: =B23/SUM($B$7:$B$23) -> 0
A30: Filtro de tópicos — série temporal
A31: Tópico | B31: Incluir?
A32: 01 — Contas Nacionais | B32: Não
A33: 02 — Balanço de Pagamentos | B33: Não
A34: 03 — Sistema Monetário | B34: Não
A35: 04 — Demanda por Moeda | B35: Não
A36: 05 — IS-LM | B36: Não
A37: 06 — IS-LM-BP | B37: Sim
A38: 07a — Paridades | B38: Não
A39: 07b — OA-DA | B39: Não
A40: 08 — Curva de Phillips | B40: Não
A41: 09 — Expectativas, Novos Clássicos e Novos Keynesianos | B41: Não
A42: 10 — Ciclos Reais de Negócios (RBC) | B42: Não
... A48: E2 — Demanda de Bens e Complementaridade | B48: Não

Sheet Base_Itens
A1: Base detalhada — classificação item a item
A2: Regra de peso: item V/F = 1; questão aberta/numérica = 5 itens equivalentes. Se um mesmo item pertencer a n tópicos, repita o mesmo Item_ID em n linhas (uma por tópico): cada linha recebe Peso base/n.
A4: Ano | B4: Questão | C4: Item | D4: Tipo | E4: Item_ID | F4: Peso base | G4: Tópico | H4: n tópicos | I4: Pontos do tópico | J4: Observação | K4: Fonte/URL
A5: 2010 | B5: 1 | C5: 0 | D5: V/F | E5: =IF(A5="","",TEXT(A5,"0")&"-Q"&TEXT(B5,"0")&"-"&IF(C5="","ABERTA",C5)) -> 2010-Q1-0 | F5: =IF(D5="V/F",1,IF(D5="Aberta/numérica",5,"")) -> 1 | G5: 01 — Contas Nacionais | H5: =IF(A5="","",IF(C5="",COUNTIFS($A$5:$A$1504,A5,$B$5:$B$1504,B5,$C$5:$C$1504,"",$D$5:$D$1504,D5),COUNTIFS($A$5:$A$1504,A5,$B$5:$B$1504,B5,$C$5:$C$1504,C5,$D$5:$D$1504,D5))) -> 1 | I5: =IF(OR(F5="",H5="",G5=""),"",F5/H5) -> 1 | J5: Identidade do produto e absorção em economia aberta. | K5: Prova Macroeconomia 2010.pdf — p. 5 — Q1 item 0
A6: 2010 | B6: 1 | C6: 1 | D6: V/F | E6: =IF(A6="","",TEXT(A6,"0")&"-Q"&TEXT(B6,"0")&"-"&IF(C6="","ABERTA",C6)) -> 2010-Q1-1 | F6: =IF(D6="V/F",1,IF(D6="Aberta/numérica",5,"")) -> 1 | G6: 01 — Contas Nacionais | H6: =IF(A6="","",IF(C6="",COUNTIFS($A$5:$A$1504,A6,$B$5:$B$1504,B6,$C$5:$C$1504,"",$D$5:$D$1504,D6),COUNTIFS($A$5:$A$1504,A6,$B$5:$B$1504,B6,$C$5:$C$1504,C6,$D$5:$D$1504,D6))) -> 1 | I6: =IF(OR(F6="",H6="",G6=""),"",F6/H6) -> 1 | J6: Identidade poupança-investimento e saldo corrente. | K6: Prova Macroeconomia 2010.pdf — p. 5 — Q1 item 1
A7: 2010 | B7: 1 | C7: 2 | D7: V/F | E7: =IF(A7="","",TEXT(A7,"0")&"-Q"&TEXT(B7,"0")&"-"&IF(C7="","ABERTA",C7)) -> 2010-Q1-2 | F7: =IF(D7="V/F",1,IF(D7="Aberta/numérica",5,"")) -> 1 | G7: 01 — Contas Nacionais | H7: =IF(A7="","",IF(C7="",COUNTIFS($A$5:$A$1504,A7,$B$5:$B$1504,B7,$C$5:$C$1504,"",$D$5:$D$1504,D7),COUNTIFS($A$5:$A$1504,A7,$B$5:$B$1504,B7,$C$5:$C$1504,C7,$D$5:$D$1504,D7))) -> 1 | I7: =IF(OR(F7="",H7="",G7=""),"",F7/H7) -> 1 | J7: Consumo público versus transferências nas contas nacionais. | K7: Prova Macroeconomia 2010.pdf — p. 5 — Q1 item 2
A8: 2010 | B8: 1 | C8: 3 | D8: V/F | E8: =IF(A8="","",TEXT(A8,"0")&"-Q"&TEXT(B8,"0")&"-"&IF(C8="","ABERTA",C8)) -> 2010-Q1-3 | F8: =IF(D8="V/F",1,IF(D8="Aberta/numérica",5,"")) -> 1 | G8: 01 — Contas Nacionais | H8: =IF(A8="","",IF(C8="",COUNTIFS($A$5:$A$1504,A8,$B$5:$B$1504,B8,$C$5:$C$1504,"",$D$5:$D$1504,D8),COUNTIFS($A$5:$A$1504,A8,$B$5:$B$1504,B8,$C$5:$C$1504,C8,$D$5:$D$1504,D8))) -> 1 | I8: =IF(OR(F8="",H8="",G8=""),"",F8/H8) -> 1 | J8: PIB nominal, PIB real e deflator. | K8: Prova Macroeconomia 2010.pdf — p. 5 — Q1 item 3
A9: 2010 | B9: 1 | C9: 4 | D9: V/F | E9: =IF(A9="","",TEXT(A9,"0")&"-Q"&TEXT(B9,"0")&"-"&IF(C9="","ABERTA",C9)) -> 2010-Q1-4 | F9: =IF(D9="V/F",1,IF(D9="Aberta/numérica",5,"")) -> 1 | G9: 01 — Contas Nacionais | H9: =IF(A9="","",IF(C9="",COUNTIFS($A$5:$A$1504,A9,$B$5:$B$1504,B9,$C$5:$C$1504,"",$D$5:$D$1504,D9),COUNTIFS($A$5:$A$1504,A9,$B$5:$B$1504,B9,$C$5:$C$1504,C9,$D$5:$D$1504,D9))) -> 1 | I9: =IF(OR(F9="",H9="",G9=""),"",F9/H9) -> 1 | J9: PIB, renda nacional líquida e depreciação. | K9: Prova Macroeconomia 2010.pdf — p. 5 — Q1 item 4
A10: 2010 | B10: 2 | C10: 0 | D10: V/F | E10: =IF(A10="","",TEXT(A10,"0")&"-Q"&TEXT(B10,"0")&"-"&IF(C10="","ABERTA",C10)) -> 2010-Q2-0 | F10: =IF(D10="V/F",1,IF(D10="Aberta/numérica",5,"")) -> 1 | G10: 05 — IS-LM | H10: =IF(A10="","",IF(C10="",COUNTIFS($A$5:$A$1504,A10,$B$5:$B$1504,B10,$C$5:$C$1504,"",$D$5:$D$1504,D10),COUNTIFS($A$5:$A$1504,A10,$B$5:$B$1504,B10,$C$5:$C$1504,C10,$D$5:$D$1504,D10))) -> 1 | I10: =IF(OR(F10="",H10="",G10=""),"",F10/H10) -> 1 | J10: IS-LM com meta de juros: choque de demanda por moeda. | K10: Prova Macroeconomia 2010.pdf — p. 6 — Q2 item 0
A11: 2010 | B11: 2 | C11: 1 | D11: V/F | E11: =IF(A11="","",TEXT(A11,"0")&"-Q"&TEXT(B11,"0")&"-"&IF(C11="","ABERTA",C11)) -> 2010-Q2-1 | F11: =IF(D11="V/F",1,IF(D11="Aberta/numérica",5,"")) -> 1 | G11: 05 — IS-LM | H11: =IF(A11="","",IF(C11="",COUNTIFS($A$5:$A$1504,A11,$B$5:$B$1504,B11,$C$5:$C$1504,"",$D$5:$D$1504,D11),COUNTIFS($A$5:$A$1504,A11,$B$5:$B$1504,B11,$C$5:$C$1504,C11,$D$5:$D$1504,D11))) -> 1 | I11: =IF(OR(F11="",H11="",G11=""),"",F11/H11) -> 1 | J11: IS-LM: escolha do instrumento e estabilização diante de choques. | K11: Prova Macroeconomia 2010.pdf — p. 6 — Q2 item 1
A12: 2010 | B12: 2 | C12: 2 | D12: V/F | E12: =IF(A12="","",TEXT(A12,"0")&"-Q"&TEXT(B12,"0")&"-"&IF(C12="","ABERTA",C12)) -> 2010-Q2-2 | F12: =IF(D12="V/F",1,IF(D12="Aberta/numérica",5,"")) -> 1 | G12: 05 — IS-LM | H12: =IF(A12="","",IF(C12="",COUNTIFS($A$5:$A$1504,A12,$B$5:$B$1504,B12,$C$5:$C$1504,"",$D$5:$D$1504,D12),COUNTIFS($A$5:$A$1504,A12,$B$5:$B$1504,B12,$C$5:$C$1504,C12,$D$5:$D$1504,D12))) -> 1 | I12: =IF(OR(F12="",H12="",G12=""),"",F12/H12) -> 1 | J12: Multiplicador fiscal com juros fixos versus moeda fixa. | K12: Prova Macroeconomia 2010.pdf — p. 6 — Q2 item 2
A13: 2010 | B13: 2 | C13: 3 | D13: V/F | E13: =IF(A13="","",TEXT(A13,"0")&"-Q"&TEXT(B13,"0")&"-"&IF(C13="","ABERTA",C13)) -> 2010-Q2-3 | F13: =IF(D13="V/F",1,IF(D13="Aberta/numérica",5,"")) -> 1 | G13: 05 — IS-LM | H13: =IF(A13="","",IF(C13="",COUNTIFS($A$5:$A$1504,A13,$B$5:$B$1504,B13,$C$5:$C$1504,"",$D$5:$D$1504,D13),COUNTIFS($A$5:$A$1504,A13,$B$5:$B$1504,B13,$C$5:$C$1504,C13,$D$5:$D$1504,D13))) -> 1 | I13: =IF(OR(F13="",H13="",G13=""),"",F13/H13) -> 1 | J13: Acomodação monetária para manter os juros no IS-LM. | K13: Prova Macroeconomia 2010.pdf — p. 6 — Q2 item 3
A14: 2010 | B14: 2 | C14: 4 | D14: V/F | E14: =IF(A14="","",TEXT(A14,"0")&"-Q"&TEXT(B14,"0")&"-"&IF(C14="","ABERTA",C14)) -> 2010-Q2-4 | F14: =IF(D14="V/F",1,IF(D14="Aberta/numérica",5,"")) -> 1 | G14: 03 — Sistema Monetário | H14: =IF(A14="","",IF(C14="",COUNTIFS($A$5:$A$1504,A14,$B$5:$B$1504,B14,$C$5:$C$1504,"",$D$5:$D$1504,D14),COUNTIFS($A$5:$A$1504,A14,$B$5:$B$1504,B14,$C$5:$C$1504,C14,$D$5:$D$1504,D14))) -> 1 | I14: =IF(OR(F14="",H14="",G14=""),"",F14/H14) -> 1 | J14: Composição de M1, multiplicador e compensação via mercado aberto. | K14: Prova Macroeconomia 2010.pdf — p. 6 — Q2 item 4
A15: 2010 | B15: 3 | C15: 0 | D15: V/F | E15: =IF(A15="","",TEXT(A15,"0")&"-Q"&TEXT(B15,"0")&"-"&IF(C15="","ABERTA",C15)) -> 2010-Q3-0 | F15: =IF(D15="V/F",1,IF(D15="Aberta/numérica",5,"")) -> 1 | G15: 01 — Contas Nacionais | H15: =IF(A15="","",IF(C15="",COUNTIFS($A$5:$A$1504,A15,$B$5:$B$1504,B15,$C$5:$C$1504,"",$D$5:$D$1504,D15),COUNTIFS($A$5:$A$1504,A15,$B$5:$B$1504,B15,$C$5:$C$1504,C15,$D$5:$D$1504,D15))) -> 1 | I15: =IF(OR(F15="",H15="",G15=""),"",F15/H15) -> 1 | J15: PIB real a preços constantes. | K15: Prova Macroeconomia 2010.pdf — p. 7 — Q3 item 0
A16: 2010 | B16: 3 | C16: 1 | D16: V/F | E16: =IF(A16="","",TEXT(A16,"0")&"-Q"&TEXT(B16,"0")&"-"&IF(C16="","ABERTA",C16)) -> 2010-Q3-1 | F16: =IF(D16="V/F",1,IF(D16="Aberta/numérica",5,"")) -> 1 | G16: 01 — Contas Nacionais | H16: =IF(A16="","",IF(C16="",COUNTIFS($A$5:$A$1504,A16,$B$5:$B$1504,B16,$C$5:$C$1504,"",$D$5:$D$1504,D16),COUNTIFS($A$5:$A$1504,A16,$B$5:$B$1504,B16,$C$5:$C$1504,C16,$D$5:$D$1504,D16))) -> 1 | I16: =IF(OR(F16="",H16="",G16=""),"",F16/H16) -> 1 | J16: Valoração da produção a preços do ano-base. | K16: Prova Macroeconomia 2010.pdf — p. 7 — Q3 item 1
... A60: 2010 | B60: 11 | C60: 4 | D60: V/F | E60: =IF(A60="","",TEXT(A60,"0")&"-Q"&TEXT(B60,"0")&"-"&IF(C60="","ABERTA",C60)) -> 2010-Q11-4 | F60: =IF(D60="V/F",1,IF(D60="Aberta/numérica",5,"")) -> 1 | G60: 11 — Crescimento Econômico | H60: =IF(A60="","",IF(C60="",COUNTIFS($A$5:$A$1504,A60,$B$5:$B$1504,B60,$C$5:$C$1504,"",$D$5:$D$1504,D60),COUNTIFS($A$5:$A$1504,A60,$B$5:$B$1504,B60,$C$5:$C$1504,C60,$D$5:$D$1504,D60))) -> 1 | I60: =IF(OR(F60="",H60="",G60=""),"",F60/H60) -> 1 | J60: Crescimento semiendógeno e trajetória equilibrada. | K60: Prova Macroeconomia 2010.pdf — p. 16 — Q11 item 4
A61: 2010 | B61: 12 | D61: Aberta/numérica | E61: =IF(A61="","",TEXT(A61,"0")&"-Q"&TEXT(B61,"0")&"-"&IF(C61="","ABERTA",C61)) -> 2010-Q12-ABERTA | F61: =IF(D61="V/F",1,IF(D61="Aberta/numérica",5,"")) -> 5 | G61: 07a — Paridades | H61: =IF(A61="","",IF(C61="",COUNTIFS($A$5:$A$1504,A61,$B$5:$B$1504,B61,$C$5:$C$1504,"",$D$5:$D$1504,D61),COUNTIFS($A$5:$A$1504,A61,$B$5:$B$1504,B61,$C$5:$C$1504,C61,$D$5:$D$1504,D61))) -> 1 | I61: =IF(OR(F61="",H61="",G61=""),"",F61/H61) -> 5 | J61: Paridade descoberta de juros e valor de resgate em moeda estrangeira. | K61: Prova Macroeconomia 2010.pdf — p. 17 — Q12 — Tipo B
A62: 2010 | B62: 13 | D62: Aberta/numérica | E62: =IF(A62="","",TEXT(A62,"0")&"-Q"&TEXT(B62,"0")&"-"&IF(C62="","ABERTA",C62)) -> 2010-Q13-ABERTA | F62: =IF(D62="V/F",1,IF(D62="Aberta/numérica",5,"")) -> 5 | G62: 07b — OA-DA | H62: =IF(A62="","",IF(C62="",COUNTIFS($A$5:$A$1504,A62,$B$5:$B$1504,B62,$C$5:$C$1504,"",$D$5:$D$1504,D62),COUNTIFS($A$5:$A$1504,A62,$B$5:$B$1504,B62,$C$5:$C$1504,C62,$D$5:$D$1504,D62))) -> 2 | I62: =IF(OR(F62="",H62="",G62=""),"",F62/H62) -> 2.5 | J62: Item misto: demanda agregada monetária, Phillips e lei de Okun. | K62: Prova Macroeconomia 2010.pdf — p. 18 — Q13 — Tipo B
A63: 2010 | B63: 13 | D63: Aberta/numérica | E63: =IF(A63="","",TEXT(A63,"0")&"-Q"&TEXT(B63,"0")&"-"&IF(C63="","ABERTA",C63)) -> 2010-Q13-ABERTA | F63: =IF(D63="V/F",1,IF(D63="Aberta/numérica",5,"")) -> 5 | G63: 08 — Curva de Phillips | H63: =IF(A63="","",IF(C63="",COUNTIFS($A$5:$A$1504,A63,$B$5:$B$1504,B63,$C$5:$C$1504,"",$D$5:$D$1504,D63),COUNTIFS($A$5:$A$1504,A63,$B$5:$B$1504,B63,$C$5:$C$1504,C63,$D$5:$D$1504,D63))) -> 2 | I63: =IF(OR(F63="",H63="",G63=""),"",F63/H63) -> 2.5 | J63: Item misto: demanda agregada monetária, Phillips e lei de Okun. | K63: Prova Macroeconomia 2010.pdf — p. 18 — Q13 — Tipo B
A64: 2010 | B64: 14 | D64: Aberta/numérica | E64: =IF(A64="","",TEXT(A64,"0")&"-Q"&TEXT(B64,"0")&"-"&IF(C64="","ABERTA",C64)) -> 2010-Q14-ABERTA | F64: =IF(D64="V/F",1,IF(D64="Aberta/numérica",5,"")) -> 5 | G64: 03 — Sistema Monetário | H64: =IF(A64="","",IF(C64="",COUNTIFS($A$5:$A$1504,A64,$B$5:$B$1504,B64,$C$5:$C$1504,"",$D$5:$D$1504,D64),COUNTIFS($A$5:$A$1504,A64,$B$5:$B$1504,B64,$C$5:$C$1504,C64,$D$5:$D$1504,D64))) -> 3 | I64: =IF(OR(F64="",H64="",G64=""),"",F64/H64) -> 1.6666667 | J64: Item misto: multiplicador monetário, teoria quantitativa e receita de senhoriagem/PIB. | K64: Prova Macroeconomia 2010.pdf — p. 19 — Q14 — Tipo B
A65: 2010 | B65: 14 | D65: Aberta/numérica | E65: =IF(A65="","",TEXT(A65,"0")&"-Q"&TEXT(B65,"0")&"-"&IF(C65="","ABERTA",C65)) -> 2010-Q14-ABERTA | F65: =IF(D65="V/F",1,IF(D65="Aberta/numérica",5,"")) -> 5 | G65: 04 — Demanda por Moeda | H65: =IF(A65="","",IF(C65="",COUNTIFS($A$5:$A$1504,A65,$B$5:$B$1504,B65,$C$5:$C$1504,"",$D$5:$D$1504,D65),COUNTIFS($A$5:$A$1504,A65,$B$5:$B$1504,B65,$C$5:$C$1504,C65,$D$5:$D$1504,D65))) -> 3 | I65: =IF(OR(F65="",H65="",G65=""),"",F65/H65) -> 1.6666667 | J65: Item misto: multiplicador monetário, teoria quantitativa e receita de senhoriagem/PIB. | K65: Prova Macroeconomia 2010.pdf — p. 19 — Q14 — Tipo B
A66: 2010 | B66: 14 | D66: Aberta/numérica | E66: =IF(A66="","",TEXT(A66,"0")&"-Q"&TEXT(B66,"0")&"-"&IF(C66="","ABERTA",C66)) -> 2010-Q14-ABERTA | F66: =IF(D66="V/F",1,IF(D66="Aberta/numérica",5,"")) -> 5 | G66: 14 — Dívida Pública e Senhoriagem | H66: =IF(A66="","",IF(C66="",COUNTIFS($A$5:$A$1504,A66,$B$5:$B$1504,B66,$C$5:$C$1504,"",$D$5:$D$1504,D66),COUNTIFS($A$5:$A$1504,A66,$B$5:$B$1504,B66,$C$5:$C$1504,C66,$D$5:$D$1504,D66))) -> 3 | I66: =IF(OR(F66="",H66="",G66=""),"",F66/H66) -> 1.6666667 | J66: Item misto: multiplicador monetário, teoria quantitativa e receita de senhoriagem/PIB. | K66: Prova Macroeconomia 2010.pdf — p. 19 — Q14 — Tipo B
A67: 2010 | B67: 15 | D67: Aberta/numérica | E67: =IF(A67="","",TEXT(A67,"0")&"-Q"&TEXT(B67,"0")&"-"&IF(C67="","ABERTA",C67)) -> 2010-Q15-ABERTA | F67: =IF(D67="V/F",1,IF(D67="Aberta/numérica",5,"")) -> 5 | G67: 06 — IS-LM-BP | H67: =IF(A67="","",IF(C67="",COUNTIFS($A$5:$A$1504,A67,$B$5:$B$1504,B67,$C$5:$C$1504,"",$D$5:$D$1504,D67),COUNTIFS($A$5:$A$1504,A67,$B$5:$B$1504,B67,$C$5:$C$1504,C67,$D$5:$D$1504,D67))) -> 1 | I67: =IF(OR(F67="",H67="",G67=""),"",F67/H67) -> 5 | J67: Mundell-Fleming com câmbio fixo: contração fiscal e exportações líquidas. | K67: Prova Macroeconomia 2010.pdf — p. 20 — Q15 — Tipo B
A68: 2011 | B68: 1 | C68: 0 | D68: V/F | E68: =IF(A68="","",TEXT(A68,"0")&"-Q"&TEXT(B68,"0")&"-"&IF(C68="","ABERTA",C68)) -> 2011-Q1-0 | F68: =IF(D68="V/F",1,IF(D68="Aberta/numérica",5,"")) -> 1 | G68: 01 — Contas Nacionais | H68: =IF(A68="","",IF(C68="",COUNTIFS($A$5:$A$1504,A68,$B$5:$B$1504,B68,$C$5:$C$1504,"",$D$5:$D$1504,D68),COUNTIFS($A$5:$A$1504,A68,$B$5:$B$1504,B68,$C$5:$C$1504,C68,$D$5:$D$1504,D68))) -> 1 | I68: =IF(OR(F68="",H68="",G68=""),"",F68/H68) -> 1 | J68: Produto líquido a custo de fatores versus PIB a preços de mercado. | K68: Prova Macroeconomia 2011.doc — Q1 item 0
A69: 2011 | B69: 1 | C69: 1 | D69: V/F | E69: =IF(A69="","",TEXT(A69,"0")&"-Q"&TEXT(B69,"0")&"-"&IF(C69="","ABERTA",C69)) -> 2011-Q1-1 | F69: =IF(D69="V/F",1,IF(D69="Aberta/numérica",5,"")) -> 1 | G69: 01 — Contas Nacionais | H69: =IF(A69="","",IF(C69="",COUNTIFS($A$5:$A$1504,A69,$B$5:$B$1504,B69,$C$5:$C$1504,"",$D$5:$D$1504,D69),COUNTIFS($A$5:$A$1504,A69,$B$5:$B$1504,B69,$C$5:$C$1504,C69,$D$5:$D$1504,D69))) -> 1 | I69: =IF(OR(F69="",H69="",G69=""),"",F69/H69) -> 1 | J69: Investimento público a partir das contas do governo. | K69: Prova Macroeconomia 2011.doc — Q1 item 1
A70: 2011 | B70: 1 | C70: 2 | D70: V/F | E70: =IF(A70="","",TEXT(A70,"0")&"-Q"&TEXT(B70,"0")&"-"&IF(C70="","ABERTA",C70)) -> 2011-Q1-2 | F70: =IF(D70="V/F",1,IF(D70="Aberta/numérica",5,"")) -> 1 | G70: 01 — Contas Nacionais | H70: =IF(A70="","",IF(C70="",COUNTIFS($A$5:$A$1504,A70,$B$5:$B$1504,B70,$C$5:$C$1504,"",$D$5:$D$1504,D70),COUNTIFS($A$5:$A$1504,A70,$B$5:$B$1504,B70,$C$5:$C$1504,C70,$D$5:$D$1504,D70))) -> 1 | I70: =IF(OR(F70="",H70="",G70=""),"",F70/H70) -> 1 | J70: Poupança privada nas contas nacionais. | K70: Prova Macroeconomia 2011.doc — Q1 item 2
A71: 2011 | B71: 1 | C71: 3 | D71: V/F | E71: =IF(A71="","",TEXT(A71,"0")&"-Q"&TEXT(B71,"0")&"-"&IF(C71="","ABERTA",C71)) -> 2011-Q1-3 | F71: =IF(D71="V/F",1,IF(D71="Aberta/numérica",5,"")) -> 1 | G71: 01 — Contas Nacionais | H71: =IF(A71="","",IF(C71="",COUNTIFS($A$5:$A$1504,A71,$B$5:$B$1504,B71,$C$5:$C$1504,"",$D$5:$D$1504,D71),COUNTIFS($A$5:$A$1504,A71,$B$5:$B$1504,B71,$C$5:$C$1504,C71,$D$5:$D$1504,D71))) -> 1 | I71: =IF(OR(F71="",H71="",G71=""),"",F71/H71) -> 1 | J71: Investimento bruto versus líquido. | K71: Prova Macroeconomia 2011.doc — Q1 item 3
A72: 2011 | B72: 1 | C72: 4 | D72: V/F | E72: =IF(A72="","",TEXT(A72,"0")&"-Q"&TEXT(B72,"0")&"-"&IF(C72="","ABERTA",C72)) -> 2011-Q1-4 | F72: =IF(D72="V/F",1,IF(D72="Aberta/numérica",5,"")) -> 1 | G72: 01 — Contas Nacionais | H72: =IF(A72="","",IF(C72="",COUNTIFS($A$5:$A$1504,A72,$B$5:$B$1504,B72,$C$5:$C$1504,"",$D$5:$D$1504,D72),COUNTIFS($A$5:$A$1504,A72,$B$5:$B$1504,B72,$C$5:$C$1504,C72,$D$5:$D$1504,D72))) -> 1 | I72: =IF(OR(F72="",H72="",G72=""),"",F72/H72) -> 1 | J72: Poupança externa e déficit corrente. | K72: Prova Macroeconomia 2011.doc — Q1 item 4
A73: 2011 | B73: 2 | C73: 0 | D73: V/F | E73: =IF(A73="","",TEXT(A73,"0")&"-Q"&TEXT(B73,"0")&"-"&IF(C73="","ABERTA",C73)) -> 2011-Q2-0 | F73: =IF(D73="V/F",1,IF(D73="Aberta/numérica",5,"")) -> 1 | G73: 03 — Sistema Monetário | H73: =IF(A73="","",IF(C73="",COUNTIFS($A$5:$A$1504,A73,$B$5:$B$1504,B73,$C$5:$C$1504,"",$D$5:$D$1504,D73),COUNTIFS($A$5:$A$1504,A73,$B$5:$B$1504,B73,$C$5:$C$1504,C73,$D$5:$D$1504,D73))) -> 1 | I73: =IF(OR(F73="",H73="",G73=""),"",F73/H73) -> 1 | J73: Composição dos meios de pagamento. | K73: Prova Macroeconomia 2011.doc — Q2 item 0
A74: 2011 | B74: 2 | C74: 1 | D74: V/F | E74: =IF(A74="","",TEXT(A74,"0")&"-Q"&TEXT(B74,"0")&"-"&IF(C74="","ABERTA",C74)) -> 2011-Q2-1 | F74: =IF(D74="V/F",1,IF(D74="Aberta/numérica",5,"")) -> 1 | G74: 03 — Sistema Monetário | H74: =IF(A74="","",IF(C74="",COUNTIFS($A$5:$A$1504,A74,$B$5:$B$1504,B74,$C$5:$C$1504,"",$D$5:$D$1504,D74),COUNTIFS($A$5:$A$1504,A74,$B$5:$B$1504,B74,$C$5:$C$1504,C74,$D$5:$D$1504,D74))) -> 1 | I74: =IF(OR(F74="",H74="",G74=""),"",F74/H74) -> 1 | J74: Aplicação financeira e contração de M1. | K74: Prova Macroeconomia 2011.doc — Q2 item 1
A75: 2011 | B75: 2 | C75: 2 | D75: V/F | E75: =IF(A75="","",TEXT(A75,"0")&"-Q"&TEXT(B75,"0")&"-"&IF(C75="","ABERTA",C75)) -> 2011-Q2-2 | F75: =IF(D75="V/F",1,IF(D75="Aberta/numérica",5,"")) -> 1 | G75: 03 — Sistema Monetário | H75: =IF(A75="","",IF(C75="",COUNTIFS($A$5:$A$1504,A75,$B$5:$B$1504,B75,$C$5:$C$1504,"",$D$5:$D$1504,D75),COUNTIFS($A$5:$A$1504,A75,$B$5:$B$1504,B75,$C$5:$C$1504,C75,$D$5:$D$1504,D75))) -> 1 | I75: =IF(OR(F75="",H75="",G75=""),"",F75/H75) -> 1 | J75: Reservas voluntárias e multiplicador monetário. | K75: Prova Macroeconomia 2011.doc — Q2 item 2
A76: 2011 | B76: 2 | C76: 3 | D76: V/F | E76: =IF(A76="","",TEXT(A76,"0")&"-Q"&TEXT(B76,"0")&"-"&IF(C76="","ABERTA",C76)) -> 2011-Q2-3 | F76: =IF(D76="V/F",1,IF(D76="Aberta/numérica",5,"")) -> 1 | G76: 03 — Sistema Monetário | H76: =IF(A76="","",IF(C76="",COUNTIFS($A$5:$A$1504,A76,$B$5:$B$1504,B76,$C$5:$C$1504,"",$D$5:$D$1504,D76),COUNTIFS($A$5:$A$1504,A76,$B$5:$B$1504,B76,$C$5:$C$1504,C76,$D$5:$D$1504,D76))) -> 1 | I76: =IF(OR(F76="",H76="",G76=""),"",F76/H76) -> 1 | J76: Depósitos do Tesouro e base monetária. | K76: Prova Macroeconomia 2011.doc — Q2 item 3
A77: 2011 | B77: 2 | C77: 4 | D77: V/F | E77: =IF(A77="","",TEXT(A77,"0")&"-Q"&TEXT(B77,"0")&"-"&IF(C77="","ABERTA",C77)) -> 2011-Q2-4 | F77: =IF(D77="V/F",1,IF(D77="Aberta/numérica",5,"")) -> 1 | G77: 03 — Sistema Monetário | H77: =IF(A77="","",IF(C77="",COUNTIFS($A$5:$A$1504,A77,$B$5:$B$1504,B77,$C$5:$C$1504,"",$D$5:$D$1504,D77),COUNTIFS($A$5:$A$1504,A77,$B$5:$B$1504,B77,$C$5:$C$1504,C77,$D$5:$D$1504,D77))) -> 1 | I77: =IF(OR(F77="",H77="",G77=""),"",F77/H77) -> 1 | J77: Cálculo de M1 a partir do multiplicador. | K77: Prova Macroeconomia 2011.doc — Q2 item 4
A78: 2011 | B78: 3 | C78: 0 | D78: V/F | E78: =IF(A78="","",TEXT(A78,"0")&"-Q"&TEXT(B78,"0")&"-"&IF(C78="","ABERTA",C78)) -> 2011-Q3-0 | F78: =IF(D78="V/F",1,IF(D78="Aberta/numérica",5,"")) -> 1 | G78: 02 — Balanço de Pagamentos | H78: =IF(A78="","",IF(C78="",COUNTIFS($A$5:$A$1504,A78,$B$5:$B$1504,B78,$C$5:$C$1504,"",$D$5:$D$1504,D78),COUNTIFS($A$5:$A$1504,A78,$B$5:$B$1504,B78,$C$5:$C$1504,C78,$D$5:$D$1504,D78))) -> 1 | I78: =IF(OR(F78="",H78="",G78=""),"",F78/H78) -> 1 | J78: Transações correntes e passivo externo líquido. | K78: Prova Macroeconomia 2011.doc — Q3 item 0
A79: 2011 | B79: 3 | C79: 1 | D79: V/F | E79: =IF(A79="","",TEXT(A79,"0")&"-Q"&TEXT(B79,"0")&"-"&IF(C79="","ABERTA",C79)) -> 2011-Q3-1 | F79: =IF(D79="V/F",1,IF(D79="Aberta/numérica",5,"")) -> 1 | G79: 02 — Balanço de Pagamentos | H79: =IF(A79="","",IF(C79="",COUNTIFS($A$5:$A$1504,A79,$B$5:$B$1504,B79,$C$5:$C$1504,"",$D$5:$D$1504,D79),COUNTIFS($A$5:$A$1504,A79,$B$5:$B$1504,B79,$C$5:$C$1504,C79,$D$5:$D$1504,D79))) -> 1 | I79: =IF(OR(F79="",H79="",G79=""),"",F79/H79) -> 1 | J79: Dívida externa bruta versus passivo externo. | K79: Prova Macroeconomia 2011.doc — Q3 item 1
... A132: 2011 | B132: 13 | C132: 4 | D132: V/F | E132: =IF(A132="","",TEXT(A132,"0")&"-Q"&TEXT(B132,"0")&"-"&IF(C132="","ABERTA",C132)) -> 2011-Q13-4 | F132: =IF(D132="V/F",1,IF(D132="Aberta/numérica",5,"")) -> 1 | G132: 14 — Dívida Pública e Senhoriagem | H132: =IF(A132="","",IF(C132="",COUNTIFS($A$5:$A$1504,A132,$B$5:$B$1504,B132,$C$5:$C$1504,"",$D$5:$D$1504,D132),COUNTIFS($A$5:$A$1504,A132,$B$5:$B$1504,B132,$C$5:$C$1504,C132,$D$5:$D$1504,D132))) -> 1 | I132: =IF(OR(F132="",H132="",G132=""),"",F132/H132) -> 1 | J132: Dinâmica da dívida/PIB com saldo primário nulo. | K132: Prova Macroeconomia 2011.doc — Q13 item 4
A133: 2011 | B133: 14 | D133: Aberta/numérica | E133: =IF(A133="","",TEXT(A133,"0")&"-Q"&TEXT(B133,"0")&"-"&IF(C133="","ABERTA",C133)) -> 2011-Q14-ABERTA | F133: =IF(D133="V/F",1,IF(D133="Aberta/numérica",5,"")) -> 5 | G133: 05 — IS-LM | H133: =IF(A133="","",IF(C133="",COUNTIFS($A$5:$A$1504,A133,$B$5:$B$1504,B133,$C$5:$C$1504,"",$D$5:$D$1504,D133),COUNTIFS($A$5:$A$1504,A133,$B$5:$B$1504,B133,$C$5:$C$1504,C133,$D$5:$D$1504,D133))) -> 1 | I133: =IF(OR(F133="",H133="",G133=""),"",F133/H133) -> 5 | J133: Produto de equilíbrio no modelo IS-LM fechado. | K133: Prova Macroeconomia 2011.doc — Q14 — Tipo B
A134: 2011 | B134: 15 | D134: Aberta/numérica | E134: =IF(A134="","",TEXT(A134,"0")&"-Q"&TEXT(B134,"0")&"-"&IF(C134="","ABERTA",C134)) -> 2011-Q15-ABERTA | F134: =IF(D134="V/F",1,IF(D134="Aberta/numérica",5,"")) -> 5 | G134: 11 — Crescimento Econômico | H134: =IF(A134="","",IF(C134="",COUNTIFS($A$5:$A$1504,A134,$B$5:$B$1504,B134,$C$5:$C$1504,"",$D$5:$D$1504,D134),COUNTIFS($A$5:$A$1504,A134,$B$5:$B$1504,B134,$C$5:$C$1504,C134,$D$5:$D$1504,D134))) -> 1 | I134: =IF(OR(F134="",H134="",G134=""),"",F134/H134) -> 5 | J134: Solow: salário real no estado estacionário. | K134: Prova Macroeconomia 2011.doc — Q15 — Tipo B
A135: 2012 | B135: 1 | C135: 0 | D135: V/F | E135: =IF(A135="","",TEXT(A135,"0")&"-Q"&TEXT(B135,"0")&"-"&IF(C135="","ABERTA",C135)) -> 2012-Q1-0 | F135: =IF(D135="V/F",1,IF(D135="Aberta/numérica",5,"")) -> 1 | G135: 12 — Consumo | H135: =IF(A135="","",IF(C135="",COUNTIFS($A$5:$A$1504,A135,$B$5:$B$1504,B135,$C$5:$C$1504,"",$D$5:$D$1504,D135),COUNTIFS($A$5:$A$1504,A135,$B$5:$B$1504,B135,$C$5:$C$1504,C135,$D$5:$D$1504,D135))) -> 1 | I135: =IF(OR(F135="",H135="",G135=""),"",F135/H135) -> 1 | J135: Renda permanente: antecipação de renda temporária. | K135: Prova Macroeconomia 2012.pdf — p. 5 — Q1 item 0
A136: 2012 | B136: 1 | C136: 1 | D136: V/F | E136: =IF(A136="","",TEXT(A136,"0")&"-Q"&TEXT(B136,"0")&"-"&IF(C136="","ABERTA",C136)) -> 2012-Q1-1 | F136: =IF(D136="V/F",1,IF(D136="Aberta/numérica",5,"")) -> 1 | G136: 12 — Consumo | H136: =IF(A136="","",IF(C136="",COUNTIFS($A$5:$A$1504,A136,$B$5:$B$1504,B136,$C$5:$C$1504,"",$D$5:$D$1504,D136),COUNTIFS($A$5:$A$1504,A136,$B$5:$B$1504,B136,$C$5:$C$1504,C136,$D$5:$D$1504,D136))) -> 1 | I136: =IF(OR(F136="",H136="",G136=""),"",F136/H136) -> 1 | J136: Restrição de crédito e equivalência ricardiana. | K136: Prova Macroeconomia 2012.pdf — p. 5 — Q1 item 1
A137: 2012 | B137: 1 | C137: 2 | D137: V/F | E137: =IF(A137="","",TEXT(A137,"0")&"-Q"&TEXT(B137,"0")&"-"&IF(C137="","ABERTA",C137)) -> 2012-Q1-2 | F137: =IF(D137="V/F",1,IF(D137="Aberta/numérica",5,"")) -> 1 | G137: 13 — Investimento | H137: =IF(A137="","",IF(C137="",COUNTIFS($A$5:$A$1504,A137,$B$5:$B$1504,B137,$C$5:$C$1504,"",$D$5:$D$1504,D137),COUNTIFS($A$5:$A$1504,A137,$B$5:$B$1504,B137,$C$5:$C$1504,C137,$D$5:$D$1504,D137))) -> 1 | I137: =IF(OR(F137="",H137="",G137=""),"",F137/H137) -> 1 | J137: Valor presente dos lucros e viabilidade do investimento. | K137: Prova Macroeconomia 2012.pdf — p. 5 — Q1 item 2
A138: 2012 | B138: 1 | C138: 3 | D138: V/F | E138: =IF(A138="","",TEXT(A138,"0")&"-Q"&TEXT(B138,"0")&"-"&IF(C138="","ABERTA",C138)) -> 2012-Q1-3 | F138: =IF(D138="V/F",1,IF(D138="Aberta/numérica",5,"")) -> 1 | G138: 13 — Investimento | H138: =IF(A138="","",IF(C138="",COUNTIFS($A$5:$A$1504,A138,$B$5:$B$1504,B138,$C$5:$C$1504,"",$D$5:$D$1504,D138),COUNTIFS($A$5:$A$1504,A138,$B$5:$B$1504,B138,$C$5:$C$1504,C138,$D$5:$D$1504,D138))) -> 1 | I138: =IF(OR(F138="",H138="",G138=""),"",F138/H138) -> 1 | J138: Acelerador e investimento em estoques. | K138: Prova Macroeconomia 2012.pdf — p. 5 — Q1 item 3
A139: 2012 | B139: 1 | C139: 4 | D139: V/F | E139: =IF(A139="","",TEXT(A139,"0")&"-Q"&TEXT(B139,"0")&"-"&IF(C139="","ABERTA",C139)) -> 2012-Q1-4 | F139: =IF(D139="V/F",1,IF(D139="Aberta/numérica",5,"")) -> 1 | G139: 13 — Investimento | H139: =IF(A139="","",IF(C139="",COUNTIFS($A$5:$A$1504,A139,$B$5:$B$1504,B139,$C$5:$C$1504,"",$D$5:$D$1504,D139),COUNTIFS($A$5:$A$1504,A139,$B$5:$B$1504,B139,$C$5:$C$1504,C139,$D$5:$D$1504,D139))) -> 1 | I139: =IF(OR(F139="",H139="",G139=""),"",F139/H139) -> 1 | J139: Custos de ajuste e sensibilidade ao q de Tobin. | K139: Prova Macroeconomia 2012.pdf — p. 5 — Q1 item 4
A140: 2012 | B140: 2 | C140: 0 | D140: V/F | E140: =IF(A140="","",TEXT(A140,"0")&"-Q"&TEXT(B140,"0")&"-"&IF(C140="","ABERTA",C140)) -> 2012-Q2-0 | F140: =IF(D140="V/F",1,IF(D140="Aberta/numérica",5,"")) -> 1 | G140: 06 — IS-LM-BP | H140: =IF(A140="","",IF(C140="",COUNTIFS($A$5:$A$1504,A140,$B$5:$B$1504,B140,$C$5:$C$1504,"",$D$5:$D$1504,D140),COUNTIFS($A$5:$A$1504,A140,$B$5:$B$1504,B140,$C$5:$C$1504,C140,$D$5:$D$1504,D140))) -> 1 | I140: =IF(OR(F140="",H140="",G140=""),"",F140/H140) -> 1 | J140: Ajustamento externo sob câmbio flutuante. | K140: Prova Macroeconomia 2012.pdf — p. 6 — Q2 item 0
A141: 2012 | B141: 2 | C141: 1 | D141: V/F | E141: =IF(A141="","",TEXT(A141,"0")&"-Q"&TEXT(B141,"0")&"-"&IF(C141="","ABERTA",C141)) -> 2012-Q2-1 | F141: =IF(D141="V/F",1,IF(D141="Aberta/numérica",5,"")) -> 1 | G141: 06 — IS-LM-BP | H141: =IF(A141="","",IF(C141="",COUNTIFS($A$5:$A$1504,A141,$B$5:$B$1504,B141,$C$5:$C$1504,"",$D$5:$D$1504,D141),COUNTIFS($A$5:$A$1504,A141,$B$5:$B$1504,B141,$C$5:$C$1504,C141,$D$5:$D$1504,D141))) -> 1 | I141: =IF(OR(F141="",H141="",G141=""),"",F141/H141) -> 1 | J141: Câmbio fixo e endogeneidade monetária. | K141: Prova Macroeconomia 2012.pdf — p. 6 — Q2 item 1
A142: 2012 | B142: 2 | C142: 2 | D142: V/F | E142: =IF(A142="","",TEXT(A142,"0")&"-Q"&TEXT(B142,"0")&"-"&IF(C142="","ABERTA",C142)) -> 2012-Q2-2 | F142: =IF(D142="V/F",1,IF(D142="Aberta/numérica",5,"")) -> 1 | G142: 06 — IS-LM-BP | H142: =IF(A142="","",IF(C142="",COUNTIFS($A$5:$A$1504,A142,$B$5:$B$1504,B142,$C$5:$C$1504,"",$D$5:$D$1504,D142),COUNTIFS($A$5:$A$1504,A142,$B$5:$B$1504,B142,$C$5:$C$1504,C142,$D$5:$D$1504,D142))) -> 1 | I142: =IF(OR(F142="",H142="",G142=""),"",F142/H142) -> 1 | J142: Comparação dos regimes cambiais. | K142: Prova Macroeconomia 2012.pdf — p. 6 — Q2 item 2
A143: 2012 | B143: 2 | C143: 3 | D143: V/F | E143: =IF(A143="","",TEXT(A143,"0")&"-Q"&TEXT(B143,"0")&"-"&IF(C143="","ABERTA",C143)) -> 2012-Q2-3 | F143: =IF(D143="V/F",1,IF(D143="Aberta/numérica",5,"")) -> 1 | G143: 06 — IS-LM-BP | H143: =IF(A143="","",IF(C143="",COUNTIFS($A$5:$A$1504,A143,$B$5:$B$1504,B143,$C$5:$C$1504,"",$D$5:$D$1504,D143),COUNTIFS($A$5:$A$1504,A143,$B$5:$B$1504,B143,$C$5:$C$1504,C143,$D$5:$D$1504,D143))) -> 1 | I143: =IF(OR(F143="",H143="",G143=""),"",F143/H143) -> 1 | J143: Mobilidade de capitais e inclinação da BP. | K143: Prova Macroeconomia 2012.pdf — p. 6 — Q2 item 3
A144: 2012 | B144: 2 | C144: 4 | D144: V/F | E144: =IF(A144="","",TEXT(A144,"0")&"-Q"&TEXT(B144,"0")&"-"&IF(C144="","ABERTA",C144)) -> 2012-Q2-4 | F144: =IF(D144="V/F",1,IF(D144="Aberta/numérica",5,"")) -> 1 | G144: 06 — IS-LM-BP | H144: =IF(A144="","",IF(C144="",COUNTIFS($A$5:$A$1504,A144,$B$5:$B$1504,B144,$C$5:$C$1504,"",$D$5:$D$1504,D144),COUNTIFS($A$5:$A$1504,A144,$B$5:$B$1504,B144,$C$5:$C$1504,C144,$D$5:$D$1504,D144))) -> 1 | I144: =IF(OR(F144="",H144="",G144=""),"",F144/H144) -> 1 | J144: Desequilíbrio externo acima/abaixo da BP. | K144: Prova Macroeconomia 2012.pdf — p. 6 — Q2 item 4
A145: 2012 | B145: 3 | C145: 0 | D145: V/F | E145: =IF(A145="","",TEXT(A145,"0")&"-Q"&TEXT(B145,"0")&"-"&IF(C145="","ABERTA",C145)) -> 2012-Q3-0 | F145: =IF(D145="V/F",1,IF(D145="Aberta/numérica",5,"")) -> 1 | G145: 02 — Balanço de Pagamentos | H145: =IF(A145="","",IF(C145="",COUNTIFS($A$5:$A$1504,A145,$B$5:$B$1504,B145,$C$5:$C$1504,"",$D$5:$D$1504,D145),COUNTIFS($A$5:$A$1504,A145,$B$5:$B$1504,B145,$C$5:$C$1504,C145,$D$5:$D$1504,D145))) -> 1 | I145: =IF(OR(F145="",H145="",G145=""),"",F145/H145) -> 1 | J145: Fechamento das contas externas e exportações. | K145: Prova Macroeconomia 2012.pdf — p. 7 — Q3 item 0
A146: 2012 | B146: 3 | C146: 1 | D146: V/F | E146: =IF(A146="","",TEXT(A146,"0")&"-Q"&TEXT(B146,"0")&"-"&IF(C146="","ABERTA",C146)) -> 2012-Q3-1 | F146: =IF(D146="V/F",1,IF(D146="Aberta/numérica",5,"")) -> 1 | G146: 02 — Balanço de Pagamentos | H146: =IF(A146="","",IF(C146="",COUNTIFS($A$5:$A$1504,A146,$B$5:$B$1504,B146,$C$5:$C$1504,"",$D$5:$D$1504,D146),COUNTIFS($A$5:$A$1504,A146,$B$5:$B$1504,B146,$C$5:$C$1504,C146,$D$5:$D$1504,D146))) -> 1 | I146: =IF(OR(F146="",H146="",G146=""),"",F146/H146) -> 1 | J146: Capitais compensatórios e variação de reservas. | K146: Prova Macroeconomia 2012.pdf — p. 7 — Q3 item 1
... A202: 2012 | B202: 13 | C202: 4 | D202: V/F | E202: =IF(A202="","",TEXT(A202,"0")&"-Q"&TEXT(B202,"0")&"-"&IF(C202="","ABERTA",C202)) -> 2012-Q13-4 | F202: =IF(D202="V/F",1,IF(D202="Aberta/numérica",5,"")) -> 1 | G202: 11 — Crescimento Econômico | H202: =IF(A202="","",IF(C202="",COUNTIFS($A$5:$A$1504,A202,$B$5:$B$1504,B202,$C$5:$C$1504,"",$D$5:$D$1504,D202),COUNTIFS($A$5:$A$1504,A202,$B$5:$B$1504,B202,$C$5:$C$1504,C202,$D$5:$D$1504,D202))) -> 1 | I202: =IF(OR(F202="",H202="",G202=""),"",F202/H202) -> 1 | J202: Solow: razão capital-produto. | K202: Prova Macroeconomia 2012.pdf — p. 18 — Q13 item 4
A203: 2012 | B203: 14 | D203: Aberta/numérica | E203: =IF(A203="","",TEXT(A203,"0")&"-Q"&TEXT(B203,"0")&"-"&IF(C203="","ABERTA",C203)) -> 2012-Q14-ABERTA | F203: =IF(D203="V/F",1,IF(D203="Aberta/numérica",5,"")) -> 5 | G203: 04 — Demanda por Moeda | H203: =IF(A203="","",IF(C203="",COUNTIFS($A$5:$A$1504,A203,$B$5:$B$1504,B203,$C$5:$C$1504,"",$D$5:$D$1504,D203),COUNTIFS($A$5:$A$1504,A203,$B$5:$B$1504,B203,$C$5:$C$1504,C203,$D$5:$D$1504,D203))) -> 1 | I203: =IF(OR(F203="",H203="",G203=""),"",F203/H203) -> 5 | J203: Cagan com expectativas racionais: transição para menor expansão monetária. | K203: Prova Macroeconomia 2012.pdf — p. 19 — Q14 — Tipo B
A204: 2012 | B204: 15 | D204: Aberta/numérica | E204: =IF(A204="","",TEXT(A204,"0")&"-Q"&TEXT(B204,"0")&"-"&IF(C204="","ABERTA",C204)) -> 2012-Q15-ABERTA | F204: =IF(D204="V/F",1,IF(D204="Aberta/numérica",5,"")) -> 5 | G204: 09 — Expectativas, Novos Clássicos e Novos Keynesianos | H204: =IF(A204="","",IF(C204="",COUNTIFS($A$5:$A$1504,A204,$B$5:$B$1504,B204,$C$5:$C$1504,"",$D$5:$D$1504,D204),COUNTIFS($A$5:$A$1504,A204,$B$5:$B$1504,B204,$C$5:$C$1504,C204,$D$5:$D$1504,D204))) -> 1 | I204: =IF(OR(F204="",H204="",G204=""),"",F204/H204) -> 5 | J204: Inconsistência temporal: inflação discricionária com expectativas racionais. | K204: Prova Macroeconomia 2012.pdf — p. 20 — Q15 — Tipo B
A205: 2013 | B205: 1 | C205: 0 | D205: V/F | E205: =IF(A205="","",TEXT(A205,"0")&"-Q"&TEXT(B205,"0")&"-"&IF(C205="","ABERTA",C205)) -> 2013-Q1-0 | F205: =IF(D205="V/F",1,IF(D205="Aberta/numérica",5,"")) -> 1 | G205: 05 — IS-LM | H205: =IF(A205="","",IF(C205="",COUNTIFS($A$5:$A$1504,A205,$B$5:$B$1504,B205,$C$5:$C$1504,"",$D$5:$D$1504,D205),COUNTIFS($A$5:$A$1504,A205,$B$5:$B$1504,B205,$C$5:$C$1504,C205,$D$5:$D$1504,D205))) -> 1 | I205: =IF(OR(F205="",H205="",G205=""),"",F205/H205) -> 1 | J205: IS-LM com demanda de moeda dependente da renda disponível. | K205: Prova Macroeconomia 2013.pdf — p. 5 — Q1 item 0
A206: 2013 | B206: 1 | C206: 1 | D206: V/F | E206: =IF(A206="","",TEXT(A206,"0")&"-Q"&TEXT(B206,"0")&"-"&IF(C206="","ABERTA",C206)) -> 2013-Q1-1 | F206: =IF(D206="V/F",1,IF(D206="Aberta/numérica",5,"")) -> 1 | G206: 05 — IS-LM | H206: =IF(A206="","",IF(C206="",COUNTIFS($A$5:$A$1504,A206,$B$5:$B$1504,B206,$C$5:$C$1504,"",$D$5:$D$1504,D206),COUNTIFS($A$5:$A$1504,A206,$B$5:$B$1504,B206,$C$5:$C$1504,C206,$D$5:$D$1504,D206))) -> 1 | I206: =IF(OR(F206="",H206="",G206=""),"",F206/H206) -> 1 | J206: Multiplicador de orçamento equilibrado no IS-LM. | K206: Prova Macroeconomia 2013.pdf — p. 5 — Q1 item 1
A207: 2013 | B207: 1 | C207: 2 | D207: V/F | E207: =IF(A207="","",TEXT(A207,"0")&"-Q"&TEXT(B207,"0")&"-"&IF(C207="","ABERTA",C207)) -> 2013-Q1-2 | F207: =IF(D207="V/F",1,IF(D207="Aberta/numérica",5,"")) -> 1 | G207: 05 — IS-LM | H207: =IF(A207="","",IF(C207="",COUNTIFS($A$5:$A$1504,A207,$B$5:$B$1504,B207,$C$5:$C$1504,"",$D$5:$D$1504,D207),COUNTIFS($A$5:$A$1504,A207,$B$5:$B$1504,B207,$C$5:$C$1504,C207,$D$5:$D$1504,D207))) -> 1 | I207: =IF(OR(F207="",H207="",G207=""),"",F207/H207) -> 1 | J207: Distribuição da redução tributária e multiplicador fiscal. | K207: Prova Macroeconomia 2013.pdf — p. 5 — Q1 item 2
A208: 2013 | B208: 1 | C208: 3 | D208: V/F | E208: =IF(A208="","",TEXT(A208,"0")&"-Q"&TEXT(B208,"0")&"-"&IF(C208="","ABERTA",C208)) -> 2013-Q1-3 | F208: =IF(D208="V/F",1,IF(D208="Aberta/numérica",5,"")) -> 1 | G208: 05 — IS-LM | H208: =IF(A208="","",IF(C208="",COUNTIFS($A$5:$A$1504,A208,$B$5:$B$1504,B208,$C$5:$C$1504,"",$D$5:$D$1504,D208),COUNTIFS($A$5:$A$1504,A208,$B$5:$B$1504,B208,$C$5:$C$1504,C208,$D$5:$D$1504,D208))) -> 1 | I208: =IF(OR(F208="",H208="",G208=""),"",F208/H208) -> 1 | J208: LM horizontal e eficácia fiscal. | K208: Prova Macroeconomia 2013.pdf — p. 5 — Q1 item 3
A209: 2013 | B209: 1 | C209: 4 | D209: V/F | E209: =IF(A209="","",TEXT(A209,"0")&"-Q"&TEXT(B209,"0")&"-"&IF(C209="","ABERTA",C209)) -> 2013-Q1-4 | F209: =IF(D209="V/F",1,IF(D209="Aberta/numérica",5,"")) -> 1 | G209: 05 — IS-LM | H209: =IF(A209="","",IF(C209="",COUNTIFS($A$5:$A$1504,A209,$B$5:$B$1504,B209,$C$5:$C$1504,"",$D$5:$D$1504,D209),COUNTIFS($A$5:$A$1504,A209,$B$5:$B$1504,B209,$C$5:$C$1504,C209,$D$5:$D$1504,D209))) -> 1 | I209: =IF(OR(F209="",H209="",G209=""),"",F209/H209) -> 1 | J209: Propensão a consumir e equilíbrio IS-LM. | K209: Prova Macroeconomia 2013.pdf — p. 5 — Q1 item 4
A210: 2013 | B210: 2 | C210: 0 | D210: V/F | E210: =IF(A210="","",TEXT(A210,"0")&"-Q"&TEXT(B210,"0")&"-"&IF(C210="","ABERTA",C210)) -> 2013-Q2-0 | F210: =IF(D210="V/F",1,IF(D210="Aberta/numérica",5,"")) -> 1 | G210: 07a — Paridades | H210: =IF(A210="","",IF(C210="",COUNTIFS($A$5:$A$1504,A210,$B$5:$B$1504,B210,$C$5:$C$1504,"",$D$5:$D$1504,D210),COUNTIFS($A$5:$A$1504,A210,$B$5:$B$1504,B210,$C$5:$C$1504,C210,$D$5:$D$1504,D210))) -> 1 | I210: =IF(OR(F210="",H210="",G210=""),"",F210/H210) -> 1 | J210: Poupança-investimento e câmbio real em pequena economia aberta. | K210: Prova Macroeconomia 2013.pdf — p. 6 — Q2 item 0
A211: 2013 | B211: 2 | C211: 1 | D211: V/F | E211: =IF(A211="","",TEXT(A211,"0")&"-Q"&TEXT(B211,"0")&"-"&IF(C211="","ABERTA",C211)) -> 2013-Q2-1 | F211: =IF(D211="V/F",1,IF(D211="Aberta/numérica",5,"")) -> 1 | G211: 07a — Paridades | H211: =IF(A211="","",IF(C211="",COUNTIFS($A$5:$A$1504,A211,$B$5:$B$1504,B211,$C$5:$C$1504,"",$D$5:$D$1504,D211),COUNTIFS($A$5:$A$1504,A211,$B$5:$B$1504,B211,$C$5:$C$1504,C211,$D$5:$D$1504,D211))) -> 1 | I211: =IF(OR(F211="",H211="",G211=""),"",F211/H211) -> 1 | J211: Expansão fiscal externa e câmbio real. | K211: Prova Macroeconomia 2013.pdf — p. 6 — Q2 item 1
A212: 2013 | B212: 2 | C212: 2 | D212: V/F | E212: =IF(A212="","",TEXT(A212,"0")&"-Q"&TEXT(B212,"0")&"-"&IF(C212="","ABERTA",C212)) -> 2013-Q2-2 | F212: =IF(D212="V/F",1,IF(D212="Aberta/numérica",5,"")) -> 1 | G212: 07a — Paridades | H212: =IF(A212="","",IF(C212="",COUNTIFS($A$5:$A$1504,A212,$B$5:$B$1504,B212,$C$5:$C$1504,"",$D$5:$D$1504,D212),COUNTIFS($A$5:$A$1504,A212,$B$5:$B$1504,B212,$C$5:$C$1504,C212,$D$5:$D$1504,D212))) -> 1 | I212: =IF(OR(F212="",H212="",G212=""),"",F212/H212) -> 1 | J212: Determinação do câmbio nominal versus real. | K212: Prova Macroeconomia 2013.pdf — p. 6 — Q2 item 2
A213: 2013 | B213: 2 | C213: 3 | D213: V/F | E213: =IF(A213="","",TEXT(A213,"0")&"-Q"&TEXT(B213,"0")&"-"&IF(C213="","ABERTA",C213)) -> 2013-Q2-3 | F213: =IF(D213="V/F",1,IF(D213="Aberta/numérica",5,"")) -> 1 | G213: 07a — Paridades | H213: =IF(A213="","",IF(C213="",COUNTIFS($A$5:$A$1504,A213,$B$5:$B$1504,B213,$C$5:$C$1504,"",$D$5:$D$1504,D213),COUNTIFS($A$5:$A$1504,A213,$B$5:$B$1504,B213,$C$5:$C$1504,C213,$D$5:$D$1504,D213))) -> 1 | I213: =IF(OR(F213="",H213="",G213=""),"",F213/H213) -> 1 | J213: Paridade descoberta e retorno esperado de títulos. | K213: Prova Macroeconomia 2013.pdf — p. 6 — Q2 item 3
A214: 2013 | B214: 2 | C214: 4 | D214: V/F | E214: =IF(A214="","",TEXT(A214,"0")&"-Q"&TEXT(B214,"0")&"-"&IF(C214="","ABERTA",C214)) -> 2013-Q2-4 | F214: =IF(D214="V/F",1,IF(D214="Aberta/numérica",5,"")) -> 1 | G214: 07a — Paridades | H214: =IF(A214="","",IF(C214="",COUNTIFS($A$5:$A$1504,A214,$B$5:$B$1504,B214,$C$5:$C$1504,"",$D$5:$D$1504,D214),COUNTIFS($A$5:$A$1504,A214,$B$5:$B$1504,B214,$C$5:$C$1504,C214,$D$5:$D$1504,D214))) -> 1 | I214: =IF(OR(F214="",H214="",G214=""),"",F214/H214) -> 1 | J214: Overshooting cambial e ajuste de preços. | K214: Prova Macroeconomia 2013.pdf — p. 6 — Q2 item 4
A215: 2013 | B215: 3 | C215: 0 | D215: V/F | E215: =IF(A215="","",TEXT(A215,"0")&"-Q"&TEXT(B215,"0")&"-"&IF(C215="","ABERTA",C215)) -> 2013-Q3-0 | F215: =IF(D215="V/F",1,IF(D215="Aberta/numérica",5,"")) -> 1 | G215: 14 — Dívida Pública e Senhoriagem | H215: =IF(A215="","",IF(C215="",COUNTIFS($A$5:$A$1504,A215,$B$5:$B$1504,B215,$C$5:$C$1504,"",$D$5:$D$1504,D215),COUNTIFS($A$5:$A$1504,A215,$B$5:$B$1504,B215,$C$5:$C$1504,C215,$D$5:$D$1504,D215))) -> 1 | I215: =IF(OR(F215="",H215="",G215=""),"",F215/H215) -> 1 | J215: Dívida pública e resultado nominal. | K215: Prova Macroeconomia 2013.pdf — p. 7 — Q3 item 0
A216: 2013 | B216: 3 | C216: 1 | D216: V/F | E216: =IF(A216="","",TEXT(A216,"0")&"-Q"&TEXT(B216,"0")&"-"&IF(C216="","ABERTA",C216)) -> 2013-Q3-1 | F216: =IF(D216="V/F",1,IF(D216="Aberta/numérica",5,"")) -> 1 | G216: 03 — Sistema Monetário | H216: =IF(A216="","",IF(C216="",COUNTIFS($A$5:$A$1504,A216,$B$5:$B$1504,B216,$C$5:$C$1504,"",$D$5:$D$1504,D216),COUNTIFS($A$5:$A$1504,A216,$B$5:$B$1504,B216,$C$5:$C$1504,C216,$D$5:$D$1504,D216))) -> 1 | I216: =IF(OR(F216="",H216="",G216=""),"",F216/H216) -> 1 | J216: Compra de divisas por banco comercial e criação de moeda. | K216: Prova Macroeconomia 2013.pdf — p. 7 — Q3 item 1
... A272: 2013 | B272: 13 | C272: 4 | D272: V/F | E272: =IF(A272="","",TEXT(A272,"0")&"-Q"&TEXT(B272,"0")&"-"&IF(C272="","ABERTA",C272)) -> 2013-Q13-4 | F272: =IF(D272="V/F",1,IF(D272="Aberta/numérica",5,"")) -> 1 | G272: 06 — IS-LM-BP | H272: =IF(A272="","",IF(C272="",COUNTIFS($A$5:$A$1504,A272,$B$5:$B$1504,B272,$C$5:$C$1504,"",$D$5:$D$1504,D272),COUNTIFS($A$5:$A$1504,A272,$B$5:$B$1504,B272,$C$5:$C$1504,C272,$D$5:$D$1504,D272))) -> 1 | I272: =IF(OR(F272="",H272="",G272=""),"",F272/H272) -> 1 | J272: Renda externa e apreciação sob câmbio flexível. | K272: Prova Macroeconomia 2013.pdf — p. 18 — Q13 item 4
A273: 2013 | B273: 14 | D273: Aberta/numérica | E273: =IF(A273="","",TEXT(A273,"0")&"-Q"&TEXT(B273,"0")&"-"&IF(C273="","ABERTA",C273)) -> 2013-Q14-ABERTA | F273: =IF(D273="V/F",1,IF(D273="Aberta/numérica",5,"")) -> 5 | G273: 11 — Crescimento Econômico | H273: =IF(A273="","",IF(C273="",COUNTIFS($A$5:$A$1504,A273,$B$5:$B$1504,B273,$C$5:$C$1504,"",$D$5:$D$1504,D273),COUNTIFS($A$5:$A$1504,A273,$B$5:$B$1504,B273,$C$5:$C$1504,C273,$D$5:$D$1504,D273))) -> 1 | I273: =IF(OR(F273="",H273="",G273=""),"",F273/H273) -> 5 | J273: Solow: capital por trabalhador no estado estacionário. | K273: Prova Macroeconomia 2013.pdf — p. 20 — Q14 — Tipo B
A274: 2013 | B274: 15 | C274: 0 | D274: V/F | E274: =IF(A274="","",TEXT(A274,"0")&"-Q"&TEXT(B274,"0")&"-"&IF(C274="","ABERTA",C274)) -> 2013-Q15-0 | F274: =IF(D274="V/F",1,IF(D274="Aberta/numérica",5,"")) -> 1 | G274: 12 — Consumo | H274: =IF(A274="","",IF(C274="",COUNTIFS($A$5:$A$1504,A274,$B$5:$B$1504,B274,$C$5:$C$1504,"",$D$5:$D$1504,D274),COUNTIFS($A$5:$A$1504,A274,$B$5:$B$1504,B274,$C$5:$C$1504,C274,$D$5:$D$1504,D274))) -> 1 | I274: =IF(OR(F274="",H274="",G274=""),"",F274/H274) -> 1 | J274: Suavização do consumo diante de recessão. | K274: Prova Macroeconomia 2013.pdf — p. 21 — Q15 item 0
A275: 2013 | B275: 15 | C275: 1 | D275: V/F | E275: =IF(A275="","",TEXT(A275,"0")&"-Q"&TEXT(B275,"0")&"-"&IF(C275="","ABERTA",C275)) -> 2013-Q15-1 | F275: =IF(D275="V/F",1,IF(D275="Aberta/numérica",5,"")) -> 1 | G275: 13 — Investimento | H275: =IF(A275="","",IF(C275="",COUNTIFS($A$5:$A$1504,A275,$B$5:$B$1504,B275,$C$5:$C$1504,"",$D$5:$D$1504,D275),COUNTIFS($A$5:$A$1504,A275,$B$5:$B$1504,B275,$C$5:$C$1504,C275,$D$5:$D$1504,D275))) -> 1 | I275: =IF(OR(F275="",H275="",G275=""),"",F275/H275) -> 1 | J275: Definição do q de Tobin. | K275: Prova Macroeconomia 2013.pdf — p. 21 — Q15 item 1
A276: 2013 | B276: 15 | C276: 2 | D276: V/F | E276: =IF(A276="","",TEXT(A276,"0")&"-Q"&TEXT(B276,"0")&"-"&IF(C276="","ABERTA",C276)) -> 2013-Q15-2 | F276: =IF(D276="V/F",1,IF(D276="Aberta/numérica",5,"")) -> 1 | G276: 01 — Contas Nacionais | H276: =IF(A276="","",IF(C276="",COUNTIFS($A$5:$A$1504,A276,$B$5:$B$1504,B276,$C$5:$C$1504,"",$D$5:$D$1504,D276),COUNTIFS($A$5:$A$1504,A276,$B$5:$B$1504,B276,$C$5:$C$1504,C276,$D$5:$D$1504,D276))) -> 1 | I276: =IF(OR(F276="",H276="",G276=""),"",F276/H276) -> 1 | J276: Preços de importados versus deflator do PIB. | K276: Prova Macroeconomia 2013.pdf — p. 21 — Q15 item 2
A277: 2013 | B277: 15 | C277: 3 | D277: V/F | E277: =IF(A277="","",TEXT(A277,"0")&"-Q"&TEXT(B277,"0")&"-"&IF(C277="","ABERTA",C277)) -> 2013-Q15-3 | F277: =IF(D277="V/F",1,IF(D277="Aberta/numérica",5,"")) -> 1 | G277: 12 — Consumo | H277: =IF(A277="","",IF(C277="",COUNTIFS($A$5:$A$1504,A277,$B$5:$B$1504,B277,$C$5:$C$1504,"",$D$5:$D$1504,D277),COUNTIFS($A$5:$A$1504,A277,$B$5:$B$1504,B277,$C$5:$C$1504,C277,$D$5:$D$1504,D277))) -> 1 | I277: =IF(OR(F277="",H277="",G277=""),"",F277/H277) -> 1 | J277: Ciclo de vida e estabilização do consumo. | K277: Prova Macroeconomia 2013.pdf — p. 21 — Q15 item 3
A278: 2013 | B278: 15 | C278: 4 | D278: V/F | E278: =IF(A278="","",TEXT(A278,"0")&"-Q"&TEXT(B278,"0")&"-"&IF(C278="","ABERTA",C278)) -> 2013-Q15-4 | F278: =IF(D278="V/F",1,IF(D278="Aberta/numérica",5,"")) -> 1 | G278: 12 — Consumo | H278: =IF(A278="","",IF(C278="",COUNTIFS($A$5:$A$1504,A278,$B$5:$B$1504,B278,$C$5:$C$1504,"",$D$5:$D$1504,D278),COUNTIFS($A$5:$A$1504,A278,$B$5:$B$1504,B278,$C$5:$C$1504,C278,$D$5:$D$1504,D278))) -> 1 | I278: =IF(OR(F278="",H278="",G278=""),"",F278/H278) -> 1 | J278: Renda permanente e transitória. | K278: Prova Macroeconomia 2013.pdf — p. 21 — Q15 item 4
A279: 2014 | B279: 1 | C279: 0 | D279: V/F | E279: =IF(A279="","",TEXT(A279,"0")&"-Q"&TEXT(B279,"0")&"-"&IF(C279="","ABERTA",C279)) -> 2014-Q1-0 | F279: =IF(D279="V/F",1,IF(D279="Aberta/numérica",5,"")) -> 1 | G279: 01 — Contas Nacionais | H279: =IF(A279="","",IF(C279="",COUNTIFS($A$5:$A$1504,A279,$B$5:$B$1504,B279,$C$5:$C$1504,"",$D$5:$D$1504,D279),COUNTIFS($A$5:$A$1504,A279,$B$5:$B$1504,B279,$C$5:$C$1504,C279,$D$5:$D$1504,D279))) -> 1 | I279: =IF(OR(F279="",H279="",G279=""),"",F279/H279) -> 1 | J279: Renda líquida externa e diferença PNB-PIB. | K279: Prova Macroeconomia 2014.docx — Q1 item 0
A280: 2014 | B280: 1 | C280: 1 | D280: V/F | E280: =IF(A280="","",TEXT(A280,"0")&"-Q"&TEXT(B280,"0")&"-"&IF(C280="","ABERTA",C280)) -> 2014-Q1-1 | F280: =IF(D280="V/F",1,IF(D280="Aberta/numérica",5,"")) -> 1 | G280: 01 — Contas Nacionais | H280: =IF(A280="","",IF(C280="",COUNTIFS($A$5:$A$1504,A280,$B$5:$B$1504,B280,$C$5:$C$1504,"",$D$5:$D$1504,D280),COUNTIFS($A$5:$A$1504,A280,$B$5:$B$1504,B280,$C$5:$C$1504,C280,$D$5:$D$1504,D280))) -> 1 | I280: =IF(OR(F280="",H280="",G280=""),"",F280/H280) -> 1 | J280: Aluguel imputado de moradia própria. | K280: Prova Macroeconomia 2014.docx — Q1 item 1
A281: 2014 | B281: 1 | C281: 2 | D281: V/F | E281: =IF(A281="","",TEXT(A281,"0")&"-Q"&TEXT(B281,"0")&"-"&IF(C281="","ABERTA",C281)) -> 2014-Q1-2 | F281: =IF(D281="V/F",1,IF(D281="Aberta/numérica",5,"")) -> 1 | G281: 01 — Contas Nacionais | H281: =IF(A281="","",IF(C281="",COUNTIFS($A$5:$A$1504,A281,$B$5:$B$1504,B281,$C$5:$C$1504,"",$D$5:$D$1504,D281),COUNTIFS($A$5:$A$1504,A281,$B$5:$B$1504,B281,$C$5:$C$1504,C281,$D$5:$D$1504,D281))) -> 1 | I281: =IF(OR(F281="",H281="",G281=""),"",F281/H281) -> 1 | J281: Renda nacional, depreciação e impostos. | K281: Prova Macroeconomia 2014.docx — Q1 item 2
A282: 2014 | B282: 1 | C282: 3 | D282: V/F | E282: =IF(A282="","",TEXT(A282,"0")&"-Q"&TEXT(B282,"0")&"-"&IF(C282="","ABERTA",C282)) -> 2014-Q1-3 | F282: =IF(D282="V/F",1,IF(D282="Aberta/numérica",5,"")) -> 1 | G282: 02 — Balanço de Pagamentos | H282: =IF(A282="","",IF(C282="",COUNTIFS($A$5:$A$1504,A282,$B$5:$B$1504,B282,$C$5:$C$1504,"",$D$5:$D$1504,D282),COUNTIFS($A$5:$A$1504,A282,$B$5:$B$1504,B282,$C$5:$C$1504,C282,$D$5:$D$1504,D282))) -> 1 | I282: =IF(OR(F282="",H282="",G282=""),"",F282/H282) -> 1 | J282: Fechamento das transações correntes. | K282: Prova Macroeconomia 2014.docx — Q1 item 3
A283: 2014 | B283: 1 | C283: 4 | D283: V/F | E283: =IF(A283="","",TEXT(A283,"0")&"-Q"&TEXT(B283,"0")&"-"&IF(C283="","ABERTA",C283)) -> 2014-Q1-4 | F283: =IF(D283="V/F",1,IF(D283="Aberta/numérica",5,"")) -> 1 | G283: 01 — Contas Nacionais | H283: =IF(A283="","",IF(C283="",COUNTIFS($A$5:$A$1504,A283,$B$5:$B$1504,B283,$C$5:$C$1504,"",$D$5:$D$1504,D283),COUNTIFS($A$5:$A$1504,A283,$B$5:$B$1504,B283,$C$5:$C$1504,C283,$D$5:$D$1504,D283))) -> 1 | I283: =IF(OR(F283="",H283="",G283=""),"",F283/H283) -> 1 | J283: Deflator versus índice de cesta fixa. | K283: Prova Macroeconomia 2014.docx — Q1 item 4
A284: 2014 | B284: 2 | C284: 0 | D284: V/F | E284: =IF(A284="","",TEXT(A284,"0")&"-Q"&TEXT(B284,"0")&"-"&IF(C284="","ABERTA",C284)) -> 2014-Q2-0 | F284: =IF(D284="V/F",1,IF(D284="Aberta/numérica",5,"")) -> 1 | G284: 09 — Expectativas, Novos Clássicos e Novos Keynesianos | H284: =IF(A284="","",IF(C284="",COUNTIFS($A$5:$A$1504,A284,$B$5:$B$1504,B284,$C$5:$C$1504,"",$D$5:$D$1504,D284),COUNTIFS($A$5:$A$1504,A284,$B$5:$B$1504,B284,$C$5:$C$1504,C284,$D$5:$D$1504,D284))) -> 1 | I284: =IF(OR(F284="",H284="",G284=""),"",F284/H284) -> 1 | J284: Orçamento equilibrado e poupança privada no modelo keynesiano simples. Classificação para revisão. | K284: Prova Macroeconomia 2014.docx — Q2 item 0
A285: 2014 | B285: 2 | C285: 1 | D285: V/F | E285: =IF(A285="","",TEXT(A285,"0")&"-Q"&TEXT(B285,"0")&"-"&IF(C285="","ABERTA",C285)) -> 2014-Q2-1 | F285: =IF(D285="V/F",1,IF(D285="Aberta/numérica",5,"")) -> 1 | G285: 08 — Curva de Phillips | H285: =IF(A285="","",IF(C285="",COUNTIFS($A$5:$A$1504,A285,$B$5:$B$1504,B285,$C$5:$C$1504,"",$D$5:$D$1504,D285),COUNTIFS($A$5:$A$1504,A285,$B$5:$B$1504,B285,$C$5:$C$1504,C285,$D$5:$D$1504,D285))) -> 1 | I285: =IF(OR(F285="",H285="",G285=""),"",F285/H285) -> 1 | J285: Princípio de Taylor e juros reais/nominais. | K285: Prova Macroeconomia 2014.docx — Q2 item 1
... A324: 2014 | B324: 9 | C324: 4 | D324: V/F | E324: =IF(A324="","",TEXT(A324,"0")&"-Q"&TEXT(B324,"0")&"-"&IF(C324="","ABERTA",C324)) -> 2014-Q9-4 | F324: =IF(D324="V/F",1,IF(D324="Aberta/numérica",5,"")) -> 1 | G324: 13 — Investimento | H324: =IF(A324="","",IF(C324="",COUNTIFS($A$5:$A$1504,A324,$B$5:$B$1504,B324,$C$5:$C$1504,"",$D$5:$D$1504,D324),COUNTIFS($A$5:$A$1504,A324,$B$5:$B$1504,B324,$C$5:$C$1504,C324,$D$5:$D$1504,D324))) -> 1 | I324: =IF(OR(F324="",H324="",G324=""),"",F324/H324) -> 1 | J324: q de Tobin e decisão de investir/repor capital. | K324: Prova Macroeconomia 2014.docx — Q9 item 4
A325: 2014 | B325: 10 | D325: Aberta/numérica | E325: =IF(A325="","",TEXT(A325,"0")&"-Q"&TEXT(B325,"0")&"-"&IF(C325="","ABERTA",C325)) -> 2014-Q10-ABERTA | F325: =IF(D325="V/F",1,IF(D325="Aberta/numérica",5,"")) -> 5 | G325: 14 — Dívida Pública e Senhoriagem | H325: =IF(A325="","",IF(C325="",COUNTIFS($A$5:$A$1504,A325,$B$5:$B$1504,B325,$C$5:$C$1504,"",$D$5:$D$1504,D325),COUNTIFS($A$5:$A$1504,A325,$B$5:$B$1504,B325,$C$5:$C$1504,C325,$D$5:$D$1504,D325))) -> 1 | I325: =IF(OR(F325="",H325="",G325=""),"",F325/H325) -> 5 | J325: Superávit primário estabilizador da dívida/PIB. | K325: Prova Macroeconomia 2014.docx — Q10 — Tipo B
A326: 2014 | B326: 11 | D326: Aberta/numérica | E326: =IF(A326="","",TEXT(A326,"0")&"-Q"&TEXT(B326,"0")&"-"&IF(C326="","ABERTA",C326)) -> 2014-Q11-ABERTA | F326: =IF(D326="V/F",1,IF(D326="Aberta/numérica",5,"")) -> 5 | G326: 08 — Curva de Phillips | H326: =IF(A326="","",IF(C326="",COUNTIFS($A$5:$A$1504,A326,$B$5:$B$1504,B326,$C$5:$C$1504,"",$D$5:$D$1504,D326),COUNTIFS($A$5:$A$1504,A326,$B$5:$B$1504,B326,$C$5:$C$1504,C326,$D$5:$D$1504,D326))) -> 1 | I326: =IF(OR(F326="",H326="",G326=""),"",F326/H326) -> 5 | J326: Phillips adaptativa: duração da desinflação com desemprego acima do natural. | K326: Prova Macroeconomia 2014.docx — Q11 — Tipo B
A327: 2014 | B327: 12 | C327: 0 | D327: V/F | E327: =IF(A327="","",TEXT(A327,"0")&"-Q"&TEXT(B327,"0")&"-"&IF(C327="","ABERTA",C327)) -> 2014-Q12-0 | F327: =IF(D327="V/F",1,IF(D327="Aberta/numérica",5,"")) -> 1 | G327: 09 — Expectativas, Novos Clássicos e Novos Keynesianos | H327: =IF(A327="","",IF(C327="",COUNTIFS($A$5:$A$1504,A327,$B$5:$B$1504,B327,$C$5:$C$1504,"",$D$5:$D$1504,D327),COUNTIFS($A$5:$A$1504,A327,$B$5:$B$1504,B327,$C$5:$C$1504,C327,$D$5:$D$1504,D327))) -> 1 | I327: =IF(OR(F327="",H327="",G327=""),"",F327/H327) -> 1 | J327: Inconsistência temporal: peso do produto na função objetivo. | K327: Prova Macroeconomia 2014.docx — Q12 item 0
A328: 2014 | B328: 12 | C328: 1 | D328: V/F | E328: =IF(A328="","",TEXT(A328,"0")&"-Q"&TEXT(B328,"0")&"-"&IF(C328="","ABERTA",C328)) -> 2014-Q12-1 | F328: =IF(D328="V/F",1,IF(D328="Aberta/numérica",5,"")) -> 1 | G328: 09 — Expectativas, Novos Clássicos e Novos Keynesianos | H328: =IF(A328="","",IF(C328="",COUNTIFS($A$5:$A$1504,A328,$B$5:$B$1504,B328,$C$5:$C$1504,"",$D$5:$D$1504,D328),COUNTIFS($A$5:$A$1504,A328,$B$5:$B$1504,B328,$C$5:$C$1504,C328,$D$5:$D$1504,D328))) -> 1 | I328: =IF(OR(F328="",H328="",G328=""),"",F328/H328) -> 1 | J328: Incentivo à surpresa e viés inflacionário. | K328: Prova Macroeconomia 2014.docx — Q12 item 1
A329: 2014 | B329: 12 | C329: 2 | D329: V/F | E329: =IF(A329="","",TEXT(A329,"0")&"-Q"&TEXT(B329,"0")&"-"&IF(C329="","ABERTA",C329)) -> 2014-Q12-2 | F329: =IF(D329="V/F",1,IF(D329="Aberta/numérica",5,"")) -> 1 | G329: 09 — Expectativas, Novos Clássicos e Novos Keynesianos | H329: =IF(A329="","",IF(C329="",COUNTIFS($A$5:$A$1504,A329,$B$5:$B$1504,B329,$C$5:$C$1504,"",$D$5:$D$1504,D329),COUNTIFS($A$5:$A$1504,A329,$B$5:$B$1504,B329,$C$5:$C$1504,C329,$D$5:$D$1504,D329))) -> 1 | I329: =IF(OR(F329="",H329="",G329=""),"",F329/H329) -> 1 | J329: Discricionariedade sem ganho permanente de produto. | K329: Prova Macroeconomia 2014.docx — Q12 item 2
A330: 2014 | B330: 12 | C330: 3 | D330: V/F | E330: =IF(A330="","",TEXT(A330,"0")&"-Q"&TEXT(B330,"0")&"-"&IF(C330="","ABERTA",C330)) -> 2014-Q12-3 | F330: =IF(D330="V/F",1,IF(D330="Aberta/numérica",5,"")) -> 1 | G330: 09 — Expectativas, Novos Clássicos e Novos Keynesianos | H330: =IF(A330="","",IF(C330="",COUNTIFS($A$5:$A$1504,A330,$B$5:$B$1504,B330,$C$5:$C$1504,"",$D$5:$D$1504,D330),COUNTIFS($A$5:$A$1504,A330,$B$5:$B$1504,B330,$C$5:$C$1504,C330,$D$5:$D$1504,D330))) -> 1 | I330: =IF(OR(F330="",H330="",G330=""),"",F330/H330) -> 1 | J330: Delegação a banqueiro central conservador. | K330: Prova Macroeconomia 2014.docx — Q12 item 3
A331: 2014 | B331: 12 | C331: 4 | D331: V/F | E331: =IF(A331="","",TEXT(A331,"0")&"-Q"&TEXT(B331,"0")&"-"&IF(C331="","ABERTA",C331)) -> 2014-Q12-4 | F331: =IF(D331="V/F",1,IF(D331="Aberta/numérica",5,"")) -> 1 | G331: 09 — Expectativas, Novos Clássicos e Novos Keynesianos | H331: =IF(A331="","",IF(C331="",COUNTIFS($A$5:$A$1504,A331,$B$5:$B$1504,B331,$C$5:$C$1504,"",$D$5:$D$1504,D331),COUNTIFS($A$5:$A$1504,A331,$B$5:$B$1504,B331,$C$5:$C$1504,C331,$D$5:$D$1504,D331))) -> 1 | I331: =IF(OR(F331="",H331="",G331=""),"",F331/H331) -> 1 | J331: Compromisso com meta e inconsistência temporal. | K331: Prova Macroeconomia 2014.docx — Q12 item 4
A332: 2014 | B332: 13 | C332: 0 | D332: V/F | E332: =IF(A332="","",TEXT(A332,"0")&"-Q"&TEXT(B332,"0")&"-"&IF(C332="","ABERTA",C332)) -> 2014-Q13-0 | F332: =IF(D332="V/F",1,IF(D332="Aberta/numérica",5,"")) -> 1 | G332: 07a — Paridades | H332: =IF(A332="","",IF(C332="",COUNTIFS($A$5:$A$1504,A332,$B$5:$B$1504,B332,$C$5:$C$1504,"",$D$5:$D$1504,D332),COUNTIFS($A$5:$A$1504,A332,$B$5:$B$1504,B332,$C$5:$C$1504,C332,$D$5:$D$1504,D332))) -> 1 | I332: =IF(OR(F332="",H332="",G332=""),"",F332/H332) -> 1 | J332: Expansão fiscal externa e câmbio real da pequena economia. | K332: Prova Macroeconomia 2014.docx — Q13 item 0
A333: 2014 | B333: 13 | C333: 1 | D333: V/F | E333: =IF(A333="","",TEXT(A333,"0")&"-Q"&TEXT(B333,"0")&"-"&IF(C333="","ABERTA",C333)) -> 2014-Q13-1 | F333: =IF(D333="V/F",1,IF(D333="Aberta/numérica",5,"")) -> 1 | G333: 07a — Paridades | H333: =IF(A333="","",IF(C333="",COUNTIFS($A$5:$A$1504,A333,$B$5:$B$1504,B333,$C$5:$C$1504,"",$D$5:$D$1504,D333),COUNTIFS($A$5:$A$1504,A333,$B$5:$B$1504,B333,$C$5:$C$1504,C333,$D$5:$D$1504,D333))) -> 1 | I333: =IF(OR(F333="",H333="",G333=""),"",F333/H333) -> 1 | J333: Expansão fiscal doméstica e exportações líquidas. | K333: Prova Macroeconomia 2014.docx — Q13 item 1
A334: 2014 | B334: 13 | C334: 2 | D334: V/F | E334: =IF(A334="","",TEXT(A334,"0")&"-Q"&TEXT(B334,"0")&"-"&IF(C334="","ABERTA",C334)) -> 2014-Q13-2 | F334: =IF(D334="V/F",1,IF(D334="Aberta/numérica",5,"")) -> 1 | G334: 07a — Paridades | H334: =IF(A334="","",IF(C334="",COUNTIFS($A$5:$A$1504,A334,$B$5:$B$1504,B334,$C$5:$C$1504,"",$D$5:$D$1504,D334),COUNTIFS($A$5:$A$1504,A334,$B$5:$B$1504,B334,$C$5:$C$1504,C334,$D$5:$D$1504,D334))) -> 1 | I334: =IF(OR(F334="",H334="",G334=""),"",F334/H334) -> 1 | J334: PPC relativa versus lei do preço único. | K334: Prova Macroeconomia 2014.docx — Q13 item 2
A335: 2014 | B335: 13 | C335: 3 | D335: V/F | E335: =IF(A335="","",TEXT(A335,"0")&"-Q"&TEXT(B335,"0")&"-"&IF(C335="","ABERTA",C335)) -> 2014-Q13-3 | F335: =IF(D335="V/F",1,IF(D335="Aberta/numérica",5,"")) -> 1 | G335: 07a — Paridades | H335: =IF(A335="","",IF(C335="",COUNTIFS($A$5:$A$1504,A335,$B$5:$B$1504,B335,$C$5:$C$1504,"",$D$5:$D$1504,D335),COUNTIFS($A$5:$A$1504,A335,$B$5:$B$1504,B335,$C$5:$C$1504,C335,$D$5:$D$1504,D335))) -> 1 | I335: =IF(OR(F335="",H335="",G335=""),"",F335/H335) -> 1 | J335: Definição e interpretação da taxa real de câmbio. | K335: Prova Macroeconomia 2014.docx — Q13 item 3
A336: 2014 | B336: 13 | C336: 4 | D336: V/F | E336: =IF(A336="","",TEXT(A336,"0")&"-Q"&TEXT(B336,"0")&"-"&IF(C336="","ABERTA",C336)) -> 2014-Q13-4 | F336: =IF(D336="V/F",1,IF(D336="Aberta/numérica",5,"")) -> 1 | G336: 07a — Paridades | H336: =IF(A336="","",IF(C336="",COUNTIFS($A$5:$A$1504,A336,$B$5:$B$1504,B336,$C$5:$C$1504,"",$D$5:$D$1504,D336),COUNTIFS($A$5:$A$1504,A336,$B$5:$B$1504,B336,$C$5:$C$1504,C336,$D$5:$D$1504,D336))) -> 1 | I336: =IF(OR(F336="",H336="",G336=""),"",F336/H336) -> 1 | J336: Paridade descoberta: juros domésticos e câmbio corrente. | K336: Prova Macroeconomia 2014.docx — Q13 item 4
A337: 2014 | B337: 14 | C337: 0 | D337: V/F | E337: =IF(A337="","",TEXT(A337,"0")&"-Q"&TEXT(B337,"0")&"-"&IF(C337="","ABERTA",C337)) -> 2014-Q14-0 | F337: =IF(D337="V/F",1,IF(D337="Aberta/numérica",5,"")) -> 1 | G337: 05 — IS-LM | H337: =IF(A337="","",IF(C337="",COUNTIFS($A$5:$A$1504,A337,$B$5:$B$1504,B337,$C$5:$C$1504,"",$D$5:$D$1504,D337),COUNTIFS($A$5:$A$1504,A337,$B$5:$B$1504,B337,$C$5:$C$1504,C337,$D$5:$D$1504,D337))) -> 1 | I337: =IF(OR(F337="",H337="",G337=""),"",F337/H337) -> 1 | J337: Poole no IS-LM: choques monetários e escolha de instrumento. | K337: Prova Macroeconomia 2014.docx — Q14 item 0
A338: 2014 | B338: 14 | C338: 1 | D338: V/F | E338: =IF(A338="","",TEXT(A338,"0")&"-Q"&TEXT(B338,"0")&"-"&IF(C338="","ABERTA",C338)) -> 2014-Q14-1 | F338: =IF(D338="V/F",1,IF(D338="Aberta/numérica",5,"")) -> 1 | G338: 05 — IS-LM | H338: =IF(A338="","",IF(C338="",COUNTIFS($A$5:$A$1504,A338,$B$5:$B$1504,B338,$C$5:$C$1504,"",$D$5:$D$1504,D338),COUNTIFS($A$5:$A$1504,A338,$B$5:$B$1504,B338,$C$5:$C$1504,C338,$D$5:$D$1504,D338))) -> 1 | I338: =IF(OR(F338="",H338="",G338=""),"",F338/H338) -> 1 | J338: Poole no IS-LM: meta de juros diante de choques na LM. | K338: Prova Macroeconomia 2014.docx — Q14 item 1
... A341: 2014 | B341: 14 | C341: 4 | D341: V/F | E341: =IF(A341="","",TEXT(A341,"0")&"-Q"&TEXT(B341,"0")&"-"&IF(C341="","ABERTA",C341)) -> 2014-Q14-4 | F341: =IF(D341="V/F",1,IF(D341="Aberta/numérica",5,"")) -> 1 | G341: 14 — Dívida Pública e Senhoriagem | H341: =IF(A341="","",IF(C341="",COUNTIFS($A$5:$A$1504,A341,$B$5:$B$1504,B341,$C$5:$C$1504,"",$D$5:$D$1504,D341),COUNTIFS($A$5:$A$1504,A341,$B$5:$B$1504,B341,$C$5:$C$1504,C341,$D$5:$D$1504,D341))) -> 1 | I341: =IF(OR(F341="",H341="",G341=""),"",F341/H341) -> 1 | J341: Equação dinâmica da dívida/PIB. | K341: Prova Macroeconomia 2014.docx — Q14 item 4
A342: 2014 | B342: 15 | D342: Aberta/numérica | E342: =IF(A342="","",TEXT(A342,"0")&"-Q"&TEXT(B342,"0")&"-"&IF(C342="","ABERTA",C342)) -> 2014-Q15-ABERTA | F342: =IF(D342="V/F",1,IF(D342="Aberta/numérica",5,"")) -> 5 | G342: 11 — Crescimento Econômico | H342: =IF(A342="","",IF(C342="",COUNTIFS($A$5:$A$1504,A342,$B$5:$B$1504,B342,$C$5:$C$1504,"",$D$5:$D$1504,D342),COUNTIFS($A$5:$A$1504,A342,$B$5:$B$1504,B342,$C$5:$C$1504,C342,$D$5:$D$1504,D342))) -> 1 | I342: =IF(OR(F342="",H342="",G342=""),"",F342/H342) -> 5 | J342: Modelo AK com capital amplo e população constante. | K342: Prova Macroeconomia 2014.docx — Q15 — Tipo B
A343: 2015 | B343: 1 | C343: 0 | D343: V/F | E343: =IF(A343="","",TEXT(A343,"0")&"-Q"&TEXT(B343,"0")&"-"&IF(C343="","ABERTA",C343)) -> 2015-Q1-0 | F343: =IF(D343="V/F",1,IF(D343="Aberta/numérica",5,"")) -> 1 | G343: 02 — Balanço de Pagamentos | H343: =IF(A343="","",IF(C343="",COUNTIFS($A$5:$A$1504,A343,$B$5:$B$1504,B343,$C$5:$C$1504,"",$D$5:$D$1504,D343),COUNTIFS($A$5:$A$1504,A343,$B$5:$B$1504,B343,$C$5:$C$1504,C343,$D$5:$D$1504,D343))) -> 1 | I343: =IF(OR(F343="",H343="",G343=""),"",F343/H343) -> 1 | J343: Saldo da balança comercial. | K343: Prova Macroeconomia 2015.pdf — p. 5 — Q1 item 0
A344: 2015 | B344: 1 | C344: 1 | D344: V/F | E344: =IF(A344="","",TEXT(A344,"0")&"-Q"&TEXT(B344,"0")&"-"&IF(C344="","ABERTA",C344)) -> 2015-Q1-1 | F344: =IF(D344="V/F",1,IF(D344="Aberta/numérica",5,"")) -> 1 | G344: 02 — Balanço de Pagamentos | H344: =IF(A344="","",IF(C344="",COUNTIFS($A$5:$A$1504,A344,$B$5:$B$1504,B344,$C$5:$C$1504,"",$D$5:$D$1504,D344),COUNTIFS($A$5:$A$1504,A344,$B$5:$B$1504,B344,$C$5:$C$1504,C344,$D$5:$D$1504,D344))) -> 1 | I344: =IF(OR(F344="",H344="",G344=""),"",F344/H344) -> 1 | J344: Saldo em transações correntes. | K344: Prova Macroeconomia 2015.pdf — p. 5 — Q1 item 1
A345: 2015 | B345: 1 | C345: 2 | D345: V/F | E345: =IF(A345="","",TEXT(A345,"0")&"-Q"&TEXT(B345,"0")&"-"&IF(C345="","ABERTA",C345)) -> 2015-Q1-2 | F345: =IF(D345="V/F",1,IF(D345="Aberta/numérica",5,"")) -> 1 | G345: 02 — Balanço de Pagamentos | H345: =IF(A345="","",IF(C345="",COUNTIFS($A$5:$A$1504,A345,$B$5:$B$1504,B345,$C$5:$C$1504,"",$D$5:$D$1504,D345),COUNTIFS($A$5:$A$1504,A345,$B$5:$B$1504,B345,$C$5:$C$1504,C345,$D$5:$D$1504,D345))) -> 1 | I345: =IF(OR(F345="",H345="",G345=""),"",F345/H345) -> 1 | J345: Saldo global do balanço de pagamentos. | K345: Prova Macroeconomia 2015.pdf — p. 5 — Q1 item 2
A346: 2015 | B346: 1 | C346: 3 | D346: V/F | E346: =IF(A346="","",TEXT(A346,"0")&"-Q"&TEXT(B346,"0")&"-"&IF(C346="","ABERTA",C346)) -> 2015-Q1-3 | F346: =IF(D346="V/F",1,IF(D346="Aberta/numérica",5,"")) -> 1 | G346: 02 — Balanço de Pagamentos | H346: =IF(A346="","",IF(C346="",COUNTIFS($A$5:$A$1504,A346,$B$5:$B$1504,B346,$C$5:$C$1504,"",$D$5:$D$1504,D346),COUNTIFS($A$5:$A$1504,A346,$B$5:$B$1504,B346,$C$5:$C$1504,C346,$D$5:$D$1504,D346))) -> 1 | I346: =IF(OR(F346="",H346="",G346=""),"",F346/H346) -> 1 | J346: Conta de serviços: fretes internacionais. | K346: Prova Macroeconomia 2015.pdf — p. 5 — Q1 item 3
...

Sheet Metodologia
A1: Metodologia e instruções
A3: Regra | B3: Como aplicar | C3: Exemplo | D3: Observação
A4: Item V/F | B4: Peso base = 1. | C4: Um item só de IS-LM soma 1 ao tópico 05. | D4: Uma linha na Base_Itens.
A5: Questão aberta/numérica | B5: Peso base = 5 itens equivalentes. | C5: Questão só de Crescimento soma 5 ao tópico 11. | D5: Convenção solicitada pelo usuário.
A6: Item misto | B6: Pertence a n tópicos ⇒ dividir o peso igualmente. | C6: V/F em 2 tópicos: 0,5 + 0,5; aberta em 2: 2,5 + 2,5. | D6: Repita o mesmo Item_ID em n linhas.
A7: n tópicos | B7: Calculado por COUNTIF do Item_ID. | C7: Três linhas com o mesmo Item_ID ⇒ n=3. | D7: Não repita o mesmo tópico para o mesmo item.
A8: Tópicos principais | B8: Taxonomia atualizada: 07a = Paridades; 07b = OA-DA. E1/E5 foram absorvidos por 09; E2 por 07b; E3 por 08. | D8: Lista 07 combina Paridades e OA-DA.
A9: Tópicos extras | B9: Seis linhas Extra preenchidas para conteúdos que não se enquadram diretamente nas 14 listas. | C9: Renomeie na aba Tópicos. | D9: Para itens que não se encaixem nas 14 listas.
A10: Gráfico de barras | B10: Eixo X = tópico; eixo Y = quantidade; filtro por ano em Dashboard!B3. | D10: O seletor B3 funciona como filtro de ano.
A11: Gráfico de linhas | B11: Eixo X = ano; eixo Y = itens equivalentes; filtro Sim/Não no Dashboard escolhe as séries exibidas. | D11: Cores distintas definidas por série.
A12: Status do levantamento | B12: 17 provas e 240 questões lidas; classificação individual de 1.008 itens econômicos. Taxonomia consolidada conforme revisão posterior. | D12: Auditoria anual e por Item_ID na aba Validação; dúvidas no TXT entregue.
A13: Fonte oficial | B13: Provas anteriores da ANPEC. | D13: https://www.anpec.org.br/novosite/br/exame
A14: Fonte auxiliar | B14: Indexação de questões ANPEC. | D14: https://provasanpec.com.br/
A16: Item_ID | B16: Convenção original preservada: ano-Qquestão-item; questões numéricas usam ABERTA. | C16: 2015-Q1-0; 2015-Q12-ABERTA | D16: O mesmo Item_ID aparece uma vez por tópico distinto.
A17: Não arredondamento | B17: Peso base / número de tópicos, sem arredondar a fórmula. | C17: Duas casas decimais apenas na exibição. | D17: Diferenças são auditadas antes do arredondamento.
A18: Fonte | B18: Nome do arquivo e localização da questão/item; PDFs incluem página física do arquivo. | C18: DOC/DOCX identificados por questão e item. | D18: Arquivos originais preservados; ano é o do exame, não a data de aplicação.
A19: Anulação | B19: Itens anulados permanecem com peso integral. | C19: 2025-Q9-3: Item anulado. | D19: Gabarito final 2025 fornecido, de 28/10/2024. Não se presume ausência de anulação nos demais anos.
A20: Fronteiras temáticas | B20: TQM/Fisher → 04; equivalência ricardiana → 12; inconsistência temporal → 09. | C20: Menções incidentais não geram rateio. | D20: 07 mantém a combinação original de Paridades e OA-DA.
A21: Extra E1 | B21: Equilíbrio keynesiano do mercado de bens com juros dados, sem equilíbrio monetário independente. | C21: Multiplicador e cruz keynesiana, fechada ou aberta. | D21: IS-LM e IS-LM-BP mantidos quando o mecanismo monetário/externo integra o modelo.
A22: Outros extras | B22: E2: trabalho; E3: regras/instrumentos; E1: finanças; E5: modelo clássico; E2: complementaridade de bens. | C22: Nomes completos na aba Tópicos. | D22: Rateio somente para mecanismos distintos materialmente necessários.
A23: Revisão conceitual | B23: Cinco casos com alternativa plausível constam do TXT de revisão. | C23: O rateio não substitui o registro de incerteza. | D23: A coluna Observação registra o fundamento econômico de cada item.

Sheet Validação
A1: Auditoria de cobertura e pesos — ANPEC Macroeconomia 2010–2026
A2: Esperado: inventário das provas. Classificado: fórmulas vinculadas à Base_Itens. Diferenças devem ser zero.
A4: Ano | B4: Nº questões | C4: Peso esperado | D4: Peso classificado | E4: Diferença | F4: Itens V/F | G4: Tipo B | H4: Itens econômicos | I4: Situação | J4: Pares Item_ID × tópico duplicados | K4: =COUNTIF(L28:L1075,">1") -> 0
A5: 2010 | B5: 15 | C5: =5*B5 -> 75 | D5: =SUMIF(Base_Itens!$A$5:$A$1504,A5,Base_Itens!$I$5:$I$1504) -> 75 | E5: =D5-C5 -> 0 | F5: 55 | G5: 4 | H5: 59 | I5: =IF(E5=0,"OK","REVER") -> OK | J5: Itens com peso incorreto | K5: =COUNTIF(G28:G1035,"<>0") -> 0
A6: 2011 | B6: 15 | C6: =5*B6 -> 75 | D6: =SUMIF(Base_Itens!$A$5:$A$1504,A6,Base_Itens!$I$5:$I$1504) -> 75 | E6: =D6-C6 -> 0 | F6: 65 | G6: 2 | H6: 67 | I6: =IF(E2=0,"OK","REVER") -> OK | J6: Linhas na Base_Itens | K6: =COUNT(Base_Itens!A5:A1504) -> 1048
A7: 2012 | B7: 15 | C7: =5*B7 -> 75 | D7: =SUMIF(Base_Itens!$A$5:$A$1504,A7,Base_Itens!$I$5:$I$1504) -> 75 | E7: =D7-C7 -> 0 | F7: 65 | G7: 2 | H7: 67 | I7: =IF(E7=0,"OK","REVER") -> OK | J7: Itens com mais de um tópico | K7: =COUNTIF(H28:H1035,">1") -> 39
A8: 2013 | B8: 15 | C8: =5*B8 -> 75 | D8: =SUMIF(Base_Itens!$A$5:$A$1504,A8,Base_Itens!$I$5:$I$1504) -> 75 | E8: =D8-C8 -> 0 | F8: 70 | G8: 1 | H8: 71 | I8: =IF(E8=0,"OK","REVER") -> OK | J8: Revisões conceituais | K8: 5
A9: 2014 | B9: 15 | C9: =5*B9 -> 75 | D9: =SUMIF(Base_Itens!$A$5:$A$1504,A9,Base_Itens!$I$5:$I$1504) -> 75 | E9: =D9-C9 -> 0 | F9: 60 | G9: 3 | H9: 63 | I9: =IF(E9=0,"OK","REVER") -> OK | J9: Tópicos ativos | K9: 17
A10: 2015 | B10: 15 | C10: =5*B10 -> 75 | D10: =SUMIF(Base_Itens!$A$5:$A$1504,A10,Base_Itens!$I$5:$I$1504) -> 75 | E10: =D10-C10 -> 0 | F10: 50 | G10: 5 | H10: 55 | I10: =IF(E10=0,"OK","REVER") -> OK
A11: 2016 | B11: 15 | C11: =5*B11 -> 75 | D11: =SUMIF(Base_Itens!$A$5:$A$1504,A11,Base_Itens!$I$5:$I$1504) -> 75 | E11: =D11-C11 -> 0 | F11: 60 | G11: 3 | H11: 63 | I11: =IF(E11=0,"OK","REVER") -> OK
A12: 2017 | B12: 15 | C12: =5*B12 -> 75 | D12: =SUMIF(Base_Itens!$A$5:$A$1504,A12,Base_Itens!$I$5:$I$1504) -> 75 | E12: =D12-C12 -> 0 | F12: 65 | G12: 2 | H12: 67 | I12: =IF(E12=0,"OK","REVER") -> OK
A13: 2018 | B13: 15 | C13: =5*B13 -> 75 | D13: =SUMIF(Base_Itens!$A$5:$A$1504,A13,Base_Itens!$I$5:$I$1504) -> 75 | E13: =D13-C13 -> 0 | F13: 60 | G13: 3 | H13: 63 | I13: =IF(E13=0,"OK","REVER") -> OK
A14: 2019 | B14: 15 | C14: =5*B14 -> 75 | D14: =SUMIF(Base_Itens!$A$5:$A$1504,A14,Base_Itens!$I$5:$I$1504) -> 75 | E14: =D14-C14 -> 0 | F14: 60 | G14: 3 | H14: 63 | I14: =IF(E14=0,"OK","REVER") -> OK
A15: 2020 | B15: 15 | C15: =5*B15 -> 75 | D15: =SUMIF(Base_Itens!$A$5:$A$1504,A15,Base_Itens!$I$5:$I$1504) -> 75 | E15: =D15-C15 -> 0 | F15: 60 | G15: 3 | H15: 63 | I15: =IF(E15=0,"OK","REVER") -> OK
A16: 2021 | B16: 15 | C16: =5*B16 -> 75 | D16: =SUMIF(Base_Itens!$A$5:$A$1504,A16,Base_Itens!$I$5:$I$1504) -> 75 | E16: =D16-C16 -> 0 | F16: 55 | G16: 4 | H16: 59 | I16: =IF(E16=0,"OK","REVER") -> OK
A17: 2022 | B17: 15 | C17: =5*B17 -> 75 | D17: =SUMIF(Base_Itens!$A$5:$A$1504,A17,Base_Itens!$I$5:$I$1504) -> 75 | E17: =D17-C17 -> 0 | F17: 55 | G17: 4 | H17: 59 | I17: =IF(E17=0,"OK","REVER") -> OK
A18: 2023 | B18: 15 | C18: =5*B18 -> 75 | D18: =SUMIF(Base_Itens!$A$5:$A$1504,A18,Base_Itens!$I$5:$I$1504) -> 75 | E18: =D18-C18 -> 0 | F18: 60 | G18: 3 | H18: 63 | I18: =IF(E18=0,"OK","REVER") -> OK
A19: 2024 | B19: 10 | C19: =5*B19 -> 50 | D19: =SUMIF(Base_Itens!$A$5:$A$1504,A19,Base_Itens!$I$5:$I$1504) -> 50 | E19: =D19-C19 -> 0 | F19: 35 | G19: 3 | H19: 38 | I19: =IF(E19=0,"OK","REVER") -> OK
A20: 2025 | B20: 10 | C20: =5*B20 -> 50 | D20: =SUMIF(Base_Itens!$A$5:$A$1504,A20,Base_Itens!$I$5:$I$1504) -> 50 | E20: =D20-C20 -> 0 | F20: 45 | G20: 1 | H20: 46 | I20: =IF(E20=0,"OK","REVER") -> OK
A21: 2026 | B21: 10 | C21: =5*B21 -> 50 | D21: =SUMIF(Base_Itens!$A$5:$A$1504,A21,Base_Itens!$I$5:$I$1504) -> 50 | E21: =D21-C21 -> 0 | F21: 40 | G21: 2 | H21: 42 | I21: =IF(E21=0,"OK","REVER") -> OK
A23: TOTAL | B23: =SUM(B5:B21) -> 240 | C23: =SUM(C5:C21) -> 1200 | D23: =SUM(D5:D21) -> 1200 | E23: =SUM(E5:E21) -> 0 | F23: =SUM(F5:F21) -> 960 | G23: =SUM(G5:G21) -> 48 | H23: =SUM(H5:H21) -> 1008 | I23: =IF(E23=0,"OK","REVER") -> OK
A27: Item_ID esperado | B27: Ano | C27: Tipo | D27: Peso esperado | E27: n esperado | F27: Peso classificado | G27: Diferença | H27: Linhas / tópicos | I27: Situação | J27: Item_ID cadastrado | K27: Tópico cadastrado | L27: Repetições do par
A28: 2010-Q1-0 | B28: 2010 | C28: V/F | D28: 1 | E28: 1 | F28: =SUMIF(Base_Itens!$E$5:$E$1504,A28,Base_Itens!$I$5:$I$1504) -> 1 | G28: =F28-D28 -> 0 | H28: =COUNTIF(Base_Itens!$E$5:$E$1504,A28) -> 1 | I28: =IF(AND(G28=0,H28=E28),"OK","REVER") -> OK | J28: =Base_Itens!E5 -> 2010-Q1-0 | K28: =Base_Itens!G5 -> 01 — Contas Nacionais | L28: =COUNTIFS(Base_Itens!$E$5:$E$1504,J28,Base_Itens!$G$5:$G$1504,K28) -> 1
A29: 2010-Q1-1 | B29: 2010 | C29: V/F | D29: 1 | E29: 1 | F29: =SUMIF(Base_Itens!$E$5:$E$1504,A29,Base_Itens!$I$5:$I$1504) -> 1 | G29: =F29-D29 -> 0 | H29: =COUNTIF(Base_Itens!$E$5:$E$1504,A29) -> 1 | I29: =IF(AND(G29=0,H29=E29),"OK","REVER") -> OK | J29: =Base_Itens!E2 -> 0 | K29: =Base_Itens!G6 -> 01 — Contas Nacionais | L29: =COUNTIFS(Base_Itens!$E$5:$E$1504,J29,Base_Itens!$G$5:$G$1504,K29) -> 0
A30: 2010-Q1-2 | B30: 2010 | C30: V/F | D30: 1 | E30: 1 | F30: =SUMIF(Base_Itens!$E$5:$E$1504,A30,Base_Itens!$I$5:$I$1504) -> 1 | G30: =F30-D30 -> 0 | H30: =COUNTIF(Base_Itens!$E$5:$E$1504,A30) -> 1 | I30: =IF(AND(G30=0,H30=E30),"OK","REVER") -> OK | J30: =Base_Itens!E7 -> 2010-Q1-2 | K30: =Base_Itens!G7 -> 01 — Contas Nacionais | L30: =COUNTIFS(Base_Itens!$E$5:$E$1504,J30,Base_Itens!$G$5:$G$1504,K30) -> 1
A31: 2010-Q1-3 | B31: 2010 | C31: V/F | D31: 1 | E31: 1 | F31: =SUMIF(Base_Itens!$E$5:$E$1504,A31,Base_Itens!$I$5:$I$1504) -> 1 | G31: =F31-D31 -> 0 | H31: =COUNTIF(Base_Itens!$E$5:$E$1504,A31) -> 1 | I31: =IF(AND(G31=0,H31=E31),"OK","REVER") -> OK | J31: =Base_Itens!E8 -> 2010-Q1-3 | K31: =Base_Itens!G8 -> 01 — Contas Nacionais | L31: =COUNTIFS(Base_Itens!$E$5:$E$1504,J31,Base_Itens!$G$5:$G$1504,K31) -> 1
A32: 2010-Q1-4 | B32: 2010 | C32: V/F | D32: 1 | E32: 1 | F32: =SUMIF(Base_Itens!$E$5:$E$1504,A32,Base_Itens!$I$5:$I$1504) -> 1 | G32: =F32-D32 -> 0 | H32: =COUNTIF(Base_Itens!$E$5:$E$1504,A32) -> 1 | I32: =IF(AND(G32=0,H32=E32),"OK","REVER") -> OK | J32: =Base_Itens!E9 -> 2010-Q1-4 | K32: =Base_Itens!G9 -> 01 — Contas Nacionais | L32: =COUNTIFS(Base_Itens!$E$5:$E$1504,J32,Base_Itens!$G$5:$G$1504,K32) -> 1
A33: 2010-Q2-0 | B33: 2010 | C33: V/F | D33: 1 | E33: 1 | F33: =SUMIF(Base_Itens!$E$5:$E$1504,A33,Base_Itens!$I$5:$I$1504) -> 1 | G33: =F33-D33 -> 0 | H33: =COUNTIF(Base_Itens!$E$5:$E$1504,A33) -> 1 | I33: =IF(AND(G33=0,H33=E33),"OK","REVER") -> OK | J33: =Base_Itens!E10 -> 2010-Q2-0 | K33: =Base_Itens!G10 -> 05 — IS-LM | L33: =COUNTIFS(Base_Itens!$E$5:$E$1504,J33,Base_Itens!$G$5:$G$1504,K33) -> 1
A34: 2010-Q2-1 | B34: 2010 | C34: V/F | D34: 1 | E34: 1 | F34: =SUMIF(Base_Itens!$E$5:$E$1504,A34,Base_Itens!$I$5:$I$1504) -> 1 | G34: =F34-D34 -> 0 | H34: =COUNTIF(Base_Itens!$E$5:$E$1504,A34) -> 1 | I34: =IF(AND(G34=0,H34=E34),"OK","REVER") -> OK | J34: =Base_Itens!E11 -> 2010-Q2-1 | K34: =Base_Itens!G11 -> 05 — IS-LM | L34: =COUNTIFS(Base_Itens!$E$5:$E$1504,J34,Base_Itens!$G$5:$G$1504,K34) -> 1
A35: 2010-Q2-2 | B35: 2010 | C35: V/F | D35: 1 | E35: 1 | F35: =SUMIF(Base_Itens!$E$5:$E$1504,A35,Base_Itens!$I$5:$I$1504) -> 1 | G35: =F35-D35 -> 0 | H35: =COUNTIF(Base_Itens!$E$5:$E$1504,A35) -> 1 | I35: =IF(AND(G35=0,H35=E35),"OK","REVER") -> OK | J35: =Base_Itens!E12 -> 2010-Q2-2 | K35: =Base_Itens!G12 -> 05 — IS-LM | L35: =COUNTIFS(Base_Itens!$E$5:$E$1504,J35,Base_Itens!$G$5:$G$1504,K35) -> 1
A36: 2010-Q2-3 | B36: 2010 | C36: V/F | D36: 1 | E36: 1 | F36: =SUMIF(Base_Itens!$E$5:$E$1504,A36,Base_Itens!$I$5:$I$1504) -> 1 | G36: =F36-D36 -> 0 | H36: =COUNTIF(Base_Itens!$E$5:$E$1504,A36) -> 1 | I36: =IF(AND(G36=0,H36=E36),"OK","REVER") -> OK | J36: =Base_Itens!E13 -> 2010-Q2-3 | K36: =Base_Itens!G13 -> 05 — IS-LM | L36: =COUNTIFS(Base_Itens!$E$5:$E$1504,J36,Base_Itens!$G$5:$G$1504,K36) -> 1
A37: 2010-Q2-4 | B37: 2010 | C37: V/F | D37: 1 | E37: 1 | F37: =SUMIF(Base_Itens!$E$5:$E$1504,A37,Base_Itens!$I$5:$I$1504) -> 1 | G37: =F37-D37 -> 0 | H37: =COUNTIF(Base_Itens!$E$5:$E$1504,A37) -> 1 | I37: =IF(AND(G37=0,H37=E37),"OK","REVER") -> OK | J37: =Base_Itens!E14 -> 2010-Q2-4 | K37: =Base_Itens!G14 -> 03 — Sistema Monetário | L37: =COUNTIFS(Base_Itens!$E$5:$E$1504,J37,Base_Itens!$G$5:$G$1504,K37) -> 1
A38: 2010-Q3-0 | B38: 2010 | C38: V/F | D38: 1 | E38: 1 | F38: =SUMIF(Base_Itens!$E$5:$E$1504,A38,Base_Itens!$I$5:$I$1504) -> 1 | G38: =F38-D38 -> 0 | H38: =COUNTIF(Base_Itens!$E$5:$E$1504,A38) -> 1 | I38: =IF(AND(G38=0,H38=E38),"OK","REVER") -> OK | J38: =Base_Itens!E15 -> 2010-Q3-0 | K38: =Base_Itens!G15 -> 01 — Contas Nacionais | L38: =COUNTIFS(Base_Itens!$E$5:$E$1504,J38,Base_Itens!$G$5:$G$1504,K38) -> 1
A39: 2010-Q3-1 | B39: 2010 | C39: V/F | D39: 1 | E39: 1 | F39: =SUMIF(Base_Itens!$E$5:$E$1504,A39,Base_Itens!$I$5:$I$1504) -> 1 | G39: =F39-D39 -> 0 | H39: =COUNTIF(Base_Itens!$E$5:$E$1504,A39) -> 1 | I39: =IF(AND(G39=0,H39=E39),"OK","REVER") -> OK | J39: =Base_Itens!E16 -> 2010-Q3-1 | K39: =Base_Itens!G16 -> 01 — Contas Nacionais | L39: =COUNTIFS(Base_Itens!$E$5:$E$1504,J39,Base_Itens!$G$5:$G$1504,K39) -> 1
A40: 2010-Q3-2 | B40: 2010 | C40: V/F | D40: 1 | E40: 1 | F40: =SUMIF(Base_Itens!$E$5:$E$1504,A40,Base_Itens!$I$5:$I$1504) -> 1 | G40: =F40-D40 -> 0 | H40: =COUNTIF(Base_Itens!$E$5:$E$1504,A40) -> 1 | I40: =IF(AND(G40=0,H40=E10),"OK","REVER") -> REVER | J40: =Base_Itens!E17 -> 2010-Q3-2 | K40: =Base_Itens!G17 -> 01 — Contas Nacionais | L40: =COUNTIFS(Base_Itens!$E$5:$E$1504,J40,Base_Itens!$G$5:$G$1504,K40) -> 1
A41: 2010-Q3-3 | B41: 2010 | C41: V/F | D41: 1 | E41: 1 | F41: =SUMIF(Base_Itens!$E$5:$E$1504,A41,Base_Itens!$I$5:$I$1504) -> 1 | G41: =F41-D41 -> 0 | H41: =COUNTIF(Base_Itens!$E$5:$E$1504,A41) -> 1 | I41: =IF(AND(G41=0,H41=E11),"OK","REVER") -> REVER | J41: =Base_Itens!E18 -> 2010-Q3-3 | K41: =Base_Itens!G18 -> 01 — Contas Nacionais | L41: =COUNTIFS(Base_Itens!$E$5:$E$1504,J41,Base_Itens!$G$5:$G$1504,K41) -> 1
A42: 2010-Q3-4 | B42: 2010 | C42: V/F | D42: 1 | E42: 1 | F42: =SUMIF(Base_Itens!$E$5:$E$1504,A42,Base_Itens!$I$5:$I$1504) -> 1 | G42: =F42-D42 -> 0 | H42: =COUNTIF(Base_Itens!$E$5:$E$1504,A42) -> 1 | I42: =IF(AND(G42=0,H42=E12),"OK","REVER") -> REVER | J42: =Base_Itens!E19 -> 2010-Q3-4 | K42: =Base_Itens!G19 -> 01 — Contas Nacionais | L42: =COUNTIFS(Base_Itens!$E$5:$E$1504,J42,Base_Itens!$G$5:$G$1504,K42) -> 1
A43: 2010-Q4-0 | B43: 2010 | C43: V/F | D43: 1 | E43: 1 | F43: =SUMIF(Base_Itens!$E$5:$E$1504,A43,Base_Itens!$I$5:$I$1504) -> 1 | G43: =F43-D43 -> 0 | H43: =COUNTIF(Base_Itens!$E$5:$E$1504,A43) -> 1 | I43: =IF(AND(G43=0,H43=E13),"OK","REVER") -> REVER | J43: =Base_Itens!E20 -> 2010-Q4-0 | K43: =Base_Itens!G20 -> 03 — Sistema Monetário | L43: =COUNTIFS(Base_Itens!$E$5:$E$1504,J43,Base_Itens!$G$5:$G$1504,K43) -> 1
A44: 2010-Q4-1 | B44: 2010 | C44: V/F | D44: 1 | E44: 1 | F44: =SUMIF(Base_Itens!$E$5:$E$1504,A44,Base_Itens!$I$5:$I$1504) -> 1 | G44: =F44-D44 -> 0 | H44: =COUNTIF(Base_Itens!$E$5:$E$1504,A44) -> 1 | I44: =IF(AND(G44=0,H44=E14),"OK","REVER") -> REVER | J44: =Base_Itens!E21 -> 2010-Q4-1 | K44: =Base_Itens!G21 -> 03 — Sistema Monetário | L44: =COUNTIFS(Base_Itens!$E$5:$E$1504,J44,Base_Itens!$G$5:$G$1504,K44) -> 1
A45: 2010-Q4-2 | B45: 2010 | C45: V/F | D45: 1 | E45: 1 | F45: =SUMIF(Base_Itens!$E$5:$E$1504,A45,Base_Itens!$I$5:$I$1504) -> 1 | G45: =F45-D45 -> 0 | H45: =COUNTIF(Base_Itens!$E$5:$E$1504,A45) -> 1 | I45: =IF(AND(G45=0,H45=E15),"OK","REVER") -> REVER | J45: =Base_Itens!E22 -> 2010-Q4-2 | K45: =Base_Itens!G22 -> 03 — Sistema Monetário | L45: =COUNTIFS(Base_Itens!$E$5:$E$1504,J45,Base_Itens!$G$5:$G$1504,K45) -> 1
A46: 2010-Q4-3 | B46: 2010 | C46: V/F | D46: 1 | E46: 1 | F46: =SUMIF(Base_Itens!$E$5:$E$1504,A46,Base_Itens!$I$5:$I$1504) -> 1 | G46: =F46-D46 -> 0 | H46: =COUNTIF(Base_Itens!$E$5:$E$1504,A46) -> 1 | I46: =IF(AND(G46=0,H46=E16),"OK","REVER") -> REVER | J46: =Base_Itens!E23 -> 2010-Q4-3 | K46: =Base_Itens!G23 -> 03 — Sistema Monetário | L46: =COUNTIFS(Base_Itens!$E$5:$E$1504,J46,Base_Itens!$G$5:$G$1504,K46) -> 1
A47: 2010-Q4-4 | B47: 2010 | C47: V/F | D47: 1 | E47: 1 | F47: =SUMIF(Base_Itens!$E$5:$E$1504,A47,Base_Itens!$I$5:$I$1504) -> 1 | G47: =F47-D47 -> 0 | H47: =COUNTIF(Base_Itens!$E$5:$E$1504,A47) -> 1 | I47: =IF(AND(G47=0,H47=E17),"OK","REVER") -> REVER | J47: =Base_Itens!E24 -> 2010-Q4-4 | K47: =Base_Itens!G24 -> 03 — Sistema Monetário | L47: =COUNTIFS(Base_Itens!$E$5:$E$1504,J47,Base_Itens!$G$5:$G$1504,K47) -> 1
A48: 2010-Q5-0 | B48: 2010 | C48: V/F | D48: 1 | E48: 1 | F48: =SUMIF(Base_Itens!$E$5:$E$1504,A48,Base_Itens!$I$5:$I$1504) -> 1 | G48: =F48-D48 -> 0 | H48: =COUNTIF(Base_Itens!$E$5:$E$1504,A48) -> 1 | I48: =IF(AND(G48=0,H48=E18),"OK","REVER") -> REVER | J48: =Base_Itens!E25 -> 2010-Q5-0 | K48: =Base_Itens!G25 -> 12 — Consumo | L48: =COUNTIFS(Base_Itens!$E$5:$E$1504,J48,Base_Itens!$G$5:$G$1504,K48) -> 1
A49: 2010-Q5-1 | B49: 2010 | C49: V/F | D49: 1 | E49: 1 | F49: =SUMIF(Base_Itens!$E$5:$E$1504,A49,Base_Itens!$I$5:$I$1504) -> 1 | G49: =F49-D49 -> 0 | H49: =COUNTIF(Base_Itens!$E$5:$E$1504,A49) -> 1 | I49: =IF(AND(G49=0,H49=E19),"OK","REVER") -> REVER | J49: =Base_Itens!E26 -> 2010-Q5-1 | K49: =Base_Itens!G26 -> 12 — Consumo | L49: =COUNTIFS(Base_Itens!$E$5:$E$1504,J49,Base_Itens!$G$5:$G$1504,K49) -> 1
A50: 2010-Q5-2 | B50: 2010 | C50: V/F | D50: 1 | E50: 1 | F50: =SUMIF(Base_Itens!$E$5:$E$1504,A50,Base_Itens!$I$5:$I$1504) -> 1 | G50: =F50-D50 -> 0 | H50: =COUNTIF(Base_Itens!$E$5:$E$1504,A50) -> 1 | I50: =IF(AND(G50=0,H50=E50),"OK","REVER") -> OK | J50: =Base_Itens!E27 -> 2010-Q5-2 | K50: =Base_Itens!G27 -> 12 — Consumo | L50: =COUNTIFS(Base_Itens!$E$5:$E$1504,J50,Base_Itens!$G$5:$G$1504,K50) -> 1
A51: 2010-Q5-3 | B51: 2010 | C51: V/F | D51: 1 | E51: 1 | F51: =SUMIF(Base_Itens!$E$5:$E$1504,A51,Base_Itens!$I$5:$I$1504) -> 1 | G51: =F51-D51 -> 0 | H51: =COUNTIF(Base_Itens!$E$5:$E$1504,A51) -> 1 | I51: =IF(AND(G51=0,H51=E51),"OK","REVER") -> OK | J51: =Base_Itens!E28 -> 2010-Q5-3 | K51: =Base_Itens!G28 -> 10 — Ciclos Reais de Negócios (RBC) | L51: =COUNTIFS(Base_Itens!$E$5:$E$1504,J51,Base_Itens!$G$5:$G$1504,K51) -> 1
A52: 2010-Q5-4 | B52: 2010 | C52: V/F | D52: 1 | E52: 1 | F52: =SUMIF(Base_Itens!$E$5:$E$1504,A52,Base_Itens!$I$5:$I$1504) -> 1 | G52: =F52-D52 -> 0 | H52: =COUNTIF(Base_Itens!$E$5:$E$1504,A52) -> 1 | I52: =IF(AND(G52=0,H52=E52),"OK","REVER") -> OK | J52: =Base_Itens!E29 -> 2010-Q5-4 | K52: =Base_Itens!G29 -> 09 — Expectativas, Novos Clássicos e Novos Keynesianos | L52: =COUNTIFS(Base_Itens!$E$5:$E$1504,J52,Base_Itens!$G$5:$G$1504,K52) -> 1
A53: 2010-Q6-0 | B53: 2010 | C53: V/F | D53: 1 | E53: 1 | F53: =SUMIF(Base_Itens!$E$5:$E$1504,A53,Base_Itens!$I$5:$I$1504) -> 1 | G53: =F53-D53 -> 0 | H53: =COUNTIF(Base_Itens!$E$5:$E$1504,A53) -> 1 | I53: =IF(AND(G53=0,H53=E53),"OK","REVER") -> OK | J53: =Base_Itens!E30 -> 2010-Q6-0 | K53: =Base_Itens!G30 -> 07a — Paridades | L53: =COUNTIFS(Base_Itens!$E$5:$E$1504,J53,Base_Itens!$G$5:$G$1504,K53) -> 1
A54: 2010-Q6-1 | B54: 2010 | C54: V/F | D54: 1 | E54: 1 | F54: =SUMIF(Base_Itens!$E$5:$E$1504,A54,Base_Itens!$I$5:$I$1504) -> 1 | G54: =F54-D54 -> 0 | H54: =COUNTIF(Base_Itens!$E$5:$E$1504,A54) -> 1 | I54: =IF(AND(G54=0,H54=E54),"OK","REVER") -> OK | J54: =Base_Itens!E31 -> 2010-Q6-1 | K54: =Base_Itens!G31 -> 07a — Paridades | L54: =COUNTIFS(Base_Itens!$E$5:$E$1504,J54,Base_Itens!$G$5:$G$1504,K54) -> 1
A55: 2010-Q6-2 | B55: 2010 | C55: V/F | D55: 1 | E55: 2 | F55: =SUMIF(Base_Itens!$E$5:$E$1504,A55,Base_Itens!$I$5:$I$1504) -> 1 | G55: =F55-D55 -> 0 | H55: =COUNTIF(Base_Itens!$E$5:$E$1504,A55) -> 2 | I55: =IF(AND(G55=0,H55=E55),"OK","REVER") -> OK | J55: =Base_Itens!E32 -> 2010-Q6-2 | K55: =Base_Itens!G32 -> 04 — Demanda por Moeda | L55: =COUNTIFS(Base_Itens!$E$5:$E$1504,J55,Base_Itens!$G$5:$G$1504,K55) -> 1
A56: 2010-Q6-3 | B56: 2010 | C56: V/F | D56: 1 | E56: 1 | F56: =SUMIF(Base_Itens!$E$5:$E$1504,A56,Base_Itens!$I$5:$I$1504) -> 1 | G56: =F56-D56 -> 0 | H56: =COUNTIF(Base_Itens!$E$5:$E$1504,A56) -> 1 | I56: =IF(AND(G56=0,H56=E56),"OK","REVER") -> OK | J56: =Base_Itens!E33 -> 2010-Q6-2 | K56: =Base_Itens!G33 -> 07a — Paridades | L56: =COUNTIFS(Base_Itens!$E$5:$E$1504,J56,Base_Itens!$G$5:$G$1504,K56) -> 1
A57: 2010-Q6-4 | B57: 2010 | C57: V/F | D57: 1 | E57: 1 | F57: =SUMIF(Base_Itens!$E$5:$E$1504,A57,Base_Itens!$I$5:$I$1504) -> 1 | G57: =F57-D57 -> 0 | H57: =COUNTIF(Base_Itens!$E$5:$E$1504,A57) -> 1 | I57: =IF(AND(G57=0,H57=E57),"OK","REVER") -> OK | J57: =Base_Itens!E34 -> 2010-Q6-3 | K57: =Base_Itens!G34 -> 06 — IS-LM-BP | L57: =COUNTIFS(Base_Itens!$E$5:$E$1504,J57,Base_Itens!$G$5:$G$1504,K57) -> 1
A58: 2010-Q7-0 | B58: 2010 | C58: V/F | D58: 1 | E58: 1 | F58: =SUMIF(Base_Itens!$E$5:$E$1504,A58,Base_Itens!$I$5:$I$1504) -> 1 | G58: =F58-D58 -> 0 | H58: =COUNTIF(Base_Itens!$E$5:$E$1504,A58) -> 1 | I58: =IF(AND(G58=0,H58=E58),"OK","REVER") -> OK | J58: =Base_Itens!E35 -> 2010-Q6-4 | K58: =Base_Itens!G35 -> 06 — IS-LM-BP | L58: =COUNTIFS(Base_Itens!$E$5:$E$1504,J58,Base_Itens!$G$5:$G$1504,K58) -> 1
A59: 2010-Q7-1 | B59: 2010 | C59: V/F | D59: 1 | E59: 1 | F59: =SUMIF(Base_Itens!$E$5:$E$1504,A59,Base_Itens!$I$5:$I$1504) -> 1 | G59: =F59-D59 -> 0 | H59: =COUNTIF(Base_Itens!$E$5:$E$1504,A59) -> 1 | I59: =IF(AND(G59=0,H59=E59),"OK","REVER") -> OK | J59: =Base_Itens!E36 -> 2010-Q7-0 | K59: =Base_Itens!G36 -> 05 — IS-LM | L59: =COUNTIFS(Base_Itens!$E$5:$E$1504,J59,Base_Itens!$G$5:$G$1504,K59) -> 1
A60: 2010-Q7-2 | B60: 2010 | C60: V/F | D60: 1 | E60: 1 | F60: =SUMIF(Base_Itens!$E$5:$E$1504,A60,Base_Itens!$I$5:$I$1504) -> 1 | G60: =F60-D60 -> 0 | H60: =COUNTIF(Base_Itens!$E$5:$E$1504,A60) -> 1 | I60: =IF(AND(G60=0,H60=E20),"OK","REVER") -> REVER | J60: =Base_Itens!E37 -> 2010-Q7-1 | K60: =Base_Itens!G37 -> 05 — IS-LM | L60: =COUNTIFS(Base_Itens!$E$5:$E$1504,J60,Base_Itens!$G$5:$G$1504,K60) -> 1
A61: 2010-Q7-3 | B61: 2010 | C61: V/F | D61: 1 | E61: 1 | F61: =SUMIF(Base_Itens!$E$5:$E$1504,A61,Base_Itens!$I$5:$I$1504) -> 1 | G61: =F61-D61 -> 0 | H61: =COUNTIF(Base_Itens!$E$5:$E$1504,A61) -> 1 | I61: =IF(AND(G61=0,H61=E21),"OK","REVER") -> REVER | J61: =Base_Itens!E38 -> 2010-Q7-2 | K61: =Base_Itens!G38 -> 05 — IS-LM | L61: =COUNTIFS(Base_Itens!$E$5:$E$1504,J61,Base_Itens!$G$5:$G$1504,K61) -> 1
A62: 2010-Q7-4 | B62: 2010 | C62: V/F | D62: 1 | E62: 1 | F62: =SUMIF(Base_Itens!$E$5:$E$1504,A62,Base_Itens!$I$5:$I$1504) -> 1 | G62: =F62-D62 -> 0 | H62: =COUNTIF(Base_Itens!$E$5:$E$1504,A62) -> 1 | I62: =IF(AND(G62=0,H62=E22),"OK","REVER") -> REVER | J62: =Base_Itens!E39 -> 2010-Q7-3 | K62: =Base_Itens!G39 -> 05 — IS-LM | L62: =COUNTIFS(Base_Itens!$E$5:$E$1504,J62,Base_Itens!$G$5:$G$1504,K62) -> 1
A63: 2010-Q8-0 | B63: 2010 | C63: V/F | D63: 1 | E63: 1 | F63: =SUMIF(Base_Itens!$E$5:$E$1504,A63,Base_Itens!$I$5:$I$1504) -> 1 | G63: =F63-D63 -> 0 | H63: =COUNTIF(Base_Itens!$E$5:$E$1504,A63) -> 1 | I63: =IF(AND(G63=0,H63=E23),"OK","REVER") -> REVER | J63: =Base_Itens!E10 -> 2010-Q2-0 | K63: =Base_Itens!G40 -> 05 — IS-LM | L63: =COUNTIFS(Base_Itens!$E$5:$E$1504,J63,Base_Itens!$G$5:$G$1504,K63) -> 1
A64: 2010-Q8-1 | B64: 2010 | C64: V/F | D64: 1 | E64: 1 | F64: =SUMIF(Base_Itens!$E$5:$E$1504,A64,Base_Itens!$I$5:$I$1504) -> 1 | G64: =F64-D64 -> 0 | H64: =COUNTIF(Base_Itens!$E$5:$E$1504,A64) -> 1 | I64: =IF(AND(G64=0,H64=E24),"OK","REVER") -> REVER | J64: =Base_Itens!E11 -> 2010-Q2-1 | K64: =Base_Itens!G41 -> 08 — Curva de Phillips | L64: =COUNTIFS(Base_Itens!$E$5:$E$1504,J64,Base_Itens!$G$5:$G$1504,K64) -> 0
A65: 2010-Q8-2 | B65: 2010 | C65: V/F | D65: 1 | E65: 1 | F65: =SUMIF(Base_Itens!$E$5:$E$1504,A65,Base_Itens!$I$5:$I$1504) -> 1 | G65: =F65-D65 -> 0 | H65: =COUNTIF(Base_Itens!$E$5:$E$1504,A65) -> 1 | I65: =IF(AND(G65=0,H65=E25),"OK","REVER") -> REVER | J65: =Base_Itens!E12 -> 2010-Q2-2 | K65: =Base_Itens!G42 -> 08 — Curva de Phillips | L65: =COUNTIFS(Base_Itens!$E$5:$E$1504,J65,Base_Itens!$G$5:$G$1504,K65) -> 0
A66: 2010-Q8-3 | B66: 2010 | C66: V/F | D66: 1 | E66: 1 | F66: =SUMIF(Base_Itens!$E$5:$E$1504,A66,Base_Itens!$I$5:$I$1504) -> 1 | G66: =F66-D66 -> 0 | H66: =COUNTIF(Base_Itens!$E$5:$E$1504,A66) -> 1 | I66: =IF(AND(G66=0,H66=E26),"OK","REVER") -> REVER | J66: =Base_Itens!E13 -> 2010-Q2-3 | K66: =Base_Itens!G43 -> 08 — Curva de Phillips | L66: =COUNTIFS(Base_Itens!$E$5:$E$1504,J66,Base_Itens!$G$5:$G$1504,K66) -> 0
A67: 2010-Q8-4 | B67: 2010 | C67: V/F | D67: 1 | E67: 1 | F67: =SUMIF(Base_Itens!$E$5:$E$1504,A67,Base_Itens!$I$5:$I$1504) -> 1 | G67: =F67-D67 -> 0 | H67: =COUNTIF(Base_Itens!$E$5:$E$1504,A67) -> 1 | I67: =IF(AND(G67=0,H67=E27),"OK","REVER") -> REVER | J67: =Base_Itens!E14 -> 2010-Q2-4 | K67: =Base_Itens!G44 -> 08 — Curva de Phillips | L67: =COUNTIFS(Base_Itens!$E$5:$E$1504,J67,Base_Itens!$G$5:$G$1504,K67) -> 0
A68: 2010-Q9-0 | B68: 2010 | C68: V/F | D68: 1 | E68: 1 | F68: =SUMIF(Base_Itens!$E$5:$E$1504,A68,Base_Itens!$I$5:$I$1504) -> 1 | G68: =F68-D68 -> 0 | H68: =COUNTIF(Base_Itens!$E$5:$E$1504,A68) -> 1 | I68: =IF(AND(G68=0,H68=E28),"OK","REVER") -> OK | J68: =Base_Itens!E15 -> 2010-Q3-0 | K68: =Base_Itens!G45 -> 08 — Curva de Phillips | L68: =COUNTIFS(Base_Itens!$E$5:$E$1504,J68,Base_Itens!$G$5:$G$1504,K68) -> 0
A69: 2010-Q9-1 | B69: 2010 | C69: V/F | D69: 1 | E69: 1 | F69: =SUMIF(Base_Itens!$E$5:$E$1504,A69,Base_Itens!$I$5:$I$1504) -> 1 | G69: =F69-D69 -> 0 | H69: =COUNTIF(Base_Itens!$E$5:$E$1504,A69) -> 1 | I69: =IF(AND(G69=0,H69=E29),"OK","REVER") -> OK | J69: =Base_Itens!E16 -> 2010-Q3-1 | K69: =Base_Itens!G46 -> 09 — Expectativas, Novos Clássicos e Novos Keynesianos | L69: =COUNTIFS(Base_Itens!$E$5:$E$1504,J69,Base_Itens!$G$5:$G$1504,K69) -> 0
A70: 2010-Q9-2 | B70: 2010 | C70: V/F | D70: 1 | E70: 1 | F70: =SUMIF(Base_Itens!$E$5:$E$1504,A70,Base_Itens!$I$5:$I$1504) -> 1 | G70: =F70-D70 -> 0 | H70: =COUNTIF(Base_Itens!$E$5:$E$1504,A70) -> 1 | I70: =IF(AND(G70=0,H70=E70),"OK","REVER") -> OK | J70: =Base_Itens!E17 -> 2010-Q3-2 | K70: =Base_Itens!G47 -> 09 — Expectativas, Novos Clássicos e Novos Keynesianos | L70: =COUNTIFS(Base_Itens!$E$5:$E$1504,J70,Base_Itens!$G$5:$G$1504,K70) -> 0
A71: 2010-Q9-3 | B71: 2010 | C71: V/F | D71: 1 | E71: 1 | F71: =SUMIF(Base_Itens!$E$5:$E$1504,A71,Base_Itens!$I$5:$I$1504) -> 1 | G71: =F71-D71 -> 0 | H71: =COUNTIF(Base_Itens!$E$5:$E$1504,A71) -> 1 | I71: =IF(AND(G71=0,H71=E71),"OK","REVER") -> OK | J71: =Base_Itens!E18 -> 2010-Q3-3 | K71: =Base_Itens!G48 -> 09 — Expectativas, Novos Clássicos e Novos Keynesianos | L71: =COUNTIFS(Base_Itens!$E$5:$E$1504,J71,Base_Itens!$G$5:$G$1504,K71) -> 0
A72: 2010-Q9-4 | B72: 2010 | C72: V/F | D72: 1 | E72: 1 | F72: =SUMIF(Base_Itens!$E$5:$E$1504,A72,Base_Itens!$I$5:$I$1504) -> 1 | G72: =F72-D72 -> 0 | H72: =COUNTIF(Base_Itens!$E$5:$E$1504,A72) -> 1 | I72: =IF(AND(G72=0,H72=E72),"OK","REVER") -> OK | J72: =Base_Itens!E19 -> 2010-Q3-4 | K72: =Base_Itens!G49 -> 09 — Expectativas, Novos Clássicos e Novos Keynesianos | L72: =COUNTIFS(Base_Itens!$E$5:$E$1504,J72,Base_Itens!$G$5:$G$1504,K72) -> 0
A73: 2010-Q10-0 | B73: 2010 | C73: V/F | D73: 1 | E73: 1 | F73: =SUMIF(Base_Itens!$E$5:$E$1504,A73,Base_Itens!$I$5:$I$1504) -> 1 | G73: =F73-D73 -> 0 | H73: =COUNTIF(Base_Itens!$E$5:$E$1504,A73) -> 1 | I73: =IF(AND(G73=0,H73=E73),"OK","REVER") -> OK | J73: =Base_Itens!E50 -> 2010-Q9-4 | K73: =Base_Itens!G50 -> 09 — Expectativas, Novos Clássicos e Novos Keynesianos | L73: =COUNTIFS(Base_Itens!$E$5:$E$1504,J73,Base_Itens!$G$5:$G$1504,K73) -> 1
A74: 2010-Q10-1 | B74: 2010 | C74: V/F | D74: 1 | E74: 1 | F74: =SUMIF(Base_Itens!$E$5:$E$1504,A74,Base_Itens!$I$5:$I$1504) -> 1 | G74: =F74-D74 -> 0 | H74: =COUNTIF(Base_Itens!$E$5:$E$1504,A74) -> 1 | I74: =IF(AND(G74=0,H74=E74),"OK","REVER") -> OK | J74: =Base_Itens!E51 -> 2010-Q10-0 | K74: =Base_Itens!G51 -> 11 — Crescimento Econômico | L74: =COUNTIFS(Base_Itens!$E$5:$E$1504,J74,Base_Itens!$G$5:$G$1504,K74) -> 1
A75: 2010-Q10-2 | B75: 2010 | C75: V/F | D75: 1 | E75: 1 | F75: =SUMIF(Base_Itens!$E$5:$E$1504,A75,Base_Itens!$I$5:$I$1504) -> 1 | G75: =F75-D75 -> 0 | H75: =COUNTIF(Base_Itens!$E$5:$E$1504,A75) -> 1 | I75: =IF(AND(G75=0,H75=E75),"OK","REVER") -> OK | J75: =Base_Itens!E52 -> 2010-Q10-1 | K75: =Base_Itens!G52 -> 11 — Crescimento Econômico | L75: =COUNTIFS(Base_Itens!$E$5:$E$1504,J75,Base_Itens!$G$5:$G$1504,K75) -> 1
A76: 2010-Q10-3 | B76: 2010 | C76: V/F | D76: 1 | E76: 1 | F76: =SUMIF(Base_Itens!$E$5:$E$1504,A76,Base_Itens!$I$5:$I$1504) -> 1 | G76: =F76-D76 -> 0 | H76: =COUNTIF(Base_Itens!$E$5:$E$1504,A76) -> 1 | I76: =IF(AND(G76=0,H76=E76),"OK","REVER") -> OK | J76: =Base_Itens!E53 -> 2010-Q10-2 | K76: =Base_Itens!G53 -> 11 — Crescimento Econômico | L76: =COUNTIFS(Base_Itens!$E$5:$E$1504,J76,Base_Itens!$G$5:$G$1504,K76) -> 1
A77: 2010-Q10-4 | B77: 2010 | C77: V/F | D77: 1 | E77: 1 | F77: =SUMIF(Base_Itens!$E$5:$E$1504,A77,Base_Itens!$I$5:$I$1504) -> 1 | G77: =F77-D77 -> 0 | H77: =COUNTIF(Base_Itens!$E$5:$E$1504,A77) -> 1 | I77: =IF(AND(G77=0,H77=E77),"OK","REVER") -> OK | J77: =Base_Itens!E54 -> 2010-Q10-3 | K77: =Base_Itens!G54 -> 11 — Crescimento Econômico | L77: =COUNTIFS(Base_Itens!$E$5:$E$1504,J77,Base_Itens!$G$5:$G$1504,K77) -> 1
A78: 2010-Q11-0 | B78: 2010 | C78: V/F | D78: 1 | E78: 1 | F78: =SUMIF(Base_Itens!$E$5:$E$1504,A78,Base_Itens!$I$5:$I$1504) -> 1 | G78: =F78-D78 -> 0 | H78: =COUNTIF(Base_Itens!$E$5:$E$1504,A78) -> 1 | I78: =IF(AND(G78=0,H78=E78),"OK","REVER") -> OK | J78: =Base_Itens!E55 -> 2010-Q10-4 | K78: =Base_Itens!G55 -> 11 — Crescimento Econômico | L78: =COUNTIFS(Base_Itens!$E$5:$E$1504,J78,Base_Itens!$G$5:$G$1504,K78) -> 1
A79: 2010-Q11-1 | B79: 2010 | C79: V/F | D79: 1 | E79: 1 | F79: =SUMIF(Base_Itens!$E$5:$E$1504,A79,Base_Itens!$I$5:$I$1504) -> 1 | G79: =F79-D79 -> 0 | H79: =COUNTIF(Base_Itens!$E$5:$E$1504,A79) -> 1 | I79: =IF(AND(G79=0,H79=E79),"OK","REVER") -> OK | J79: =Base_Itens!E56 -> 2010-Q11-0 | K79: =Base_Itens!G56 -> 11 — Crescimento Econômico | L79: =COUNTIFS(Base_Itens!$E$5:$E$1504,J79,Base_Itens!$G$5:$G$1504,K79) -> 1
A80: 2010-Q11-2 | B80: 2010 | C80: V/F | D80: 1 | E80: 1 | F80: =SUMIF(Base_Itens!$E$5:$E$1504,A80,Base_Itens!$I$5:$I$1504) -> 1 | G80: =F80-D80 -> 0 | H80: =COUNTIF(Base_Itens!$E$5:$E$1504,A80) -> 1 | I80: =IF(AND(G80=0,H80=E80),"OK","REVER") -> OK | J80: =Base_Itens!E57 -> 2010-Q11-1 | K80: =Base_Itens!G57 -> 11 — Crescimento Econômico | L80: =COUNTIFS(Base_Itens!$E$5:$E$1504,J80,Base_Itens!$G$5:$G$1504,K80) -> 1
A81: 2010-Q11-3 | B81: 2010 | C81: V/F | D81: 1 | E81: 1 | F81: =SUMIF(Base_Itens!$E$5:$E$1504,A81,Base_Itens!$I$5:$I$1504) -> 1 | G81: =F81-D81 -> 0 | H81: =COUNTIF(Base_Itens!$E$5:$E$1504,A81) -> 1 | I81: =IF(AND(G81=0,H81=E81),"OK","REVER") -> OK | J81: =Base_Itens!E58 -> 2010-Q11-2 | K81: =Base_Itens!G58 -> 11 — Crescimento Econômico | L81: =COUNTIFS(Base_Itens!$E$5:$E$1504,J81,Base_Itens!$G$5:$G$1504,K81) -> 1
A82: 2010-Q11-4 | B82: 2010 | C82: V/F | D82: 1 | E82: 1 | F82: =SUMIF(Base_Itens!$E$5:$E$1504,A82,Base_Itens!$I$5:$I$1504) -> 1 | G82: =F82-D82 -> 0 | H82: =COUNTIF(Base_Itens!$E$5:$E$1504,A82) -> 1 | I82: =IF(AND(G82=0,H82=E82),"OK","REVER") -> OK | J82: =Base_Itens!E59 -> 2010-Q11-3 | K82: =Base_Itens!G59 -> 11 — Crescimento Econômico | L82: =COUNTIFS(Base_Itens!$E$5:$E$1504,J82,Base_Itens!$G$5:$G$1504,K82) -> 1
A83: 2010-Q12-ABERTA | B83: 2010 | C83: Tipo B | D83: 5 | E83: 1 | F83: =SUMIF(Base_Itens!$E$5:$E$1504,A83,Base_Itens!$I$5:$I$1504) -> 5 | G83: =F83-D83 -> 0 | H83: =COUNTIF(Base_Itens!$E$5:$E$1504,A83) -> 1 | I83: =IF(AND(G83=0,H83=E83),"OK","REVER") -> OK | J83: =Base_Itens!E20 -> 2010-Q4-0 | K83: =Base_Itens!G60 -> 11 — Crescimento Econômico | L83: =COUNTIFS(Base_Itens!$E$5:$E$1504,J83,Base_Itens!$G$5:$G$1504,K83) -> 0
A84: 2010-Q13-ABERTA | B84: 2010 | C84: Tipo B | D84: 5 | E84: 2 | F84: =SUMIF(Base_Itens!$E$5:$E$1504,A84,Base_Itens!$I$5:$I$1504) -> 5 | G84: =F84-D84 -> 0 | H84: =COUNTIF(Base_Itens!$E$5:$E$1504,A84) -> 2 | I84: =IF(AND(G84=0,H84=E84),"OK","REVER") -> OK | J84: =Base_Itens!E21 -> 2010-Q4-1 | K84: =Base_Itens!G61 -> 07a — Paridades | L84: =COUNTIFS(Base_Itens!$E$5:$E$1504,J84,Base_Itens!$G$5:$G$1504,K84) -> 0
A85: 2010-Q14-ABERTA | B85: 2010 | C85: Tipo B | D85: 5 | E85: 3 | F85: =SUMIF(Base_Itens!$E$5:$E$1504,A85,Base_Itens!$I$5:$I$1504) -> 5 | G85: =F85-D85 -> 0 | H85: =COUNTIF(Base_Itens!$E$5:$E$1504,A85) -> 3 | I85: =IF(AND(G85=0,H85=E85),"OK","REVER") -> OK | J85: =Base_Itens!E22 -> 2010-Q4-2 | K85: =Base_Itens!G62 -> 07b — OA-DA | L85: =COUNTIFS(Base_Itens!$E$5:$E$1504,J85,Base_Itens!$G$5:$G$1504,K85) -> 0
A86: 2010-Q15-ABERTA | B86: 2010 | C86: Tipo B | D86: 5 | E86: 1 | F86: =SUMIF(Base_Itens!$E$5:$E$1504,A86,Base_Itens!$I$5:$I$1504) -> 5 | G86: =F86-D86 -> 0 | H86: =COUNTIF(Base_Itens!$E$5:$E$1504,A86) -> 1 | I86: =IF(AND(G86=0,H86=E86),"OK","REVER") -> OK | J86: =Base_Itens!E23 -> 2010-Q4-3 | K86: =Base_Itens!G63 -> 08 — Curva de Phillips | L86: =COUNTIFS(Base_Itens!$E$5:$E$1504,J86,Base_Itens!$G$5:$G$1504,K86) -> 0
A87: 2011-Q1-0 | B87: 2011 | C87: V/F | D87: 1 | E87: 1 | F87: =SUMIF(Base_Itens!$E$5:$E$1504,A87,Base_Itens!$I$5:$I$1504) -> 1 | G87: =F87-D87 -> 0 | H87: =COUNTIF(Base_Itens!$E$5:$E$1504,A87) -> 1 | I87: =IF(AND(G87=0,H87=E87),"OK","REVER") -> OK | J87: =Base_Itens!E24 -> 2010-Q4-4 | K87: =Base_Itens!G64 -> 03 — Sistema Monetário | L87: =COUNTIFS(Base_Itens!$E$5:$E$1504,J87,Base_Itens!$G$5:$G$1504,K87) -> 1
A88: 2011-Q1-1 | B88: 2011 | C88: V/F | D88: 1 | E88: 1 | F88: =SUMIF(Base_Itens!$E$5:$E$1504,A88,Base_Itens!$I$5:$I$1504) -> 1 | G88: =F88-D88 -> 0 | H88: =COUNTIF(Base_Itens!$E$5:$E$1504,A88) -> 1 | I88: =IF(AND(G88=0,H88=E88),"OK","REVER") -> OK | J88: =Base_Itens!E25 -> 2010-Q5-0 | K88: =Base_Itens!G65 -> 04 — Demanda por Moeda | L88: =COUNTIFS(Base_Itens!$E$5:$E$1504,J88,Base_Itens!$G$5:$G$1504,K88) -> 0
A89: 2011-Q1-2 | B89: 2011 | C89: V/F | D89: 1 | E89: 1 | F89: =SUMIF(Base_Itens!$E$5:$E$1504,A89,Base_Itens!$I$5:$I$1504) -> 1 | G89: =F89-D89 -> 0 | H89: =COUNTIF(Base_Itens!$E$5:$E$1504,A89) -> 1 | I89: =IF(AND(G89=0,H89=E89),"OK","REVER") -> OK | J89: =Base_Itens!E26 -> 2010-Q5-1 | K89: =Base_Itens!G66 -> 14 — Dívida Pública e Senhoriagem | L89: =COUNTIFS(Base_Itens!$E$5:$E$1504,J89,Base_Itens!$G$5:$G$1504,K89) -> 0
A90: 2011-Q1-3 | B90: 2011 | C90: V/F | D90: 1 | E90: 1 | F90: =SUMIF(Base_Itens!$E$5:$E$1504,A90,Base_Itens!$I$5:$I$1504) -> 1 | G90: =F90-D90 -> 0 | H90: =COUNTIF(Base_Itens!$E$5:$E$1504,A90) -> 1 | I90: =IF(AND(G90=0,H90=E90),"OK","REVER") -> OK | J90: =Base_Itens!E27 -> 2010-Q5-2 | K90: =Base_Itens!G67 -> 06 — IS-LM-BP | L90: =COUNTIFS(Base_Itens!$E$5:$E$1504,J90,Base_Itens!$G$5:$G$1504,K90) -> 0
A91: 2011-Q1-4 | B91: 2011 | C91: V/F | D91: 1 | E91: 1 | F91: =SUMIF(Base_Itens!$E$5:$E$1504,A91,Base_Itens!$I$5:$I$1504) -> 1 | G91: =F91-D91 -> 0 | H91: =COUNTIF(Base_Itens!$E$5:$E$1504,A91) -> 1 | I91: =IF(AND(G91=0,H91=E91),"OK","REVER") -> OK | J91: =Base_Itens!E28 -> 2010-Q5-3 | K91: =Base_Itens!G68 -> 01 — Contas Nacionais | L91: =COUNTIFS(Base_Itens!$E$5:$E$1504,J91,Base_Itens!$G$5:$G$1504,K91) -> 0
A92: 2011-Q2-0 | B92: 2011 | C92: V/F | D92: 1 | E92: 1 | F92: =SUMIF(Base_Itens!$E$5:$E$1504,A92,Base_Itens!$I$5:$I$1504) -> 1 | G92: =F92-D92 -> 0 | H92: =COUNTIF(Base_Itens!$E$5:$E$1504,A92) -> 1 | I92: =IF(AND(G92=0,H92=E92),"OK","REVER") -> OK | J92: =Base_Itens!E29 -> 2010-Q5-4 | K92: =Base_Itens!G69 -> 01 — Contas Nacionais | L92: =COUNTIFS(Base_Itens!$E$5:$E$1504,J92,Base_Itens!$G$5:$G$1504,K92) -> 0
A93: 2011-Q2-1 | B93: 2011 | C93: V/F | D93: 1 | E93: 1 | F93: =SUMIF(Base_Itens!$E$5:$E$1504,A93,Base_Itens!$I$5:$I$1504) -> 1 | G93: =F93-D93 -> 0 | H93: =COUNTIF(Base_Itens!$E$5:$E$1504,A93) -> 1 | I93: =IF(AND(G93=0,H93=E93),"OK","REVER") -> OK | J93: =Base_Itens!E70 -> 2011-Q1-2 | K93: =Base_Itens!G70 -> 01 — Contas Nacionais | L93: =COUNTIFS(Base_Itens!$E$5:$E$1504,J93,Base_Itens!$G$5:$G$1504,K93) -> 1
A94: 2011-Q2-2 | B94: 2011 | C94: V/F | D94: 1 | E94: 1 | F94: =SUMIF(Base_Itens!$E$5:$E$1504,A94,Base_Itens!$I$5:$I$1504) -> 1 | G94: =F94-D94 -> 0 | H94: =COUNTIF(Base_Itens!$E$5:$E$1504,A94) -> 1 | I94: =IF(AND(G94=0,H94=E94),"OK","REVER") -> OK | J94: =Base_Itens!E71 -> 2011-Q1-3 | K94: =Base_Itens!G71 -> 01 — Contas Nacionais | L94: =COUNTIFS(Base_Itens!$E$5:$E$1504,J94,Base_Itens!$G$5:$G$1504,K94) -> 1
A95: 2011-Q2-3 | B95: 2011 | C95: V/F | D95: 1 | E95: 1 | F95: =SUMIF(Base_Itens!$E$5:$E$1504,A95,Base_Itens!$I$5:$I$1504) -> 1 | G95: =F95-D95 -> 0 | H95: =COUNTIF(Base_Itens!$E$5:$E$1504,A95) -> 1 | I95: =IF(AND(G95=0,H95=E95),"OK","REVER") -> OK | J95: =Base_Itens!E72 -> 2011-Q1-4 | K95: =Base_Itens!G72 -> 01 — Contas Nacionais | L95: =COUNTIFS(Base_Itens!$E$5:$E$1504,J95,Base_Itens!$G$5:$G$1504,K95) -> 1
A96: 2011-Q2-4 | B96: 2011 | C96: V/F | D96: 1 | E96: 1 | F96: =SUMIF(Base_Itens!$E$5:$E$1504,A96,Base_Itens!$I$5:$I$1504) -> 1 | G96: =F96-D96 -> 0 | H96: =COUNTIF(Base_Itens!$E$5:$E$1504,A96) -> 1 | I96: =IF(AND(G96=0,H96=E96),"OK","REVER") -> OK | J96: =Base_Itens!E73 -> 2011-Q2-0 | K96: =Base_Itens!G73 -> 03 — Sistema Monetário | L96: =COUNTIFS(Base_Itens!$E$5:$E$1504,J96,Base_Itens!$G$5:$G$1504,K96) -> 1
A97: 2011-Q3-0 | B97: 2011 | C97: V/F | D97: 1 | E97: 1 | F97: =SUMIF(Base_Itens!$E$5:$E$1504,A97,Base_Itens!$I$5:$I$1504) -> 1 | G97: =F97-D97 -> 0 | H97: =COUNTIF(Base_Itens!$E$5:$E$1504,A97) -> 1 | I97: =IF(AND(G97=0,H97=E97),"OK","REVER") -> OK | J97: =Base_Itens!E74 -> 2011-Q2-1 | K97: =Base_Itens!G74 -> 03 — Sistema Monetário | L97: =COUNTIFS(Base_Itens!$E$5:$E$1504,J97,Base_Itens!$G$5:$G$1504,K97) -> 1
A98: 2011-Q3-1 | B98: 2011 | C98: V/F | D98: 1 | E98: 1 | F98: =SUMIF(Base_Itens!$E$5:$E$1504,A98,Base_Itens!$I$5:$I$1504) -> 1 | G98: =F98-D98 -> 0 | H98: =COUNTIF(Base_Itens!$E$5:$E$1504,A98) -> 1 | I98: =IF(AND(G98=0,H98=E98),"OK","REVER") -> OK | J98: =Base_Itens!E75 -> 2011-Q2-2 | K98: =Base_Itens!G75 -> 03 — Sistema Monetário | L98: =COUNTIFS(Base_Itens!$E$5:$E$1504,J98,Base_Itens!$G$5:$G$1504,K98) -> 1
A99: 2011-Q3-2 | B99: 2011 | C99: V/F | D99: 1 | E99: 1 | F99: =SUMIF(Base_Itens!$E$5:$E$1504,A99,Base_Itens!$I$5:$I$1504) -> 1 | G99: =F99-D99 -> 0 | H99: =COUNTIF(Base_Itens!$E$5:$E$1504,A99) -> 1 | I99: =IF(AND(G99=0,H99=E99),"OK","REVER") -> OK | J99: =Base_Itens!E76 -> 2011-Q2-3 | K99: =Base_Itens!G76 -> 03 — Sistema Monetário | L99: =COUNTIFS(Base_Itens!$E$5:$E$1504,J99,Base_Itens!$G$5:$G$1504,K99) -> 1
A100: 2011-Q3-3 | B100: 2011 | C100: V/F | D100: 1 | E100: 1 | F100: =SUMIF(Base_Itens!$E$5:$E$1504,A100,Base_Itens!$I$5:$I$1504) -> 1 | G100: =F100-D100 -> 0 | H100: =COUNTIF(Base_Itens!$E$5:$E$1504,A100) -> 1 | I100: =IF(AND(G100=0,H100=E100),"OK","REVER") -> OK | J100: =Base_Itens!E77 -> 2011-Q2-4 | K100: =Base_Itens!G77 -> 03 — Sistema Monetário | L100: =COUNTIFS(Base_Itens!$E$5:$E$1504,J100,Base_Itens!$G$5:$G$1504,K100) -> 1
A101: 2011-Q3-4 | B101: 2011 | C101: V/F | D101: 1 | E101: 1 | F101: =SUMIF(Base_Itens!$E$5:$E$1504,A101,Base_Itens!$I$5:$I$1504) -> 1 | G101: =F101-D101 -> 0 | H101: =COUNTIF(Base_Itens!$E$5:$E$1504,A101) -> 1 | I101: =IF(AND(G101=0,H101=E101),"OK","REVER") -> OK | J101: =Base_Itens!E78 -> 2011-Q3-0 | K101: =Base_Itens!G78 -> 02 — Balanço de Pagamentos | L101: =COUNTIFS(Base_Itens!$E$5:$E$1504,J101,Base_Itens!$G$5:$G$1504,K101) -> 1
A102: 2011-Q4-0 | B102: 2011 | C102: V/F | D102: 1 | E102: 1 | F102: =SUMIF(Base_Itens!$E$5:$E$1504,A102,Base_Itens!$I$5:$I$1504) -> 1 | G102: =F102-D102 -> 0 | H102: =COUNTIF(Base_Itens!$E$5:$E$1504,A102) -> 1 | I102: =IF(AND(G102=0,H102=E102),"OK","REVER") -> OK | J102: =Base_Itens!E79 -> 2011-Q3-1 | K102: =Base_Itens!G79 -> 02 — Balanço de Pagamentos | L102: =COUNTIFS(Base_Itens!$E$5:$E$1504,J102,Base_Itens!$G$5:$G$1504,K102) -> 1
A103: 2011-Q4-1 | B103: 2011 | C103: V/F | D103: 1 | E103: 1 | F103: =SUMIF(Base_Itens!$E$5:$E$1504,A103,Base_Itens!$I$5:$I$1504) -> 1 | G103: =F103-D103 -> 0 | H103: =COUNTIF(Base_Itens!$E$5:$E$1504,A103) -> 1 | I103: =IF(AND(G103=0,H103=E103),"OK","REVER") -> OK | J103: =Base_Itens!E80 -> 2011-Q3-2 | K103: =Base_Itens!G80 -> 02 — Balanço de Pagamentos | L103: =COUNTIFS(Base_Itens!$E$5:$E$1504,J103,Base_Itens!$G$5:$G$1504,K103) -> 1
A104: 2011-Q4-2 | B104: 2011 | C104: V/F | D104: 1 | E104: 1 | F104: =SUMIF(Base_Itens!$E$5:$E$1504,A104,Base_Itens!$I$5:$I$1504) -> 1 | G104: =F104-D104 -> 0 | H104: =COUNTIF(Base_Itens!$E$5:$E$1504,A104) -> 1 | I104: =IF(AND(G104=0,H104=E104),"OK","REVER") -> OK | J104: =Base_Itens!E81 -> 2011-Q3-3 | K104: =Base_Itens!G81 -> 02 — Balanço de Pagamentos | L104: =COUNTIFS(Base_Itens!$E$5:$E$1504,J104,Base_Itens!$G$5:$G$1504,K104) -> 1
... A399: 2015-Q9-4 | B399: 2015 | C399: V/F | D399: 1 | E399: 1 | F399: =SUMIF(Base_Itens!$E$5:$E$1504,A399,Base_Itens!$I$5:$I$1504) -> 1 | G399: =F399-D399 -> 0 | H399: =COUNTIF(Base_Itens!$E$5:$E$1504,A399) -> 1 | I399: =IF(AND(G399=0,H399=E399),"OK","REVER") -> OK | J399: =Base_Itens!E376 -> 2015-Q7-0 | K399: =Base_Itens!G376 -> 09 — Expectativas, Novos Clássicos e Novos Keynesianos | L399: =COUNTIFS(Base_Itens!$E$5:$E$1504,J399,Base_Itens!$G$5:$G$1504,K399) -> 1
...
